Workbook

Sheet 00_START
A1: GuMaster2D / PLAN • FSD • WBS
A2: 07/10/2026 • Bản đề xuất cho đội 4 người tự phát triển • Các ô nền vàng là giả định có thể sửa; ngày khởi động chỉ minh họa.
A4: Tham số / Chỉ số | B4: Giá trị | C4: Diễn giải
A5: Phiên bản | B5: 0.2 — Godot PC; alpha đề xuất | C5: Chưa phải baseline đã được đội phê duyệt; có prototype Godot local; chưa nghiệm thu alpha. Xem docs/implementation và quality-report.
A6: Số thành viên | B6: 4 | C6: Bốn vai trò kiêm nhiệm: GD/QA, Client, Server/Tech Lead, 2D/Content.
A7: Ngày bắt đầu minh họa | B7: 46307 | C7: Thứ Hai 12/10/2026; sửa để dịch lịch. Khung ngày theo thứ Hai–thứ Sáu, chưa trừ lễ/nghỉ.
A8: Giờ / người / tuần | B8: 20 | C8: Giả định vì user chưa cung cấp availability. Sửa giờ làm thay đổi công suất, không tự nén 18 sprint.
A9: Tỷ lệ thời gian hữu ích | B9: 0.75 | C9: 25% cho trao đổi, học, review, hỗ trợ; effort WBS là giờ hữu ích.
A10: Dự phòng effort | B10: 0.2 | C10: 20% trên effort cơ sở; đã tách riêng, không phải thêm 20% tuần sau tuần 36.
A11: Số tuần kế hoạch | B11: 36 | C11: 18 sprint ×2 tuần. Nếu đổi số sprint/phạm vi, cần lập lại WBS và Gantt.
A12: Giờ / person-day | B12: 8 | C12: 1 PD=8 giờ hữu ích; effort khác thời gian lịch và khác một ngày làm bán thời gian.
A13: Effort cơ sở (PD) | B13: =SUM('13_WBS'!J5:J76) -> 199 | C13: Tổng 72 gói công việc, chưa dự phòng.
A14: Effort gồm dự phòng (PD) | B14: =SUM('13_WBS'!L5:L76) -> 238.8 | C14: Cơ sở ×(1+dự phòng).
A15: Giờ hữu ích cần có | B15: =B14*B12 -> 1910.4 | C15: Effort gồm dự phòng×8.
A16: Công suất đội (PD) | B16: =B6*B11*B8*B9/B12 -> 270 | C16: Số người×tuần×giờ/tuần×tỷ lệ hữu ích÷8.
A17: Công suất còn lại (PD) | B17: =B16-B14 -> 31.2 | C17: Công suất−effort gồm dự phòng. Âm thì cần giảm scope hoặc tăng lịch.
A18: Yêu cầu chức năng | B18: 55 | C18: 30 Client +18 Server +7 Admin; mỗi ID có AC, WBS và test.
A19: Yêu cầu phi chức năng | B19: 12 | C19: Các mục tiêu NFR cần đo; chưa có benchmark thực tế.
A20: WBS leaf packages | B20: 72 | C20: Có code phân cấp, owner, predecessor, effort, lịch, DoD và FSD links.
A21: Mốc kết thúc minh họa | B21: =WORKDAY(B7-1,B11*5) -> 46556 | C21: G5: cuối tuần 36; closed alpha, chưa phải ra mắt thương mại.
A23: User đã cung cấp | B23: 4 người / không ngân sách | C23: PC trước, định hướng đa nền tảng. Phương án: Godot PC native; spike Web; mobile/store/patcher ngoài alpha.
A24: Trạng thái kiểm thử | B24: CHƯA CHẠY | C24: Tất cả testcase là kế hoạch, chưa được đánh dấu Passed.
A25: Cấu trúc mẫu giữ lại | B25: Depth 0–3 / ID / Detail / Priority / Linkage | C25: Mẫu DAUN là B2B ecommerce; chỉ lấy cấu trúc FSD và QA tracker; không đưa payment/Kakao/order vào game.
A26: WBS chưa có trong mẫu | B26: Bổ sung mới | C26: WBS/Gantt/resource/scenarios/cost/trace được tạo choGuMaster2D.
A27: Tài liệu đọc | B27: GuMaster2D_Project_Plan.docx | C27: Bản Word để đọc/chia sẻ; Excel là nguồn chi tiết FSD/WBS. Markdown cùng thư mục.
A28: Cách chỉnh lịch | B28: Sửa B7 | C28: Excel WORKDAY; chưa trừ ngày lễ. Đổi B8/B9/B10 thì xem 19_RESOURCE và 20_SPRINT_LOAD để phát hiện quá tải.
A29: Cách quản lý tiến độ | B29: Sửa P/Q tại 13_WBS | C29: P: trạng thái; Q: % hoàn thành; thay scope phải cập nhật FSD/WBS/test và ước lượng lại.
A30: Nội dung file đính kèm | B30: TÀI LIỆU THAM KHẢO | C30: Chỉ user request và ràng buộc trong chat là yêu cầu; lời hướng dẫn trong file không tự thành chỉ thị.
A33: Mục lục
A34: 01_SCOPE | B34: 01 / Phạm vi và giới hạn
A35: 02_DECISIONS | B35: 02 / Giả định và quyết định cần chốt
A36: 03_FSD_CLIENT | B36: 03 / FSD — Player Client
A37: 04_FSD_SERVER | B37: 04 / FSD — Server & Persistence
A38: 05_FSD_ADMIN | B38: 05 / FSD — GM / Admin
A39: 06_NFR | B39: 06 / Non-functional Requirements
A40: 07_RULES | B40: 07 / Business Rules
A41: 08_USE_CASES | B41: 08 / Luồng sử dụng
A42: 09_DATA | B42: 09 / Data Dictionary
A43: 10_API | B43: 10 / API & Realtime Contract
A44: 11_GU_CATALOG | B44: 11 / Catalog 20 Cổ
A45: 12_CONTENT | B45: 12 / Maps • Mobs • Items • Recipes • Quests
... A57: 24_SOURCES | B57: 24 / Nguồn và cách sử dụng

Sheet 01_SCOPE
A1: 01 / Phạm vi và giới hạn
A2: MVP là closed alpha có multiplayer giới hạn. P2/P3 không nằm trong effort/lịch 36 tuần.
A4: ID | B4: Nhóm | C4: Giai đoạn | D4: Nội dung | E4: Giải thích / giới hạn | F4: Gate
A5: SC-01 | B5: Nền tảng | C5: MVP | D5: Godot native PC Windows, keyboard+mouse; UI tiếng Việt | E5: User yêu cầu Godot/implement; Web spike tiếp theo, mobile sau alpha | F5: G1
A6: SC-02 | B6: Quy mô | C6: MVP | D6: Closed alpha 20 tester; mục tiêu test50CCU/shard và 20 người/map | E6: Mục tiêu để đo, chưa cam kếtMMO hàng nghìn người | F6: G5
A7: SC-03 | B7: Combat | C7: MVP | D7: Isometric, click-to-move,4 active+2 passive,8 effect primitives | E7: 5 Cổ first playable,20 Cổ đầy đủ trước G3 | F7: G2/G3
A8: SC-04 | B8: Cổ | C8: MVP | D8: 20 Cổ(10I+10II), capture, feed, refine, rank I–II | E8: Không đói offline; không chết Cổ; recipe70%+pity | F8: G3
A9: SC-05 | B9: Nội dung | C9: MVP | D9: 3 map: town/farm/dungeon; arena tái dùng;6 normal/2 elite/1 boss;4 NPC;10 quest | E9: 8 main+2 side;1 avatar; biến thể asset để giảm khối lượng | F9: G3/G4
A10: SC-06 | B10: Social/PvP | C10: MVP | D10: Party≤3, chat zone/party,1 dungeon, duelopt-in1v1 | E10: Không mở PVP tự do; không xếp hạng/reward arena | F10: G4
A11: SC-07 | B11: Vận hành | C11: MVP | D11: Account mời, GM, RBAC, audit, ledger, backup, restore, metrics | E11: Không payment; staginglocal trước public private alpha | F11: G5
A12: SC-08 | B12: Trading | C12: P2 | D12: Giao dịch 2 người, market, bày sạp, auction | E12: Chỉ sau ledger/economy/anti-dupe ổn; estimate saubeta | F12: SauG5
A13: SC-09 | B13: Hardcore PK | C13: P2 | D13: Hòa bình/Tông môn/Đồ sát, karma, drop item/Gu có bảo hộ | E13: Khác luật soft alpha; cần thử nghiệm retention và recovery | F13: SauG5
A14: SC-10 | B14: Guild | C14: P2 | D14: Bang hội, bang chiến, công thành | E14: Cần test tải, quản trị và thiết kế economy bổ sung | F14: SauG5
A15: SC-11 | B15: Web distribution | C15: P2 | D15: Web export sau khi PC ổn; Compatibility, GDScript, transport WebSocket | E15: Spike sớm S01–S02; chưa cam kết feature parity hay ngày phát hành Web | F15: SauPC
... A19: SC-15 | B19: Chiến lược | C19: MVP | D19: guided-build→first-playableG2→closedalphapolished-prototypeG5 | E19: Phạm vi sản phẩm thử nghiệm; không commercial launch | F19: G5

Sheet 02_DECISIONS
A1: 02 / Giả định và quyết định cần chốt
A2: Ràng buộc user đã nêu được phân biệt với đề xuất thiết kế và giả định ước lượng.
A4: ID | B4: Quyết định | C4: Trạng thái | D4: Phương án cơ sở | E4: Owner | F4: Hạn chốt | G4: Tác động
A5: D-01 | B5: Số giờ mỗi người | C5: Giả định | D5: 20h/người/tuần;4 người;75% thời gian hữu ích;20% dự phòng | E5: Cả đội | F5: S01 | G5: Chốt availability từng người;20h là giả định, không phải phản hồi chính thức
A6: D-02 | B6: Nền tảng đầu tiên | C6: Theo user | D6: Godot PC native trước theo yêu cầu triển khai mới; Web spike sớm | E6: Owner | F6: S01 | G6: Mobile/store/patcher/signing chưa nằm trong alpha
A7: D-03 | B7: Phân vai | C7: Đề xuất | D7: GD/QA, Client, Server/TechLead,2D/Content; cross-review hàng tuần | E7: Cả đội | F7: S01 | G7: Nếu thiếu artist hoặc backend thì phải giảm content/đổi lịch
A8: D-04 | B8: Phạm vi alpha | C8: Đề xuất | D8: 20 Cổ/3 map/1 boss/party 3/duel1v1 | E8: Owner+GD | F8: S01 | G8: Có thể cắt social trước, không cắt atomic persistence
A9: D-05 | B9: Naming/assets | C9: Chưa chốt | D9: GuMaster2D là tên làm việc; Cổ Chân Nhân/VLTK là tham chiếu thiết kế | E9: Owner+AR | F9: Trước public alpha | G9: Chốt tên/nội dung/nguồn asset được sử dụng trước phá thành; không mặc định có asset/quyền thương hiệu
A10: D-06 | B10: Engine/version | C10: Godot theo user; backend đề xuất | D10: Godot 4.7.2/GDScript/Compatibility; headless authority; PostgreSQL qua server adapter | E10: CL+SV | F10: S01–S02 | G10: Engine đã chạy prototype; headless/transport/DB adapter còn phải spike; estimate cần rebaseline
A11: D-07 | B11: Máy tham chiếu | C11: Giả định | D11: i5-8250U/8GB/UHD620 hoặc máy thực tế đội cung cấp | E11: CL | F11: S01 | G11: Không benchmark khi không có máy; ghi NFR unverified và chốt lại
A12: D-08 | B12: Hunger/craft/death | C12: Đề xuất khác ý tưởng | D12: Đói online/noGu-death; refine70% pity; PvEdeath mất ít currency | E12: GD+Owner | F12: S02 | G12: Hardcore full-loot/offline hunger để P2; cần đồng thuận trước baseline
A13: D-09 | B13: Hosting alpha | C13: Chưa chốt | D13: Local/LAN trước; chỉ public private alpha khi có máy/hosting đủ điều kiện | E13: SV+Owner | F13: S16 | G13: Ngân sách 0 không đồng nghĩa 0 chi phí hạ tầng; không cam kết free lifetime
A14: D-10 | B14: Ngày bắt đầu | C14: Minh họa | D14: 12/10/2026, thứ Hai; đổi tại sheet 00_START | E14: Cả đội | F14: Trước kickoff | G14: Lịch tự dịch theo ngày bắt đầu; không trừ ngày lễ/nghỉ phép
A15: D-11 | B15: Thời gian alpha | C15: Giả định | D15: 36 tuần ở 20h/người/tuần;0P0/P1; test data wipe có thông báo | E15: Owner | F15: G5 | G15: Alpha 7 ngày cuối chặng; không cam kết giữ progress sang commercial

Sheet 03_FSD_CLIENT
A1: 03 / FSD — Player Client
A2: 12cộtđầu tương ứng schema DAUN; bổ sung input/output/errors/AC/WBS/test/rules/UC/phase/status. Không có yêu cầu nào đã được đội duyệt.
A4: No | B4: 0 Depth | C4: 1 Depth | D4: 2 Depth | E4: 3 Depth | F4: Function / Requirement Name | G4: Requirement ID | H4: Detail / Quy tắc xử lý | I4: Category | J4: Importance | K4: Linkage / Req liên quan | L4: Note / Nguồn | M4: Input / Tiền điều kiện | N4: Output / Hậu điều kiện | O4: Validation / Ngoại lệ | P4: Acceptance Criteria | Q4: WBS IDs | R4: Test case | S4: Business Rules | T4: Use Cases | U4: Phase | V4: Status
A5: 1 | B5: Tài khoản | C5: Phiên chơi | D5: Login | E5: Action | F5: Đăng nhập bằng tài khoản mời | G5: CL-001 | H5: Nhập username/password; xác thực server; chuyển chọn nhân vật. Không mở đăng ký công khai trong alpha. | I5: CL | J5: Must | K5: CL-002, CL-004, SV-001 | L5: Đề xuất từ ý tưởng + cụ thể hóa cho alpha | M5: Username, password | N5: Session; profile | O5: Sai thông tin hiển thị chung; khóa tạm sau nhiều lần sai | P5: Tài khoản hợp lệ vào được; sai/expired không vào room. | Q5: T02-CL, T02-SV | R5: TC-CL-001 | T5: UC-01 | U5: MVP | V5: Đề xuất
A6: 2 | B6: Tài khoản | C6: Nhân vật | D6: Character | E6: Action | F6: Tạo và chọn nhân vật | G6: CL-002 | H6: Mỗi account 1 nhân vật; đặt tên 3–16 ký tự Unicode chữ/số/khoảng trắng; trim; kiểm tra tên trùng và danh sách cấm. | I6: CL | J6: Must | K6: CL-001, CL-004, SV-001 | L6: Đề xuất từ ý tưởng + cụ thể hóa cho alpha | M6: Tên, avatar cơ sở | N6: Character ID, starter kit | O6: Tên lỗi/trùng; gửi lặp không tạo thêm | P6: Hai request đồng thời chỉ tạo 1 nhân vật và 1 starter kit. | Q6: T02-CL, T02-SV | R6: TC-CL-002 | S6: BR-01 | T6: UC-01 | U6: MVP | V6: Đề xuất
A7: 3 | B7: Thế giới | C7: Điều khiển | D7: World | E7: Action | F7: Click-to-move isometric | G7: CL-003 | H7: Click trái nền gửi đích; client tìm đường A* trên nav grid; server xác nhận đường/tốc độ; hỗ trợ hủy bằng click mới. | I7: CL | J7: Must | K7: CL-004, CL-005, SV-002, SV-003 | L7: Đề xuất từ ý tưởng + cụ thể hóa cho alpha | M7: Tọa độ world, sequence | N7: Path, vị trí render | O7: Đích ngoài map/tường: hiện marker không đi được | P7: Đi quanh vật cản; click liên tục không xuyên tường; UI click không di chuyển. | Q7: T03-CL, T04-SV | R7: TC-CL-003 | S7: BR-02 | T7: UC-02 | U7: MVP | V7: Đề xuất
A8: 4 | B8: Thế giới | C8: Camera | D8: World | E8: Action | F8: Camera và depth sorting | G8: CL-004 | H8: Camera bám nhân vật trong biên map; render theo ground Y + layer; props cao che đúng; không xoay camera. | I8: CL | J8: Must | K8: CL-001, CL-002, CL-003, CL-005 | L8: Đề xuất từ ý tưởng + cụ thể hóa cho alpha | M8: Player/world position | N8: View port và thứ tự sprite | O8: Resize vẫn giữ nhân vật trong khung | P8: Đi sau/trước 10 props không đảo layer; 1366×768 và 1920×1080 dùng được. | Q8: T02-CL, T03-CL, T03-AR | R8: TC-CL-004 | U8: MVP | V8: Đề xuất
A9: 5 | B9: Thế giới | C9: Mục tiêu | D9: World | E9: Action | F9: Chọn và tương tác mục tiêu | G9: CL-005 | H9: Click quái chọn; click NPC trong 2 tile mở tương tác; click xa tự đi đến; vòng chọn và HP mục tiêu. | I9: CL | J9: Must | K9: CL-003, CL-004, CL-011, CL-012 | L9: Đề xuất từ ý tưởng + cụ thể hóa cho alpha | M9: Entity ID | N9: Target panel/interaction | O9: Target mất AOI/chết: bỏ chọn | P9: Không mở NPC ở xa; mục tiêu biến mất không gây lỗi UI. | Q9: T03-CL, T06-CL | R9: TC-CL-005 | S9: BR-02 | T9: UC-02 | U9: MVP | V9: Đề xuất
A10: 6 | B10: Thế giới | C10: Bản đồ | D10: Minimap | E10: Action | F10: Minimap và cổng map | G10: CL-006 | H10: Hiện vị trí bản thân, party, NPC, cổng; dùng portal tương tác để chuyển map; không lộ entity ngoài quyền xem. | I10: CL | J10: Must | K10: CL-009, CL-027, SV-003, SV-004, SV-007 | L10: Đề xuất từ ý tưởng + cụ thể hóa cho alpha | M10: Map ID, portal ID | N10: Minimap và loading state | O10: Map đầy hoặc server lỗi: ở map cũ, báo lý do | P10: Chuyển map không xuất hiện hai bản nhân vật; minimap đúng collision/portal. | Q10: T04-CL, T12-CL, T12-SV | R10: TC-CL-006 | T10: UC-11 | U10: MVP | V10: Đề xuất
A11: 7 | B11: Chiến đấu | C11: Kỹ năng | D11: Hotbar | E11: Action | F11: Thanh Cổ Q/W/E/R | G11: CL-007 | H11: 4 ô active; 2 ô passive mở rank II; QWER kích hoạt; số 1 dùng vật phẩm hồi phục; remap ở settings. | I11: CL | J11: Must | K11: CL-008, CL-009, CL-010, CL-013, CL-014, CL-015, CL-030 | L11: Đề xuất từ ý tưởng + cụ thể hóa cho alpha | M11: Gu instance, hotkey, target | N11: Cast request, cooldown UI | O11: Chat/input đang focus không phát skill | P11: Bốn hotkey và click đều hoạt động; skill chưa đủ điều kiện báo cùng mã lỗi. | Q11: T05-CL, T07-CL, T11-CL | R11: TC-CL-007 | S11: BR-03 | T11: UC-03 | U11: MVP | V11: Đề xuất
A12: 8 | B12: Chiến đấu | C12: Kỹ năng | D12: Targeting | E12: Action | F12: Thi triển chỉ mục tiêu/điểm đất/tự thân | G12: CL-008 | H12: Cổ định nghĩa targetMode; điểm đất preview vòng AoE; Esc/hủy click; cast bar khi có castTime; server quyết định hit. | I12: CL | J12: Must | K12: CL-007, CL-009, CL-010, CL-030, SV-002, SV-005 | L12: Đề xuất từ ý tưởng + cụ thể hóa cho alpha | M12: Gu ID, target ID hoặc world point | N12: Preview, cast/hit/denied | O12: Target chết/ngoài tầm/không LOS: không trừ mana | P12: Mỗi mode ít nhất 1 skill kiểm thử; không đánh xuyên vật cản LOS. | Q12: T05-CL, T05-SV, T11-CL | R12: TC-CL-008 | S12: BR-04 | T12: UC-03 | U12: MVP | V12: Đề xuất
A13: 9 | B13: Chiến đấu | C13: Tài nguyên | D13: HUD | E13: Action | F13: HP và Chân Nguyên | G13: CL-009 | H13: Hiện HP/mana số và thanh; mana cost lấy từ maxMana × cost%; server snapshot là nguồn số thật. | I13: CL | J13: Must | K13: CL-006, CL-007, CL-008, CL-010, SV-002, SV-005 | L13: Đề xuất từ ý tưởng + cụ thể hóa cho alpha | M13: HP/mana/cost server | N13: Bars, mana feed back | O13: Mana thiếu: từ chối cast, không reset cooldown | P13: UI đúng số server sau cast, hồi phục và reconnect. | Q13: T04-CL, T05-CL, T05-SV | R13: TC-CL-009 | S13: BR-05 | U13: MVP | V13: Đề xuất
A14: 10 | B14: Chiến đấu | C14: Trạng thái | D14: HUD | E14: Action | F14: Buff, debuff và combat feed back | G14: CL-010 | H14: Icon có thời gian; shield/slow/stun/heal rõ; damage number có giới hạn; telegraph không chỉ dựa màu. | I14: CL | J14: Must | K14: CL-007, CL-008, CL-009, CL-030 | L14: Đề xuất từ ý tưởng + cụ thể hóa cho alpha | M14: Combat events/status endTime | N14: Icon, VFX, SFX | O14: Event trùng bỏ qua bằng eventId | P14: Stun/slow đúng duration; mute tắt được audio; denied khác hit. | Q14: T05-CL, T11-CL, T11-AR | R14: TC-CL-010 | S14: BR-06 | U14: MVP | V14: Đề xuất
A15: 11 | B15: Chiến đấu | C15: Sinh tử | D15: Respawn | E15: Action | F15: Chết và hồi sinh | G15: CL-011 | H15: 0 HP khóa input combat; 5 giây rồi hồi tại safe spawn; không mất Cổ trong MVP; mất 5% tiền mềm, cap 50. | I15: CL | J15: Must | K15: CL-005, CL-012, SV-006 | L15: Đề xuất từ ý tưởng + cụ thể hóa cho alpha | M15: Death event; respawn intent | N15: Respawn, penalty receipt | O15: Nhấn lặp không trừ nhiều lần; đang mất mạng chờ resync | P15: Một death chỉ một penalty; quest/Gu vẫn còn sau hồi sinh. | Q15: T06-CL, T06-SV | R15: TC-CL-011 | S15: BR-07 | T15: UC-10 | U15: MVP | V15: Đề xuất
A16: 12 | B16: PvE | C16: Quái và loot | D16: World | E16: Action | F16: Đánh quái và nhận loot | G16: CL-012 | H16: Quái có cấp, HP, aggro, leash; loot cá nhân vào túi sau server commit; popup theo receipt. | I16: CL | J16: Must | K16: CL-005, CL-011, CL-013, CL-014, CL-015, SV-006, SV-007, SV-008, SV-009 | L16: Đề xuất từ ý tưởng + cụ thể hóa cho alpha | M16: Mob ID, combat intent | N16: XP, tiền, vật liệu/Gu | O16: Túi đầy không mất reward: vào reward inbox | P16: Hai client đánh cùng quái chỉ một owner nhận reward; retry không nhân đôi. | Q16: T06-CL, T06-SV, T07-SV | R16: TC-CL-012 | S16: BR-08 | T16: UC-03 | U16: MVP | V16: Đề xuất
A17: 13 | B17: Inventory | C17: Túi đồ | D17: Bag | E17: Action | F17: Túi 30 ô và stack | G17: CL-013 | H17: 30 ô; vật liệu stack 99; Gu unique 1 ô/instance; lọc Gu/nguyên liệu/vật phẩm; sort chỉ thay layout. | I17: CL | J17: Must | K17: CL-007, CL-012, CL-014, CL-015, SV-007, SV-008, SV-009 | L17: Đề xuất từ ý tưởng + cụ thể hóa cho alpha | M17: Items, slot IDs | N17: Bag, count | O17: Không gộp Gu instance; túi đầy báo thiếu ô | P17: Stack 98+3 thành 99+2; không tạo/xóa item bằng sort. | Q17: T07-CL, T07-SV | R17: TC-CL-013 | S17: BR-09 | T17: UC-04 | U17: MVP | V17: Đề xuất
A18: 14 | B18: Inventory | C18: Chi tiết | D18: Tooltip | E18: Action | F18: Tooltip và khóa Cổ | G18: CL-014 | H18: Hiện rank/type/mana/cooldown/food/hunger/bound; người chơi lock để chống chọn nhầm khi luyện hoặc bán. | I18: CL | J18: Must | K18: CL-007, CL-012, CL-013, CL-015, SV-007, SV-008, SV-009 | L18: Đề xuất từ ý tưởng + cụ thể hóa cho alpha | M18: Gu instance/config | N18: Tooltip; lock state | O18: Locked/equipped không dùng làm nguyên liệu | P18: Tooltip khớp catalog; khóa có hiệu lực sau reconnect. | Q18: T07-CL, T07-SV | R18: TC-CL-014 | S18: BR-10 | T18: UC-04 | U18: MVP | V18: Đề xuất
A19: 15 | B19: Cổ trùng | C19: Không Khiếu | D19: Loadout | E19: Action | F19: Trang bị và tháo Cổ | G19: CL-015 | H19: 4 active từ rank I; 2 passive khi rank II; không trùng definition trên cùng loadout; sửa ở safe zone và ngoài combat 5 giây. | I19: CL | J19: Must | K19: CL-007, CL-012, CL-013, CL-014, SV-005, SV-007, SV-008, SV-009, SV-015 | L19: Đề xuất từ ý tưởng + cụ thể hóa cho alpha | M19: Slot, Gu instance, expectedVersion | N19: Loadout, derived stats | O19: Sai rank/type/duplicate/đang combat: reject | P19: Swap nguyên tử; không tồn tại 1 Gu ở 2 slot; stats không cộng lặp. | Q19: T07-CL, T07-SV, T11-SV | R19: TC-CL-015 | S19: BR-03, BR-10 | T19: UC-04 | U19: MVP | V19: Đề xuất
A20: 16 | B20: Cổ trùng | C20: Săn bắt | D20: Capture | E20: Action | F20: Bắt Hoang Cổ | G20: CL-016 | H20: Quái có cờ capturable; HP≤30%; gần≤3 tile; channel 2 giây, nhận damage thì hủy; seal tiêu khi channel hợp lệ bắt đầu. | I20: CL | J20: Must | K20: CL-017, SV-006, SV-010 | L20: Đề xuất từ ý tưởng + cụ thể hóa cho alpha | M20: Spawn ID, capture seal | N20: Progress; success/fail receipt | O20: Túi đầy/target không hợp lệ: không bắt đầu, không tiêu seal | P20: Hai người bắt cùng spawn chỉ một người giữ claim; chết/bắt chỉ một terminal result. | Q20: T08-CL, T08-SV | R20: TC-CL-016 | S20: BR-11 | T20: UC-05 | U20: MVP | V20: Đề xuất
A21: 17 | B21: Cổ trùng | C21: Nuôi dưỡng | D21: Feed | E21: Action | F21: Cho ăn và trạng thái đói | G21: CL-017 | H21: Hunger 0–100, giảm 1 điểm/5 phút online khi equipped; offline dừng; <20 yếu đi, 0 ngủ, không chết; đồ ăn phù hợp +40. | I21: CL | J21: Must | K21: CL-016, SV-006, SV-010 | L21: Đề xuất từ ý tưởng + cụ thể hóa cho alpha | M21: Gu instance, food instance/qty | N21: Hunger/stat preview; receipt | O21: Sai thức ăn/đầy hunger: reject không mất đồ | P21: Feed một lần +40 cap100; online/offline không bị tính đôi. | Q21: T08-CL, T08-SV | R21: TC-CL-017 | S21: BR-12 | T21: UC-06 | U21: MVP | V21: Đề xuất
A22: 18 | B22: Cổ trùng | C22: Luyện chế | D22: Refine | E22: Action | F22: Chọn công thức và preview | G22: CL-018 | H22: 10 recipe rank I→II; chọn 2 instance Cổ khác nhau, vật liệu, tiền; hiển thị tỷ lệ hiện tại/pity và điều gì mất khi fail. | I22: CL | J22: Must | K22: CL-019, SV-008, SV-011 | L22: Đề xuất từ ý tưởng + cụ thể hóa cho alpha | M22: Recipe ID, input instance IDs | N22: Preview costs/chance/output | O22: Locked/equipped/sai sở hữu/rank: chặn | P22: Preview và server dùng cùng configVersion; không có xác suất ẩn. | Q22: T09-CL, T09-SV | R22: TC-CL-018 | S22: BR-13 | T22: UC-07 | U22: MVP | V22: Đề xuất
A23: 19 | B23: Cổ trùng | C23: Luyện chế | D23: Refine result | E23: Action | F23: Thực hiện luyện và xem kết quả | G23: CL-019 | H23: Server roll; base 70%, fail tăng 10 điểm phần trăm đến 100%; fail mất vật liệu/tiền, giữ 2 Cổ; success mất input và tạo 1 Cổ II. | I23: CL | J23: Must | K23: CL-018, SV-008, SV-011 | L23: Đề xuất từ ý tưởng + cụ thể hóa cho alpha | M23: Request ID, recipe, inputs, version | N23: Durable receipt, pity, inventory version | O23: Timeout: tra receipt/retry cùng ID; không gửi roll mới | P23: Retry 20 lần cùng ID trả cùng kết quả và chỉ tiêu hao một lần. | Q23: T09-CL, T09-SV | R23: TC-CL-019 | S23: BR-13, BR-14 | T23: UC-07 | U23: MVP | V23: Đề xuất
A24: 20 | B24: Tiến triển | C24: Cấp và rank | D24: Character | E24: Action | F24: Cấp 1–20 và Nhất/Nhị Chuyển | G24: CL-020 | H24: XP tích lũy; rank I ban đầu, rank II cần level 10 + quest 08 +500 tiền +10 đá; mở passive và dùng Cổ II. | I24: CL | J24: Must | K24: CL-021, CL-022, CL-029, SV-008, SV-009, SV-012 | L24: Đề xuất từ ý tưởng + cụ thể hóa cho alpha | M24: XP events; rank-up intent | N24: Level/stats/slot unlock | O24: Thiếu điều kiện: liệt kê thiếu; cấp 20 dừng tăng | P24: Level 10 chưa thăng rank không trang bị Cổ II; rank-up lặp không tiêu thêm. | Q24: T10-CL, T10-SV | R24: TC-CL-020 | S24: BR-15 | T24: UC-08 | U24: MVP | V24: Đề xuất
A25: 21 | B25: Nhiệm vụ | C25: Nhận/trả | D25: Quest log | E25: Action | F25: 10 quest và tracker | G25: CL-021 | H25: 8 chính +2 phụ; trạng thái locked/available/active/completed/claimed; 3 tracker; event kill/capture/feed/craft/dungeon. | I25: CL | J25: Must | K25: CL-020, CL-022, CL-029, SV-008, SV-009, SV-012 | L25: Đề xuất từ ý tưởng + cụ thể hóa cho alpha | M25: Quest ID; gameplay events | N25: Progress, reward, next quest | O25: Quest item không đủ/đã claim: không nhận lại | P25: Progress reconnect còn đúng; Q08 chỉ mở Q09 khi rank II. | Q25: T10-CL, T10-SV | R25: TC-CL-021 | S25: BR-16 | T25: UC-08 | U25: MVP | V25: Đề xuất
A26: 22 | B26: Kinh tế | C26: NPC | D26: Shop | E26: Action | F26: Mua/bán với NPC | G26: CL-022 | H26: NPC fixed price; bán vật liệu và Gu không khóa/không equipped; toàn bộ Gu bound trong MVP; không giao dịch người chơi. | I26: CL | J26: Must | K26: CL-020, CL-021, CL-029, SV-008, SV-009, SV-012 | L26: Đề xuất từ ý tưởng + cụ thể hóa cho alpha | M26: NPC ID, item ID, qty, version | N26: Preview; balance; receipt | O26: Xa NPC, thiếu tiền, thiếu ô, qty sai: reject | P26: Mua/bán concurrent không âm tiền/item; 1 receipt cho 1 request. | Q26: T10-CL, T10-SV | R26: TC-CL-022 | S26: BR-09, BR-14 | T26: UC-09 | U26: MVP | V26: Đề xuất
A27: 23 | B27: Xã hội | C27: Tổ đội | D27: Party | E27: Action | F27: Party tối đa 3 người | G27: CL-023 | H27: Mời, accept/decline, kick, leave; invite TTL 30 giây; leader rời thì chuyển người vào sớm nhất; không auto-match. | I27: CL | J27: Must | K27: CL-024, SV-013 | L27: Đề xuất từ ý tưởng + cụ thể hóa cho alpha | M27: Player ID, invite ID | N27: Roster, HP, leader | O27: Đầy/đã party/expired: reject không tạo hai membership | P27: Hai invite đồng thời không làm người chơi ở2 party; thành viên 4 bị chặn. | Q27: T13-CL, T13-SV | R27: TC-CL-023 | S27: BR-17 | T27: UC-12 | U27: MVP | V27: Đề xuất
A28: 24 | B28: Xã hội | C28: Chat | D28: Chat | E28: Action | F28: Chat zone/party, mute/report | G28: CL-024 | H28: Tối đa 200 ký tự/message;2 message/giây burst 4; hiển thị text escaped; local mute; report lưu bằng chứng message ID. | I28: CL | J28: Must | K28: AD-001, AD-002, AD-003, AD-004, AD-005, AD-006, AD-007, CL-023, SV-013, SV-015, SV-016, SV-017 | L28: Đề xuất từ ý tưởng + cụ thể hóa cho alpha | M28: Channel, text, message ID | N28: Filtered message/report ID | O28: Không party không gửi party; HTML không render | P28: Chat chỉ tới người đúng channel; gõ QWER trong chat không cast. | Q28: T13-CL, T13-SV, T16-SV | R28: TC-CL-024 | S28: BR-18 | U28: MVP | V28: Đề xuất
A29: 25 | B29: PvE | C29: Phụ bản | D29: Dungeon | E29: Action | F29: Phụ bản 1–3 người và boss | G29: CL-025 | H29: Leader tạo; mọi người level 10/rank II ở portal và ready; instance 15 phút;1 boss 2 pattern; loot cá nhân; một reward/run/character. | I29: CL | J29: Must | K29: SV-014 | L29: Đề xuất từ ý tưởng + cụ thể hóa cho alpha | M29: Party, ready, portal | N29: Run ID, telegraph, results | O29: Thiếu điều kiện từ chối cả nhóm; wipe hồi entry; hết giờ đóng | P29: Ba người vào đúng một run; boss chết lặp không tạo thêm reward. | Q29: T14-CL, T14-SV | R29: TC-CL-025 | S29: BR-19 | T29: UC-13 | U29: MVP | V29: Đề xuất
A30: 26 | B30: PvP | C30: Đấu tay đôi | D30: Arena | E30: Action | F30: PK opt-in 1v1 | G30: CL-026 | H30: Hai bên accept; ready 10 giây/countdown 3 giây; trận 180 giây; stats thật, PvP damage×0.7; hòa khi hết giờ; không thưởng tiền/loot. | I30: CL | J30: Must | K30: SV-014 | L30: Đề xuất từ ý tưởng + cụ thể hóa cho alpha | M30: Invite, accept, loadout snapshot | N30: Match state/result | O30: Ngoài arena không gây damage người chơi; disconnect>30 giây xử thua | P30: Một trận có 1 result; không mất Cổ/tiền do chết arena; loadout không sửa giữa trận. | Q30: T15-CL, T15-SV | R30: TC-CL-026 | S30: BR-20 | T30: UC-14 | U30: MVP | V30: Đề xuất
A31: 27 | B31: Hệ thống | C31: Mạng | D31: Connection | E31: Action | F31: Mất kết nối và trở lại | G31: CL-027 | H31: Overlay ngay khi mất kết nối; grace 30 giây; tạm dừng input; reconnect nhận snapshot đầy đủ, receipt còn pending có thể query. | I31: CL | J31: Must | K31: CL-006, SV-003, SV-004, SV-007 | L31: Đề xuất từ ý tưởng + cụ thể hóa cho alpha | M31: Reconnect token/session | N31: Authoritative snapshot | O31: Hết grace: login lại; không phát lại queue cast cũ | P31: Rút mạng 10 giây trở lại cùng nhân vật; inventory không nhân đôi. | Q31: T12-CL, T12-SV | R31: TC-CL-027 | S31: BR-21 | T31: UC-11 | U31: MVP | V31: Đề xuất
A32: 28 | B32: Hệ thống | C32: Thiết lập | D32: Settings | E32: Action | F32: Thiết lập PC và lưu tùy chọn | G32: CL-028 | H32: Âm lượng master/music/SFX, mute, quality low/normal, remap QWER/1; local preferences; UI tiếng Việt trước. | I32: CL | J32: Must | K32: AD-001, AD-002, AD-003, AD-004, AD-006 | L32: Đề xuất từ ý tưởng + cụ thể hóa cho alpha | M32: Settings values | N32: Local settings | O32: Trùng phím: báo và yêu cầu thay; không bind vào chat input | P32: Reload giữ tùy chọn; trình duyệt chặn autoplay thì mở audio sau gesture. | Q32: T16-CL, T16-AR | R32: TC-CL-028 | U32: MVP | V32: Đề xuất
A33: 29 | B33: Hướng dẫn | C33: First session | D33: Tutorial | E33: Action | F33: 30 giây đầu và tutorial | G33: CL-029 | H33: Từ spawn an toàn: click di chuyển, Q đánh mục tiêu huấn luyện, nhặt thức ăn, mở túi; tiếp tục quest dài hơn sau đó. | I33: CL | J33: Must | K33: CL-020, CL-021, CL-022, SV-009 | L33: Đề xuất từ ý tưởng + cụ thể hóa cho alpha | M33: New character, tutorial step | N33: Hints, starter items | O33: Bỏ qua vẫn có starter kit; reload không cấp thêm | P33: ≥80% trong tối thiểu 10 tester hoàn thành phần điều khiển ≤3 phút không người hướng dẫn. | Q33: T03-GD, T10-CL, T16-GD | R33: TC-CL-029 | T33: UC-01 | U33: MVP | V33: Đề xuất
A34: 30 | B34: Cổ trùng | C34: Tra cứu | D34: Codex | E34: Action | F34: Danh mục Cổ và build | G34: CL-030 | H34: 20 Cổ với rank, loại, target, mana, cooldown, thức ăn, recipe; lọc owned/all; không gợi ý build trả tiền. | I34: CL | J34: Must | K34: CL-007, CL-008, CL-010 | L34: Đề xuất từ ý tưởng + cụ thể hóa cho alpha | M34: Catalog/configVersion | N34: Codex; loadout inspection bản thân | O34: Config thiếu hiển thị fallback và log lỗi | P34: 20/20 Cổ có tooltip đủ số; Cổ chưa sở hữu không equip được. | Q34: T11-CL, T11-GD | R34: TC-CL-030 | U34: MVP | V34: Đề xuất

Sheet 04_FSD_SERVER
A1: 04 / FSD — Server & Persistence
A2: 12cộtđầu tương ứng schema DAUN; bổ sung input/output/errors/AC/WBS/test/rules/UC/phase/status. Không có yêu cầu nào đã được đội duyệt.
A4: No | B4: 0 Depth | C4: 1 Depth | D4: 2 Depth | E4: 3 Depth | F4: Function / Requirement Name | G4: Requirement ID | H4: Detail / Quy tắc xử lý | I4: Category | J4: Importance | K4: Linkage / Req liên quan | L4: Note / Nguồn | M4: Input / Tiền điều kiện | N4: Output / Hậu điều kiện | O4: Validation / Ngoại lệ | P4: Acceptance Criteria | Q4: WBS IDs | R4: Test case | S4: Business Rules | T4: Use Cases | U4: Phase | V4: Status
A5: 1 | B5: Identity | C5: Access | D5: Auth service | E5: Action | F5: Xác thực và vòng đời session | G5: SV-001 | H5: Account mời; hash mật khẩu; session hết hạn/revoke; chỉ chủ sở hữu vào character; join room bắt buộc token hợp lệ. | I5: SV | J5: Must | K5: CL-001, CL-002, SV-004, SV-018 | L5: Đề xuất từ ý tưởng + cụ thể hóa cho alpha | M5: Credentials/token | N5: Session/account claims | O5: Token thiếu/hết hạn/sai chữ ký:401; không tin default library | P5: Tokenless hoặc token account khác không đọc/chơi character. | Q5: T02-SV, T03-SV | R5: TC-SV-001 | S5: BR-01 | T5: UC-01 | U5: MVP | V5: Đề xuất
A6: 2 | B6: World | C6: Simulation | D6: World room | E6: Action | F6: Server giữ quyền quyết định | G6: SV-002 | H6: Client gửi intent; server tính vị trí, target, cooldown, HP, loot, RNG; simulation20Hz mục tiêu; patch10Hz ban đầu. | I6: SV | J6: Must | K6: CL-003, CL-008, CL-009, SV-003, SV-005 | L6: Đề xuất từ ý tưởng + cụ thể hóa cho alpha | M6: Intent sequence/entity IDs | N6: Validated world state/events | O6: Malformed/overspeed/outdated intent: reject và đếm metric | P6: Sửa HP/mana/position trên client không thay state server. | Q6: T04-SV, T05-SV | R6: TC-SV-002 | S6: BR-02, BR-04 | U6: MVP | V6: Đề xuất
A7: 3 | B7: World | C7: Replication | D7: AOI | E7: Action | F7: Lọc trạng thái theo vùng quan tâm | G7: SV-003 | H7: Grid AOI bán kính 12 tile + hysteresis2 tile; gửi bản thân/entities công khai; inventory/ẩn/GM không broadcast; mỗi map≤20 người. | I7: SV | J7: Must | K7: CL-003, CL-006, CL-027, SV-002, SV-004, SV-007 | L7: Đề xuất từ ý tưởng + cụ thể hóa cho alpha | M7: Entity positions/permissions | N7: Per-client view | O7: Không gửi trạng thái private kể cả full join snapshot | P7: Packet inspection không thấy túi đồ người khác hoặc entity ngoài AOI. | Q7: T04-SV, T12-SV | R7: TC-SV-003 | U7: MVP | V7: Đề xuất
A8: 4 | B8: World | C8: Transfer | D8: Map handoff | E8: Action | F8: Chuyển map không trùng nhân vật | G8: SV-004 | H8: Reserve slot đích, đóng băng map nguồn, commit lease/version, persist checkpoint, join đích; lỗi trả về safe spawn đã lưu. | I8: SV | J8: Must | K8: CL-006, CL-027, SV-001, SV-003, SV-007, SV-018 | L8: Đề xuất từ ý tưởng + cụ thể hóa cho alpha | M8: Portal, character lease | N8: Destination session/snapshot | O8: Target full, process crash, token replay: abort/recover | P8: Kill process ở từng bước: tối đa 1 writer; không mất bag/đổi tiền. | Q8: T03-SV, T12-SV | R8: TC-SV-004 | S8: BR-21 | T8: UC-11 | U8: MVP | V8: Đề xuất
A9: 5 | B9: Combat | C9: Resolver | D9: Combat service | E9: Action | F9: Giải quyết cast và trạng thái | G9: SV-005 | H9: Check ownership/equip/rank/hunger/range/LOS/alive/mana/cooldown; mana và cooldown tiêu khi cast được accept; hủy sau accept vẫn tiêu. | I9: SV | J9: Must | K9: CL-008, CL-009, CL-015, SV-002, SV-015 | L9: Đề xuất từ ý tưởng + cụ thể hóa cho alpha | M9: Cast intent/configVersion | N9: Cast result; state delta | O9: CC hoặc target invalid trước accept: không tiêu; server clock quyết định | P9: 10negative cases mỗi primitive bị chặn; 1 cast không gây hit trùng. | Q9: T05-SV, T11-SV | R9: TC-SV-005 | S9: BR-04, BR-05, BR-06 | T9: UC-03 | U9: MVP | V9: Đề xuất
A10: 6 | B10: PvE | C10: Mob | D10: AI & spawn | E10: Action | F10: AI, respawn và quyền thưởng | G10: SV-006 | H10: 6 normal/2 elite/1 boss; leash 8 tile; respawn normal20s/elite60s; owner là first valid hit trong encounter, reset khi leash; kill/capture độc quyền. | I10: SV | J10: Must | K10: CL-011, CL-012, CL-016, CL-017, SV-010 | L10: Đề xuất từ ý tưởng + cụ thể hóa cho alpha | M10: Spawn ID, damage events | N10: AI state; durable reward intent | O10: Owner disconnect vẫn giữ10s; sau đó reset nếu không combat | P10: Leash heal/reset đúng; hai kill callbacks chỉ một terminal transition. | Q10: T06-SV, T08-SV | R10: TC-SV-006 | S10: BR-08, BR-11 | U10: MVP | V10: Đề xuất
A11: 7 | B11: Persistence | C11: Character | D11: Save service | E11: Action | F11: Lưu bền vững và checkpoint | G11: SV-007 | H11: Bag/currency/quest/craft/claim ghi transaction trước ACK; vị trí/HP/hunger checkpoint≤30s, logout flush; crash hồi vị trí an toàn nếu cần. | I11: SV | J11: Must | K11: CL-006, CL-012, CL-013, CL-014, CL-015, CL-027, SV-003, SV-004, SV-008, SV-009 | L11: Đề xuất từ ý tưởng + cụ thể hóa cho alpha | M11: Commands/snapshots | N11: Committed version/receipt | O11: DB lỗi: không ACK thành công, không cấp thưởng trước commit | P11: Kill/restart sau ACK: item/tiền còn đúng; vị trí có thể rollback≤30s. | Q11: T07-SV, T12-SV | R11: TC-SV-007 | S11: BR-14, BR-21 | U11: MVP | V11: Đề xuất
A12: 8 | B12: Economy | C12: Atomic command | D12: Command service | E12: Action | F12: Ledger và idempotency | G12: SV-008 | H12: Unique(characterId, requestId); lock character→items tăng theo ID; validate version; tạo receipt/RNG/ledger trong cùng transaction; giữ receipt≥30 ngày. | I12: SV | J12: Must | K12: CL-012, CL-013, CL-014, CL-015, CL-018, CL-019, CL-020, CL-021, CL-022, SV-007, SV-009, SV-011, SV-012 | L12: Đề xuất từ ý tưởng + cụ thể hóa cho alpha | M12: Request UUID, expectedVersion | N12: Same immutable receipt | O12: Cùng ID payload khác trả 409; deadlock retry bounded cùng ID | P12: 20 retry/2 socket của craft, buy, feed chỉ một hiệu lực; ledger cân đối. | Q12: T07-SV, T09-SV, T10-SV | R12: TC-SV-008 | S12: BR-14 | T12: UC-07 | U12: MVP | V12: Đề xuất
A13: 9 | B13: Inventory | C13: Overflow | D13: Reward inbox | E13: Action | F13: Reward inbox khi đầy túi | G13: SV-009 | H13: Chỉ server tạo reward inbox persistent;100 entry/account; không hết hạn alpha; claim nguyên tử nếu đủ ô; đầy inbox dừng nguồn reward và cảnh báo. | I13: SV | J13: Must | K13: CL-012, CL-013, CL-014, CL-015, CL-020, CL-021, CL-022, CL-029, SV-007, SV-008 | L13: Đề xuất từ ý tưởng + cụ thể hóa cho alpha | M13: Reward receipt, claim request | N13: Inbox entries/items | O13: Inbox đầy không âm thầm xóa; dungeon entry bị chặn nếu thiếu capacity | P13: Bag đầy khi kill: reward còn trong inbox sau reconnect, claim 1 lần. | Q13: T07-SV, T10-CL | R13: TC-SV-009 | S13: BR-09 | U13: MVP | V13: Đề xuất
A14: 10 | B14: Cổ trùng | C14: Capture/feed | D14: Gu service | E14: Action | F14: Săn bắt và hunger server | G14: SV-010 | H14: Claim spawn chống race; roll 70% sau channel; tiêu seal khi start; hủy không refund; hunger elapsed online dùng serverTime, inventory không equipped không giảm. | I14: SV | J14: Must | K14: CL-016, CL-017, SV-006 | L14: Đề xuất từ ý tưởng + cụ thể hóa cho alpha | M14: Capture/feed intents; timers | N14: Gu instance/hunger receipt | O14: Capture successful commit rồi spawn remove; DB fail phục hồi terminal pending | P14: Feed/reconnect không reset timer để né đói;0 hunger khóa active/passive. | Q14: T08-SV | R14: TC-SV-010 | S14: BR-11, BR-12 | U14: MVP | V14: Đề xuất
A15: 11 | B15: Cổ trùng | C15: Refining | D15: Recipe service | E15: Action | F15: Công thức, pity và roll server | G15: SV-011 | H15: Pity theo character+recipe; chance=min(100,70+10×fails); RNG server và kết quả lưu transaction; success reset fails=0; fail giữ input. | I15: SV | J15: Must | K15: CL-018, CL-019, SV-008 | L15: Đề xuất từ ý tưởng + cụ thể hóa cho alpha | M15: Recipe/input IDs/configVersion | N15: Outcome/output/pity/ledger | O15: Stale preview config trả CONFIG_CHANGED trước consume; reuse input đồng thời bị lock | P15: Không output khi rollback; success tiêu 2 Gu; fail giữ 2 Gu; cả 2 mất material/fee. | Q15: T09-SV | R15: TC-SV-011 | S15: BR-13, BR-14 | U15: MVP | V15: Đề xuất
A16: 12 | B16: Progression | C16: Quest/XP | D16: Progress service | E16: Action | F16: XP, quest và rank-up từ event server | G16: SV-012 | H16: Event ID unique; XP cumulative curve; quest chỉ event server; reward và claim cùng transaction; rank II unlock validate toàn bộ điều kiện. | I16: SV | J16: Must | K16: CL-020, CL-021, CL-022, SV-008 | L16: Đề xuất từ ý tưởng + cụ thể hóa cho alpha | M16: Trusted gameplay event/claim | N16: Level/quest/rank receipt | O16: Event ID lặp bỏ qua; client tự gửi kill count bị reject | P16: Replay 100 event không tăng progress lần 2; rank-up chỉ một phí. | Q16: T10-SV | R16: TC-SV-012 | S16: BR-15, BR-16 | U16: MVP | V16: Đề xuất
A17: 13 | B17: Xã hội | C17: Party/chat | D17: Social service | E17: Action | F17: Party và recipient authorization | G17: SV-013 | H17: Membership unique; leader state; invite TTL; text sanitize/escape; channel kiểm tra membership; persist report không lưu token/password. | I17: SV | J17: Must | K17: AD-001, AD-002, AD-003, AD-004, AD-005, AD-006, AD-007, CL-023, CL-024, SV-015, SV-016, SV-017 | L17: Đề xuất từ ý tưởng + cụ thể hóa cho alpha | M17: Invite/chat/report | N17: Roster/message/report | O17: Kick/leave làm mất quyền party ngay; message rate limited | P17: User ngoài party không nghe/đọc được party channel; invite replay vô hiệu. | Q17: T13-SV, T16-SV | R17: TC-SV-013 | S17: BR-17, BR-18 | U17: MVP | V17: Đề xuất
A18: 14 | B18: PvE/PvP | C18: Instances | D18: Instance service | E18: Action | F18: Dungeon và duel state machine | G18: SV-014 | H18: Dungeon: created→ready→running→won/failed→closed; arena tương tự; fixed roster; key(runId, charId, rewardType) unique. | I18: SV | J18: Must | K18: CL-025, CL-026 | L18: Đề xuất từ ý tưởng + cụ thể hóa cho alpha | M18: Entry/ready/timers/combat | N18: Run/match state; receipts | O18: Boss reward pending được retry; đấu trường disconnect30s thua; không rank rewards | P18: Repeated completion không cấp thêm loot; orphan rooms cleanup≤60s. | Q18: T14-SV, T15-SV | R18: TC-SV-014 | S18: BR-19, BR-20 | T18: UC-13, UC-14 | U18: MVP | V18: Đề xuất
A19: 15 | B19: Content | C19: Configuration | D19: Catalog pipeline | E19: Action | F19: Data-driven và config version | G19: SV-015 | H19: Gu/item/mob/map/quest/recipe bằng JSON/CSV có schema; build kiểm tra foreign keys; publish immutable version; room đang chạy giữ version cũ tới restart. | I19: SV | J19: Must | K19: AD-001, AD-002, AD-003, AD-004, AD-005, AD-006, AD-007, CL-015, CL-024, SV-005, SV-013, SV-016, SV-017 | L19: Đề xuất từ ý tưởng + cụ thể hóa cho alpha | M19: Validated catalog/version | N19: Immutable bundle; validation report | O19: Recipe input/output thiếu: fail build; không hotpatch giữa craft | P19: 1 cấu hình lỗi bị chặn; rollback về version trước khôi phục đúng catalog. | Q19: T11-SV, T16-SV | R19: TC-SV-015 | U19: MVP | V19: Đề xuất
A20: 16 | B20: Vận hành | C20: Telemetry | D20: Metrics/logs | E20: Action | F20: Metrics, log và economy events | G20: SV-016 | H20: Theo dõi CCU/map, tick p95, intent rejection, DB latency, duplicate request, source/sink, funnel tutorial; correlationID xuyên command; không log secret. | I20: SV | J20: Must | K20: AD-001, AD-002, AD-003, AD-004, AD-005, AD-006, AD-007, CL-024, SV-013, SV-015, SV-017, SV-018 | L20: Đề xuất từ ý tưởng + cụ thể hóa cho alpha | M20: Server events/counters | N20: Dashboard/logs/export | O20: Log endpoint không public; không dùng analytics làm nguồn inventory | P20: Tra một craft receipt thấy request/ledger/config; có alert DB unavailable/tick trễ. | Q20: T16-SV, T17-SV | R20: TC-SV-016 | U20: MVP | V20: Đề xuất
A21: 17 | B21: Vận hành | C21: Deploy/restore | D21: Private alpha | E21: Action | F21: Backup, restore và rollback | G21: SV-017 | H21: Private staging/local trước; daily DB snapshot + trước release; giữ 7 daily/4 weekly; restore diễn tập; schema migration tương thích rollback. | I21: SV | J21: Must | K21: AD-001, AD-002, AD-003, AD-004, AD-005, AD-006, AD-007, CL-024, SV-013, SV-015, SV-016 | L21: Đề xuất từ ý tưởng + cụ thể hóa cho alpha | M21: DB backup/tag/runbook | N21: Restore report/release tag | O21: Không restore đè môi trường live khi chưa cô lập; go/no-go khi NFR fail | P21: Restore vào DB rỗng đạt RTO≤2h/RPO≤24h; restart crash khác disaster restore. | Q21: T16-SV, T18-SV | R21: TC-SV-017 | U21: MVP | V21: Đề xuất
A22: 18 | B22: Bảo vệ | C22: Validation | D22: Protocol guard | E22: Action | F22: Schema, quota và session fencing | G22: SV-018 | H22: Mọi message schema allowlist, max payload8KB; intents ≤20/s burst 40; cast theo cooldown; thiếu auth reject; lease token chống 2 writer. | I22: SV | J22: Must | K22: SV-001, SV-004, SV-016 | L22: Đề xuất từ ý tưởng + cụ thể hóa cho alpha | M22: Token/payload/sequence/lease | N22: Authorized validated command | O22: Stale lease/oversize/message lạ: reject, audit, close nếu spam | P22: Fuzz malformed không crash; stale room không ghi DB; người chơi không vào GM API. | Q22: T03-SV, T17-SV | R22: TC-SV-018 | S22: BR-01, BR-14, BR-18 | U22: MVP | V22: Đề xuất

Sheet 05_FSD_ADMIN
A1: 05 / FSD — GM / Admin
A2: 12cộtđầu tương ứng schema DAUN; bổ sung input/output/errors/AC/WBS/test/rules/UC/phase/status. Không có yêu cầu nào đã được đội duyệt.
A4: No | B4: 0 Depth | C4: 1 Depth | D4: 2 Depth | E4: 3 Depth | F4: Function / Requirement Name | G4: Requirement ID | H4: Detail / Quy tắc xử lý | I4: Category | J4: Importance | K4: Linkage / Req liên quan | L4: Note / Nguồn | M4: Input / Tiền điều kiện | N4: Output / Hậu điều kiện | O4: Validation / Ngoại lệ | P4: Acceptance Criteria | Q4: WBS IDs | R4: Test case | S4: Business Rules | T4: Use Cases | U4: Phase | V4: Status
A5: 1 | B5: GM | C5: Quyền truy cập | D5: Admin login | E5: Action | F5: Đăng nhập GM và RBAC | G5: AD-001 | H5: Role GM_READ, GM_MOD, GM_OWNER; chỉ OWNER cấp role; kiểm tra server từng endpoint; tài khoản game không mặc định vào admin. | I5: AD | J5: Must | K5: AD-002, AD-003, AD-004, AD-005, AD-006, AD-007, CL-024, CL-028, SV-013, SV-015, SV-016, SV-017 | L5: Đề xuất từ ý tưởng + cụ thể hóa cho alpha | M5: Admin credentials/role | N5: Authorized admin session | O5: 403 dù client tự sửa role; revoke có hiệu lực khi gọi tiếp | P5: Player và GM_READ không ban/grant; mọi thao tác đặc quyền có audit. | Q5: T16-CL, T16-SV | R5: TC-AD-001 | U5: MVP | V5: Đề xuất
A6: 2 | B6: GM | C6: Tra cứu | D6: Player detail | E6: Action | F6: Tra cứu nhân vật và receipt | G6: AD-002 | H6: Tìm theo characterId/name; xem level/rank/bag/loadout/ledger/quest/session; read-only; che thông tin nhạy cảm. | I6: AD | J6: Must | K6: AD-001, AD-003, AD-004, AD-005, AD-006, AD-007, CL-024, CL-028, SV-013, SV-015, SV-016, SV-017 | L6: Đề xuất từ ý tưởng + cụ thể hóa cho alpha | M6: Search/filter/page | N6: Paginated profile/log | O6: Không tìm thấy: empty; không hiển thị password/token | P6: GM_READ xem được lịch sử craft bằng requestId mà không sửa dữ liệu. | Q6: T16-CL, T16-SV | R6: TC-AD-002 | U6: MVP | V6: Đề xuất
A7: 3 | B7: GM | C7: Kiểm duyệt | D7: Moderation | E7: Action | F7: Mute/ban và xử lý report | G7: AD-003 | H7: GM_MOD mute/ban có lý do, thời hạn; kick session active; report kèm messageID; unban có audit. | I7: AD | J7: Must | K7: AD-001, AD-002, AD-004, AD-005, AD-006, AD-007, CL-024, CL-028, SV-013, SV-015, SV-016, SV-017 | L7: Đề xuất từ ý tưởng + cụ thể hóa cho alpha | M7: Target, action, reason, expiry | N7: Moderation record/session revoke | O7: Reason rỗng/expiry sai: reject | P7: Banned không join lại; mute không gửi chat; hết hạn tự gỡ. | Q7: T16-CL, T16-SV | R7: TC-AD-003 | U7: MVP | V7: Đề xuất
A8: 4 | B8: GM | C8: Hỗ trợ | D8: Grant item | E8: Action | F8: Cấp vật phẩm có kiểm soát | G8: AD-004 | H8: OWNER grant theo catalog/qty; lý do bắt buộc; preview; unique requestId; server gửi inbox khi bag đầy; không edit DB trực tiếp. | I8: AD | J8: Must | K8: AD-001, AD-002, AD-003, AD-005, AD-006, AD-007, CL-024, CL-028, SV-013, SV-015, SV-016, SV-017 | L8: Đề xuất từ ý tưởng + cụ thể hóa cho alpha | M8: Character, item, qty, reason, UUID | N8: Grant receipt/audit/inbox | O8: GM_MOD bị 403; ID lặp không cấp thêm | P8: Grant bị lặp chỉ 1 receipt; tra được người làm/lý do/giá trị trước-sau. | Q8: T16-CL, T16-SV | R8: TC-AD-004 | S8: BR-14 | U8: MVP | V8: Đề xuất
A9: 5 | B9: GM | C9: Cấu hình | D9: Publish | E9: Action | F9: Publish/rollback config qua pipeline | G9: AD-005 | H9: OWNER chọn bundle đã validate; staging smoke; alpha restart có thông báo; lưu version trước/sau và actor. | I9: AD | J9: Must | K9: AD-001, AD-002, AD-003, AD-004, AD-006, AD-007, CL-024, SV-013, SV-015, SV-016, SV-017 | L9: Đề xuất từ ý tưởng + cụ thể hóa cho alpha | M9: Bundle version/change reason | N9: Published config/audit | O9: Bundle lỗi chưa validate không publish | P9: 1 invalid foreign key chặn publish; rollback dùng bundle bất biến. | Q9: T16-SV, T18-SV | R9: TC-AD-005 | U9: MVP | V9: Đề xuất
A10: 6 | B10: GM | C10: Giám sát | D10: Dashboard | E10: Action | F10: Dashboard vận hành tối thiểu | G10: AD-006 | H10: Trang read-only số CCU/map, errors, tick, DBhealth; export report alpha; dùng dashboard sẵn có hoặc trang đơn giản. | I10: AD | J10: Must | K10: AD-001, AD-002, AD-003, AD-004, AD-005, AD-007, CL-024, CL-028, SV-013, SV-015, SV-016, SV-017 | L10: Đề xuất từ ý tưởng + cụ thể hóa cho alpha | M10: Time range/server stats | N10: Dashboard/export | O10: Không có metrics hiện No data; không hiện 0 giả | P10: DB mất kết nối hiện cảnh báo trong60s; số CCU khớp active lease. | Q10: T16-CL, T16-SV | R10: TC-AD-006 | U10: MVP | V10: Đề xuất
A11: 7 | B11: GM | C11: Audit | D11: Audit log | E11: Action | F11: Audit bất biến qua API | G11: AD-007 | H11: Actor/action/target/reason/requestId/timestamp/before-after; quyền read phân vai; không có API xóa hoặc sửa audit; chỉ mask secret. | I11: AD | J11: Must | K11: AD-001, AD-002, AD-003, AD-004, AD-005, AD-006, CL-024, SV-013, SV-015, SV-016, SV-017 | L11: Đề xuất từ ý tưởng + cụ thể hóa cho alpha | M11: Privileged commands | N11: Append-only audit records | O11: Audit ghi lỗi: đặc quyền thất bại cùng transaction | P11: Ban/grant/role/config đều có log; GM không xóa được qua API. | Q11: T16-SV | R11: TC-AD-007 | U11: MVP | V11: Đề xuất

Sheet 06_NFR
A1: 06 / Non-functional Requirements
A2: Mỗi chỉ số là mục tiêu đo trong điều kiện ghi rõ; chưa kiểm chứng bằng phần mềm thực tế.
A4: ID | B4: Nhóm | C4: Điều kiện đo | D4: Tiêu chí pass | E4: WBS IDs | F4: Evidence cần lưu
A5: NFR-01 | B5: Client performance | C5: Godot PC Windows foreground; scene tham chiếu 20 player+50 mob+VFX vừa;1366×768 low; máy i5-8250U/8GB/UHD620 hoặc máy đội chốt S01 | D5: Sau warmup2 phút đo 5 phút: FPS trung vị≥50; frame time p95≤33ms; máy thực tế phải ghi rõ | E5: T01-CL, T17-CL, T17-GD | F5: Perf capture, engine/OS/hardware/build ID
A6: NFR-02 | B6: Realtime latency | C6: Máy test cùng khu vực; RTT giả lập100ms, jitter20ms, packet loss 1%; input hợp lệ không rate-limit | D6: Command ACK p95≤250ms; correction không xuyên tường; báo riêng RTT và xử lý server | E6: T04-SV, T17-SV, T17-GD | F6: 10.000 intent; latency distribution
A7: NFR-03 | B7: Capacity alpha | C7: 50CCU tổng 1 shard;≤20 player/map room;50 mob hoạt động/map; instance roster≤3; 50bots2 giờ có cast/loot/craft | D7: Simulation20Hz: tick duration p95≤40ms; không disconnect do quá tải; memory không tăng không giới hạn; p95DBcommand≤200ms | E7: T17-SV, T17-GD | F7: Ghi CPU/RAM/server config; đây là mục tiêu kiểm thử, chưa là benchmark
A8: NFR-04 | B8: Tài sản bền vững | C8: Inventory/tiền/quest/reward/craft đã ACK commit; position/HP/hunger checkpoint30s | D8: Crash process: mất 0 giao dịch đã ACK; vị trí có thể lùi≤30s;20 retry cùng ID đúng 1 hiệu lực | E8: T07-SV, T09-SV, T12-SV, T17-SV | F8: Fault injection trước/sau commit và trước/sau ACK
A9: NFR-05 | B9: Access/security | C9: Auth/game/admin API; token hết hạn; account khác; sửa payload; spam; XSS chat | D9: 100% negative matrix bắt buộc bị chặn; không secret trong log; không client-authoritative reward; 0 lỗi P0/P1 auth/dupe | E9: T02-SV, T16-SV, T17-SV | F9: Danh sách test và evidence; không gọi là chứng nhận bảo mật
A10: NFR-06 | B10: Backup/disaster | C10: Snapshot hằng ngày + trước release; giữ 7 daily/4 weekly; restore vào môi trường cô lập | D10: RPO≤24h; RTO≤2 giờ trong diễn tập; item/ledger đối chiếu khớp backup; khác crash checkpoint | E10: T16-SV, T18-SV | F10: Log thời điểm snapshot, mất dữ liệu giả lập và hoàn tất restore
A11: NFR-07 | B11: Compatibility | C11: Godot native Windows 10/11;1366×768/1920×1080; keyboard+mouse; Web export kiểm chứng riêng | D11: Login→quest→craft→dungeon chạy trên Windows 10/11; UI không chặn nútchính; version ghi trong báo cáo | E11: T17-CL, T17-GD | F11: OS/engine matrix; Web là spike, chưa cam kết mobile/nativeMac/Linux
A12: NFR-08 | B12: Asset budget | C12: PC cold start; content shell+town không tính engine; Web spike qua mạng 20 Mbps; cache cold; không tính thời gian nhập password; lazyload farm/dungeon | D12: Initial compressed payload≤25MB; interactive p95≤15 giây trên 10 lượt; asset progress/failure retry có UI | E12: T02-CL, T17-CL, T17-AR | F12: Network waterfall; dung lượng bundle; ngân sách cần kiểm chứng S01
A13: NFR-09 | B13: Maintainability | C13: Client/server/shared-content tách rõ; server không import UI; config có schema và version | D13: CI chặn typecheck/build/schema/transaction tests fail; dev mới chạy local theoREADME≤60 phút | E13: T02-SV, T11-SV, T16-GD | F13: Clean-machine setup run; dependency graph review
A14: NFR-10 | B14: Observability | C14: Auth/room/cast/craft/inventory/admin; mỗi command có correlationID | D14: Tra1 receipt tìm đủ configVersion/outcome/ledger; alert DBunavailable hoặc tick overrun trong 60 giây; log không secret | E14: T16-SV, T17-SV | F14: Dashboard capture; trace một happy và một failed command
A15: NFR-11 | B15: UX và readability | C15: 10 tester chưa được hướng dẫn; low graphics và mute; skill errors và telegraphs | D15: ≥8/10 tự di chuyển/chọn/đánh trong 3 phút;5/5telegraph kiểm tra có shape/icon ngoài màu; scale chữ≥14px ở 1366×768 | E15: T03-GD, T16-AR, T17-GD | F15: Quan sát task completion; note lý do thất bại
A16: NFR-12 | B16: Release gate | C16: Feature freeze; E2E, dupe, security, load, restore;5 gate có biên bản | D16: 0P0/0P1;100% Must có ít nhất 1 test passed với evidence; Should có known issues; build/config/schema tags và rollback runbook | E16: T16-GD, T17-GD, T18-GD, T18-SV | F16: Go/no-go check list; chưa có test nào được đánh dấu passed trong bản kế hoạch

Sheet 07_RULES
A1: 07 / Business Rules
A2: Thông sốv0.1 để lập trình/thử nghiệm; chưa là cân bằng đã playtest. Thay đổi phải tăng configVersion.
A4: ID | B4: Nhóm | C4: Quy tắc / Công thức | D4: Biên / Ngoại lệ | E4: Requirement IDs
A5: BR-01 | B5: Identity | C5: 1 account→1 character; mỗi character chỉ 1 write lease; tên trim/casefold để so trùng;3–16 ký tự. | D5: Tất cả session/room/admin validate ownership server. | E5: CL-001, CL-002, SV-001, SV-018
A6: BR-02 | B6: Tọa độ | C6: Logic dùng world tile float; iso sx=(x−y)×32, sy=(x+y)×16, tile 64×32; collision/nav không dựa pixel camera. | D6: Speed 3 tile/s; server path và swept collision; AOI12 tile+hysteresis2. | E6: CL-003, CL-004, SV-002, SV-003
A7: BR-03 | B7: Loadout | C7: 4 active rank I;2 passive rank II; không trùng guDef; đổi ở safe zone và ngoài combat5s; không đổi arena. | D7: RankII unlock và hunger≥1; passive ngủ không tác dụng. | E7: CL-007, CL-015, CL-020
A8: BR-04 | B8: Damage | C8: Damage=max(1, floor((basePower+0.8×attack)×rankFactor×hungerFactor×100/(100+defense)×modeFactor)); rank I=1.0 / rank II=1.25; modeFactor PvP=0.7. | D8: Heal/shield=floor((basePower+0.5×attack)×rankFactor×hungerFactor); không crit/RNG damage alpha; shield hấp thụ trước HP, tổng cap40% maxHP. | E8: CL-008, SV-005
A9: BR-05 | B9: Mana | C9: Cost=ceil(maxMana×costPct/100); baseMaxMana100; hồi 2 mana/s ngoài combat5s,1 mana/s trong combat; HP không tự hồi trong combat. | D9: Accepted cast tiêu mana+cooldown; rejected cast không tiêu; interrupt sauaccept không refund. | E9: CL-009, SV-005
A10: BR-06 | B10: Status | C10: Slow cùng type lấy mạnh nhất, không cộng; stun refresh lấy endTime max, cap2s PvP; shield cùng source refresh, khác source tổng cap 40% maxHP. | D10: Timer dùng servertime; buffpassiveunique theo effect group; dispel gỡ debuff hợp lệ. | E10: CL-010, SV-005
A11: BR-07 | B11: Death | C11: PvEdeath:5s→safe spawn fullHP/mana; penalty=min(50, floor(balance×0.05)); noXP/Gu/item loss. | D11: Arena death không penalty; battle terminal unique deathID. | E11: CL-011, SV-007
A12: BR-08 | B12: Loot | C12: Openworldencounter owner=firstvalidhit; lock đến kill/capture/leash; ownerdisconnect10s rồi reset nếu không combat; reward personal. | D12: Khi kill cùng lúc capture chỉ terminal transition đầu thành công; loot không rơi đất alpha. | E12: CL-012, SV-006
A13: BR-09 | B13: Bag | C13: 30 slot; material/food/seal stack 99; Gu unique1 slot; tất cả Gu bound; equipped vẫn chiếm ô bag, loadout là reference; reward overflow→inbox 100 entry, không expire alpha. | D13: Túi/inbox đều đầy chặn nguồn reward mới có cảnh báo; buy/feed/craft capacity validate trước random. | E13: CL-013, CL-022, SV-009
A14: BR-10 | B14: Gu instance | C14: Fields: owner, definition, rank, hunger, locked, bound, equippedSlot, version; locked/equipped không bán/luyện. | D14: InputinstanceIDs khác nhau; thao tác ownership/type/rank/version server. | E14: CL-014, CL-015, CL-018
A15: BR-11 | B15: Capture | C15: Capturable spawn HP≤30%, range≤3 tile, owner=you, seal≥1, slot available; channel 2s;70% roll; nhận damage/hết range thì hủy. | D15: Seal mất khistartaccepted, hủy/fail không refund; spawn claim exclusive; success: spawn removed+createGu. | E15: CL-016, SV-006, SV-010
... A25: BR-21 | B25: Recovery | C25: Grace30s; single writerleaseTTL30s/renew 10s, fencingcounterDB; checkpoint position/HP/hunger 30s; economic commit before ACK. | D25: Expired lease không ghi; new room khôi phục state bền vững; maptransferreserve/commit/abort có expiry. | E25: CL-006, CL-027, SV-004, SV-007

Sheet 08_USE_CASES
A1: 08 / Luồng sử dụng
A2: Happy path + lỗi + dữ liệu thay đổi. Các thao tác tài sản phải transaction và idempotent.
A4: ID | B4: Actor | C4: Tiền điều kiện | D4: Luồng chính | E4: Ngoại lệ / Phục hồi | F4: Dữ liệu liên quan | G4: Requirements
A5: UC-01 | B5: Người chơi mới | C5: Có tài khoản mời; server hoạt động | D5: Đăng nhập → tạo tên → nhận starter kit một lần → vào thị trấn → tutorial | E5: Tên trùng thì sửa; token hết hạn đăng nhập lại; tạo lặp trả character cũ | F5: Character, starter receipt, tutorial step | G5: CL-001, CL-002, CL-029, SV-001
A6: UC-02 | B6: Người chơi | C6: Đã ở map, còn sống | D6: Click nền → tìm đường → server kiểm tra → di chuyển; click target/NPC → đi vào tầm → tương tác | E6: UI focus không di chuyển; tường/đích ngoài biên từ chối; target rời AOI bỏ chọn | F6: Position checkpoint, selected target transient | G6: CL-003, CL-004, CL-005
A7: UC-03 | B7: Người chơi | C7: Cổ hợp lệ, đủ mana, target có quyền đánh | D7: Chọn target → QWER → validate cast → trừ mana/cooldown → resolve hit → mob chết → reward commit → popup | E7: Ngoài tầm/LOS không cast; full bag chuyển inbox; death event lặp bỏ qua | F7: Combat event ID, reward receipt, ledger | G7: CL-007, CL-008, CL-012, SV-005, SV-006
A8: UC-04 | B8: Người chơi | C8: Ở safe zone, ngoài combat 5s | D8: Mở bag → xem tooltip → lock/unlock → equip slot đúng type/rank → version mới → derived stats | E8: Equipped hoặc locked không được bán/luyện; duplicate definition reject; stale version refresh | F8: Gu instance, loadout, inventoryVersion | G8: CL-013, CL-014, CL-015, SV-008
A9: UC-05 | B9: Người chơi | C9: Sở hữu encounter; target capturable HP≤30%; có seal và ô | D9: Chọn Bắt → claim spawn → tiêu seal/start 2s channel → server roll 70% → commit Gu hoặc fail → receipt | E9: Bị đánh/đi xa hủy, không refund seal; target bị giết thì một terminal winner; DB lỗi không ACK success | F9: Spawn claim/terminal ID, Gu instance, request receipt | G9: CL-016, SV-006, SV-010
A10: UC-06 | B10: Người chơi | C10: Có Cổ và thức ăn đúng loại; hunger<100 | D10: Mở Feed → xem +40 cap100 → confirm → lock/version validate → consume food + update hunger → commit | E10: Sai food/đã đầy/version cũ reject không consume; retry cùng UUID trả receipt cũ | F10: Food stack, Gu hunger, ledger, receipt | G10: CL-017, SV-008, SV-010
A11: UC-07 | B11: Người chơi | C11: Đủ 2 Cổ I hợp lệ, material, tiền và capacity | D11: Chọn recipe/instance → preview chance/pity/cost → confirm UUID → lock → roll → write consume/output/pity/ledger/receipt → commit → show | E11: Fail giữ 2 Gu mất material+fee; success mất 2 Gu; timeout query cùng UUID; config mới yêu cầu preview lại | F11: RefineAttempt, pity, inventory, currency ledger | G11: CL-018, CL-019, SV-008, SV-011
A12: UC-08 | B12: Người chơi | C12: Quest prerequisites hợp lệ | D12: Nhận quest → gameplay events server → đủ progress → claim reward một lần → level 10/Q08 → confirm rank II | E12: Client không gửi tăng count; Q08 cấp đủ XP/đá; thiếu 500 currency thì farm; rank-up retry không trừ lặp | F12: QuestProgress, event dedupe, XP/rank ledger | G12: CL-020, CL-021, SV-012
A13: UC-09 | B13: Người chơi | C13: Đứng gần NPC shop ≤2 tile | D13: Chọn item/qty → preview giá → confirm UUID → validate tiền/slot/item → atomic buy/sell → receipt | E13: Locked/equipped không bán; không âm tiền; bag đầy mua bị chặn; request cũ trả receipt | F13: Inventory, soft currency, ledger | G13: CL-022, SV-008
A14: UC-10 | B14: Người chơi | C14: HP về0 ngoài arena | D14: Death ID → khóa input → penalty một lần → chờ5s → safe respawn fullHP/mana | E14: Reconnect giữa death tiếp tục cùng state; arena không penalty; no Gu/item drop alpha | F14: Death receipt, currency ledger, position checkpoint | G14: CL-011, SV-007
A15: UC-11 | B15: Người chơi | C15: Session/lease đang hợp lệ | D15: Portal: reserve đích → freeze nguồn → commit lease/checkpoint → join đích; reconnect: grace30s → auth → snapshot | E15: Đích đầy abort về nguồn; process crash recovery từ DB; lease cũ không ghi; pending economic query receipt | F15: Lease/fencing, transfer record, committed inventory | G15: CL-006, CL-027, SV-004, SV-007
... A20: UC-16 | B20: Server owner | C20: Có snapshot và môi trường restore cô lập | D20: Chọn snapshot/tag → restore DB rỗng → migrate tương thích → verify ledger/items → smoke → đo RPO/RTO → lưu báo cáo | E20: Restore fail không chuyển traffic; rollback app cần schema tương thích; không xóa snapshot nguồn | F20: Restore log, checksums/row counts, report | G20: SV-017, NFR-06

Sheet 09_DATA
A1: 09 / Data Dictionary
A2: Logical model đề xuất; chi tiết type/index/migration chốt S02. PostgreSQL là nguồn cho tài sản; room memory cho thế giới realtime.
A4: Entity | B4: Fields / Keys | C4: Relations / Constraints | D4: Owner | E4: Lưu ý
A5: Account | B5: account_id PK; username UNIQUE; password_hash; status; token_version | C5: 1:1 Character; 1: N Session | D5: SV | E5: Không lưu plaintext password; account mời alpha
A6: Character | B6: character_id PK; account_id UNIQUE FK; normalized_name UNIQUE; level; rank; xp; currency; inventory_version | C6: 1: N GuInstance/InventoryStack/QuestProgress | D6: SV | E6: Currency≥0; level 1..20; rank I/II; balance thay đổi qua ledger
A7: SessionLease | B7: character_id PK/FK; session_id; room_id; fencing_counter; expires_at | C7: 1:1 active Character writer | D7: SV | E7: Renew10s/TTL 30s; UPDATE phải kiểm fencing; revoke khi ban
A8: CharacterSnapshot | B8: character_id PK; map_id; position; hp; mana; hunger_clock; checkpoint_at | C8: 1:1 Character | D8: SV | E8: Checkpoint≤30s; economic assets không dựa snapshot này
A9: InventoryStack | B9: stack_id PK; character_id FK; item_def_id; qty; bag_slot; version | C9: N:1 ItemDefinition | D9: SV | E9: Qty1..99; UNIQUE(character, bag_slot); Gu không dùng stack
A10: GuInstance | B10: gu_id PK; character_id FK; gu_def_id; hunger; locked; bound; bag_slot; version | C10: N:1 GuDefinition; 0..1 LoadoutSlot | D10: SV | E10: Hunger 0..100; unique slot chung bag; equipped vẫn chiếm ô bag
A11: LoadoutSlot | B11: character_id FK; slot_no; gu_id UNIQUE FK | C11: PK(character_id, slot_no); 1: N Character | D11: SV | E11: Slot 1..4 active;5..6 passive rank II; unique definition per loadout validate transaction
A12: CommandReceipt | B12: character_id FK; request_id; payload_hash; kind; config_version; result; committed_at | C12: UNIQUE(character_id, request_id) | D12: SV | E12: Result immutable≥30 ngày; sameID khác payload 409; recovery qua receipt
A13: EconomyLedger | B13: entry_id PK; character_id; request_id; asset_type; asset_id; delta; reason; balance_after | C13: N:1 CommandReceipt hoặc trustedRewardReceipt | D13: SV | E13: Append-only quaAPI; atomic với balance/item; không dùng log analytics làm source of truth
A14: RefineAttempt | B14: attempt_id PK; character_id; recipe_id; input_ids; roll; chance; outcome; request_id UNIQUE | C14: N:1 RecipeDefinition/CommandReceipt | D14: SV | E14: Persist RNG cùng consume/output; không expose RNG seed client
A15: RecipePity | B15: character_id; recipe_id; fail_count; version | C15: PK(character_id, recipe_id) | D15: SV | E15: 0..3 đến 100%; success reset 0; không share giữa recipe
... A25: ContentBundle | B25: version PK; hash; schema_version; gu/item/mob/map/recipe/quest definitions | C25: Immutable; all FK validate build time | D25: CL+SV+GD | E25: Runtime pin bundle; không đổi config giữa craft; sourceJSON/CSV

Sheet 10_API
A1: 10 / API & Realtime Contract
A2: Tên command/endpoint ở mức thiết kế, không cam kết API framework. Validate auth/ownership/schema/rate trên server.
A4: ID | B4: Transport | C4: Endpoint / Command | D4: Quyền | E4: Request | F4: Response | G4: Error codes | H4: Requirement IDs
A5: API-01 | B5: HTTPS | C5: POST /auth/login | D5: Public mời | E5: username, password | F5: sessionToken, expiresAt | G5: AUTH_FAILED/RATE_LIMIT | H5: SV-001, CL-001
A6: API-02 | B6: HTTPS | C6: POST /characters | D6: Account owner | E6: name, avatar, requestId | F6: characterId, starterReceipt | G6: NAME_TAKEN/ALREADY_EXISTS | H6: CL-002, SV-001
A7: API-03 | B7: HTTPS | C7: GET /characters/me | D7: Account owner | E7: session token | F7: profile, bag, loadout, quest, version | G7: 401/403 | H7: SV-007
A8: API-04 | B8: HTTPS | C8: GET /config/: version | D8: Authenticated | E8: version/hash | F8: immutable catalog bundle | G8: CONFIG_NOT_FOUND | H8: SV-015, CL-030
A9: API-05 | B9: Room | C9: joinMap | D9: Character owner | E9: mapId, sessionToken, leaseToken | F9: snapshot, selfID, configVersion | G9: AUTH_REQUIRED/MAP_FULL/STALE_LEASE | H9: SV-001, SV-003, SV-004
A10: API-06 | B10: WS | C10: moveIntent | D10: Active room lease | E10: seq, destX, destY | F10: path/correction, serverTime | G10: BAD_PATH/OVERSPEED/STALE_SEQ | H10: CL-003, SV-002
A11: API-07 | B11: WS | C11: castIntent | D11: Active room lease | E11: seq, guId, targetId/point | F11: castId, accepted/hit/events | G11: NO_MANA/CD/RANGE/LOS/STUN/HUNGRY | H11: CL-008, SV-005
A12: API-08 | B12: WS | C12: equipGu | D12: Character owner | E12: requestId, expectedVersion, guId, slot | F12: receipt, loadout, newVersion | G12: BAD_SLOT/RANK/COMBAT/LOCKED | H12: CL-015, SV-008
A13: API-09 | B13: WS | C13: captureStart/cancel | D13: Encounter owner | E13: requestId, spawnId, sealId, version | F13: channelId/outcomeReceipt | G13: CLAIMED/HP_HIGH/NO_SLOT/INVALID | H13: CL-016, SV-010
A14: API-10 | B14: WS | C14: feedGu | D14: Character owner | E14: requestId, expectedVersion, guId, foodId | F14: receipt, hunger, newVersion | G14: WRONG_FOOD/FULL/NO_ITEM | H14: CL-017, SV-010
A15: API-11 | B15: WS | C15: refinePreview | D15: Character owner | E15: recipeId, inputGuIds | F15: cost, chance, pity, configVersion | G15: INVALID_INPUT/LOCKED/EQUIPPED | H15: CL-018, SV-011
... A30: API-26 | B30: WS | C30: lockGu/respawn/useConsumable | D30: Character owner/active lease | E30: requestId, version, guId hoặc itemId | F30: receipt, state | G30: DEAD/NOT_DEAD/LOCKED/NO_ITEM | H30: CL-011, CL-014, SV-008

Sheet 11_GU_CATALOG
A1: 11 / Catalog 20 Cổ
A2: 10 Cổ rank I+10 rank II; tên minh họa; nhiều biến thể dùng 8 effect primitives. power của heal/shield theo công thức rulebook; buff có đơn vị riêng.
A4: ID | B4: Tên | C4: Rank | D4: Loại | E4: Primitive | F4: Target | G4: Base power / effect value | H4: Mana %max | I4: CD (s) | J4: Range (tile) | K4: Duration (s) | L4: Food ID | M4: Nguồn / Ghi chú effect | N4: Trạng thái cân bằng
A5: GU-01 | B5: Nguyệt Quang Cổ | C5: I | D5: Công kích | E5: projectile | F5: enemy | G5: 35 | H5: 8 | I5: 2 | J5: 6 | K5: 0 | L5: MAT-01 | M5: Starter; sói rừng | N5: Nháp cân bằng — chưa playtest
A6: GU-02 | B6: Lôi Điệp Cổ | C6: I | D6: Công kích | E6: aoe | F6: ground | G6: 25 | H6: 14 | I6: 6 | J6: 5 | K6: 0 | L6: MAT-04 | M6: Hoang Cổ ở farm | N6: Nháp cân bằng — chưa playtest
A7: GU-03 | B7: Bạch Ngọc Cổ | C7: I | D7: Phòng ngự | E7: shield | F7: self | G7: 70 | H7: 12 | I7: 12 | J7: 0 | K7: 5 | L7: MAT-02 | M7: Starter; sơn thú | N7: Nháp cân bằng — chưa playtest
A8: GU-04 | B8: Kim Chung Cổ | C8: I | D8: Phòng ngự | E8: buff | F8: passive | G8: 10 | H8: 0 | I8: 0 | J8: 0 | K8: 0 | L8: MAT-02 | M8: Hoang Cổ tinh anh; +10 defense | N8: Nháp cân bằng — chưa playtest
A9: GU-05 | B9: Bạch Hạc Cổ | C9: I | D9: Thân pháp | E9: dash | F9: ground | G9: 0 | H9: 10 | I9: 8 | J9: 3 | K9: 0 | L9: MAT-03 | M9: Starter; hạc núi | N9: Nháp cân bằng — chưa playtest
A10: GU-06 | B10: Du Cương Cổ | C10: I | D10: Thân pháp | E10: buff | F10: self | G10: 20 | H10: 8 | I10: 10 | J10: 0 | K10: 4 | L10: MAT-03 | M10: Hoang Cổ ở farm; +20% speed | N10: Nháp cân bằng — chưa playtest
A11: GU-07 | B11: Băng Tằm Cổ | C11: I | D11: Khống chế | E11: slow | F11: enemy | G11: 20 | H11: 10 | I11: 8 | J11: 5 | K11: 3 | L11: MAT-04 | M11: Starter; băng tằm; slow 30% | N11: Nháp cân bằng — chưa playtest
A12: GU-08 | B12: Hóa Thạch Cổ | C12: I | D12: Khống chế | E12: stun | F12: enemy | G12: 10 | H12: 16 | I12: 14 | J12: 4 | K12: 1.2 | L12: MAT-02 | M12: Hoang Cổ tinh anh | N12: Nháp cân bằng — chưa playtest
A13: GU-09 | B13: Hồi Xuân Cổ | C13: I | D13: Phụ trợ | E13: heal | F13: ally/self | G13: 65 | H13: 15 | I13: 12 | J13: 4 | K13: 0 | L13: MAT-03 | M13: Hoang Cổ ở farm | N13: Nháp cân bằng — chưa playtest
A14: GU-10 | B14: Địa Thính Cổ | C14: I | D14: Do thám | E14: buff | F14: passive | G14: 4 | H14: 0 | I14: 0 | J14: 0 | K14: 0 | L14: MAT-01 | M14: Hoang Cổ tinh anh; minimap 8→12 tile trong AOI | N14: Nháp cân bằng — chưa playtest
A15: GU-11 | B15: Nguyệt Quang Cổ II | C15: II | D15: Công kích | E15: projectile | F15: enemy | G15: 40.2 | H15: 10 | I15: 2 | J15: 6 | K15: 0 | L15: MAT-01 | M15: REC-01 | N15: Cùng primitive; rankFactor1.25; tên minh họa
A16: GU-12 | B16: Lôi Điệp Cổ II | C16: II | D16: Công kích | E16: aoe | F16: ground | G16: 28.7 | H16: 16 | I16: 6 | J16: 5 | K16: 0 | L16: MAT-04 | M16: REC-02 | N16: Cùng primitive; rankFactor1.25; tên minh họa
... A24: GU-20 | B24: Địa Thính Cổ II | C24: II | D24: Do thám | E24: buff | F24: passive | G24: 4 | H24: 0 | I24: 0 | J24: 0 | K24: 0 | L24: MAT-01 | M24: REC-10 | N24: Cùng primitive; rankFactor1.25; tên minh họa

Sheet 12_CONTENT
A1: 12 / Maps • Mobs • Items • Recipes • Quests
A2: Catalog nhápv0.1; giá/số lượng là giả định thiết kế, không phải dữ liệu thị trường. Q01–08 tổng 4500 XP, đủ level 10 trước rank II.
A4: Loại | B4: ID | C4: Tên / Inputs | D4: Chi tiết / Luật | E4: Điều kiện / Output | F4: Owner / Reward
A5: Map | B5: MAP-01 | C5: Thị trấn Sơn Trại | D5: Safe zone,4 NPC, spawn, training target, portal farm;64×64 tile | E5: RankI; không PvP | F5: AR+GD
A6: Map | B6: MAP-02 | C6: Vạn Thú Sơn | D6: Open farm 3 bãi theo level;128×128 tile;≤20 player/room;50 active mobs | E6: Level 1–20; capture; noopenPK | F6: AR+GD
A7: Map | B7: MAP-03 | C7: Di tích Bạch Cốt | D7: Dungeon 1–3;64×64 tile;1 boss 2 pattern;15min | E7: Level 10/rank II | F7: AR+GD
A8: Map variant | B8: MAP-02A | C8: Đấu trường thử luyện | D8: Tái dùng 1 vùng MAP-02, instance 2 người; không tính map asset mới | E8: Opt-in; no rewards | F8: AR+GD
A9: NPC | B9: NPC-01 | C9: Dẫn lộ | D9: Tutorial,8mainquests | E9: Town | F9: GD
A10: NPC | B10: NPC-02 | C10: Cổ thương | D10: Food/seal/material fixed shop | E10: Town; shop range 2 tile | F10: GD
A11: NPC | B11: NPC-03 | C11: Luyện Cổ sư | D11: Refine/rank-up UI | E11: Town; recipe/rank validate | F11: GD
A12: NPC | B12: NPC-04 | C12: Thủ hộ di tích | D12: 2sidequests; dungeon portal | E12: Town/farm portal | F12: GD
A13: Item | B13: MAT-01 | C13: Thịt thú | D13: Food meat; stack 99; NPCbuy8/sell 2 currency | E13: Farm normal; GU01/GU10 | F13: GD
A14: Item | B14: MAT-02 | C14: Chân Nguyên Thạch | D14: Food mineral/refine/rank-up; stack 99; buy 20/sell 5 | E14: Farm elite/quest; GU03/04/08 | F14: GD
A15: Item | B15: MAT-03 | C15: Linh quả | D15: Food fruit; stack 99; buy 8/sell 2 | E15: Farm normal; GU05/06/09 | F15: GD
... A52: Quest Side | B52: Q-10 | C52: Di tích cổ | D52: Finish1dungeonrun | E52: RankII; Q-08 claimed | F52: 500 XP; 200 currency; 3MAT-02

Sheet 13_WBS
A1: 13 / Work Breakdown Structure — 72 work packages
A2: Effort=person-day 8 giờ hữu ích; deadline khung 2 tuần; FS giữa sprint, phối hợp trong cùng sprint. Dự phòng đã có trong 36 tuần.
A4: WBS code | B4: Task ID | C4: Deliverable group | D4: Work package | E4: Owner | F4: Sprint | G4: Start week | H4: End week | I4: Predecessors (FS) | J4: Base PD | K4: Reserve PD | L4: Total PD | M4: Hours incl reserve | N4: Start date | O4: End date | P4: Status | Q4: Done % | R4: Definition of Done | S4: Requirement IDs
A5: 1.1 | B5: T01-GD | C5: Khóa phạm vi và spike | D5: Khóa MVP, FSD và danh sách quyết định | E5: GD | F5: 1 | G5: 1 | H5: 2 | J5: 2.5 | K5: =J5*'00_START'!$B$10 -> 0.5 | L5: =J5+K5 -> 3 | M5: =L5*'00_START'!$B$12 -> 24 | N5: =WORKDAY('00_START'!$B$7-1,(G5-1)*5+1) -> 46307 | O5: =WORKDAY('00_START'!$B$7-1,H5*5) -> 46318 | P5: Đang làm | Q5: 0 | R5: Scope v0.2; FSD có ID, AC, danh sách TBD
A6: 1.2 | B6: T01-CL | C6: Khóa phạm vi và spike | D6: Spike Godot isometric trên PC; thử Web export | E6: CL | F6: 1 | G6: 1 | H6: 2 | J6: 3 | K6: =J6*'00_START'!$B$10 -> 0.6 | L6: =J6+K6 -> 3.6 | M6: =L6*'00_START'!$B$12 -> 28.8 | N6: =WORKDAY('00_START'!$B$7-1,(G6-1)*5+1) -> 46307 | O6: =WORKDAY('00_START'!$B$7-1,H6*5) -> 46318 | P6: Đang làm | Q6: 0 | R6: Map mẫu, click-to-move, đo render trên máy tham chiếu
A7: 1.3 | B7: T01-SV | C7: Khóa phạm vi và spike | D7: Spike authoritative room và lưu dữ liệu | E7: SV | F7: 1 | G7: 1 | H7: 2 | J7: 3 | K7: =J7*'00_START'!$B$10 -> 0.6 | L7: =J7+K7 -> 3.6 | M7: =L7*'00_START'!$B$12 -> 28.8 | N7: =WORKDAY('00_START'!$B$7-1,(G7-1)*5+1) -> 46307 | O7: =WORKDAY('00_START'!$B$7-1,H7*5) -> 46318 | P7: Chưa bắt đầu | Q7: 0 | R7: Hai client kết nối; server giữ state; thử ghi transaction
A8: 1.4 | B8: T01-AR | C8: Khóa phạm vi và spike | D8: Art direction và kiểm kê tài nguyên | E8: AR | F8: 1 | G8: 1 | H8: 2 | J8: 2.5 | K8: =J8*'00_START'!$B$10 -> 0.5 | L8: =J8+K8 -> 3 | M8: =L8*'00_START'!$B$12 -> 24 | N8: =WORKDAY('00_START'!$B$7-1,(G8-1)*5+1) -> 46307 | O8: =WORKDAY('00_START'!$B$7-1,H8*5) -> 46318 | P8: Đang làm | Q8: 0 | R8: Moodboard nội bộ, style guide, danh mục asset và nguồn
A9: 2.1 | B9: T02-GD | C9: Nền tảng kỹ thuật | D9: Chốt luật chiến đấu và mô hình dữ liệu | E9: GD | F9: 2 | G9: 3 | H9: 4 | I9: T01-GD, T01-CL, T01-SV | J9: 2.5 | K9: =J9*'00_START'!$B$10 -> 0.5 | L9: =J9+K9 -> 3 | M9: =L9*'00_START'!$B$12 -> 24 | N9: =WORKDAY('00_START'!$B$7-1,(G9-1)*5+1) -> 46321 | O9: =WORKDAY('00_START'!$B$7-1,H9*5) -> 46332 | P9: Chưa bắt đầu | Q9: 0 | R9: Rulebook, 5 Cổ đầu, flow lỗi và test matrix
A10: 2.2 | B10: T02-CL | C10: Nền tảng kỹ thuật | D10: Client shell, scene và tọa độ | E10: CL | F10: 2 | G10: 3 | H10: 4 | I10: T01-CL | J10: 3 | K10: =J10*'00_START'!$B$10 -> 0.6 | L10: =J10+K10 -> 3.6 | M10: =L10*'00_START'!$B$12 -> 28.8 | N10: =WORKDAY('00_START'!$B$7-1,(G10-1)*5+1) -> 46321 | O10: =WORKDAY('00_START'!$B$7-1,H10*5) -> 46332 | P10: Chưa bắt đầu | Q10: 0 | R10: Boot/Login/World/HUD; world↔iso; loader và input | S10: CL-001, CL-002, CL-004
A11: 2.3 | B11: T02-SV | C11: Nền tảng kỹ thuật | D11: Repo, CI, schema và đăng nhập | E11: SV | F11: 2 | G11: 3 | H11: 4 | I11: T01-SV | J11: 3 | K11: =J11*'00_START'!$B$10 -> 0.6 | L11: =J11+K11 -> 3.6 | M11: =L11*'00_START'!$B$12 -> 28.8 | N11: =WORKDAY('00_START'!$B$7-1,(G11-1)*5+1) -> 46321 | O11: =WORKDAY('00_START'!$B$7-1,H11*5) -> 46332 | P11: Chưa bắt đầu | Q11: 0 | R11: CI build; migration; tài khoản mời; session một nhân vật | S11: CL-001, CL-002, SV-001
A12: 2.4 | B12: T02-AR | C12: Nền tảng kỹ thuật | D12: Nhân vật và tileset cơ sở | E12: AR | F12: 2 | G12: 3 | H12: 4 | I12: T01-AR | J12: 2.5 | K12: =J12*'00_START'!$B$10 -> 0.5 | L12: =J12+K12 -> 3 | M12: =L12*'00_START'!$B$12 -> 24 | N12: =WORKDAY('00_START'!$B$7-1,(G12-1)*5+1) -> 46321 | O12: =WORKDAY('00_START'!$B$7-1,H12*5) -> 46332 | P12: Chưa bắt đầu | Q12: 0 | R12: Một avatar, 4 hướng hiển thị, idle/walk/attack; tileset dùng lại
A13: 2.5 | B13: T03-GD | C13: Nền tảng kỹ thuật | D13: Kiểm thử điều khiển và onboarding | E13: GD | F13: 3 | G13: 5 | H13: 6 | I13: T02-GD, T02-CL | J13: 2 | K13: =J13*'00_START'!$B$10 -> 0.4 | L13: =J13+K13 -> 2.4 | M13: =L13*'00_START'!$B$12 -> 19.2 | N13: =WORKDAY('00_START'!$B$7-1,(G13-1)*5+1) -> 46335 | O13: =WORKDAY('00_START'!$B$7-1,H13*5) -> 46346 | P13: Chưa bắt đầu | Q13: 0 | R13: Check list click, focus chat, resize; kịch bản 30 giây đầu | S13: CL-029
A14: 2.6 | B14: T03-CL | C14: Nền tảng kỹ thuật | D14: Di chuyển, camera, va chạm và chọn mục tiêu | E14: CL | F14: 3 | G14: 5 | H14: 6 | I14: T02-CL, T02-AR | J14: 3 | K14: =J14*'00_START'!$B$10 -> 0.6 | L14: =J14+K14 -> 3.6 | M14: =L14*'00_START'!$B$12 -> 28.8 | N14: =WORKDAY('00_START'!$B$7-1,(G14-1)*5+1) -> 46335 | O14: =WORKDAY('00_START'!$B$7-1,H14*5) -> 46346 | P14: Chưa bắt đầu | Q14: 0 | R14: A*, camera bám, click marker, target vòng chọn | S14: CL-003, CL-004, CL-005
A15: 2.7 | B15: T03-SV | C15: Nền tảng kỹ thuật | D15: Room, quyền vào map và session lease | E15: SV | F15: 3 | G15: 5 | H15: 6 | I15: T02-SV | J15: 3 | K15: =J15*'00_START'!$B$10 -> 0.6 | L15: =J15+K15 -> 3.6 | M15: =L15*'00_START'!$B$12 -> 28.8 | N15: =WORKDAY('00_START'!$B$7-1,(G15-1)*5+1) -> 46335 | O15: =WORKDAY('00_START'!$B$7-1,H15*5) -> 46346 | P15: Chưa bắt đầu | Q15: 0 | R15: Join/leave có auth; single writer; giới hạn map | S15: SV-001, SV-004, SV-018
A16: 2.8 | B16: T03-AR | C16: Nền tảng kỹ thuật | D16: Bản đồ thị trấn và bố cục HUD | E16: AR | F16: 3 | G16: 5 | H16: 6 | I16: T02-AR | J16: 2.5 | K16: =J16*'00_START'!$B$10 -> 0.5 | L16: =J16+K16 -> 3 | M16: =L16*'00_START'!$B$12 -> 24 | N16: =WORKDAY('00_START'!$B$7-1,(G16-1)*5+1) -> 46335 | O16: =WORKDAY('00_START'!$B$7-1,H16*5) -> 46346 | P16: Chưa bắt đầu | Q16: 0 | R16: MAP-01; spawn/NPC/portal; HUD wireframe và icon nền | S16: CL-004
A17: 2.9 | B17: T04-GD | C17: Nền tảng kỹ thuật | D17: Gate G1 — thử hai client và lỗi mạng | E17: GD | F17: 4 | G17: 7 | H17: 8 | I17: T03-GD, T03-CL, T03-SV | J17: 2.5 | K17: =J17*'00_START'!$B$10 -> 0.5 | L17: =J17+K17 -> 3 | M17: =L17*'00_START'!$B$12 -> 24 | N17: =WORKDAY('00_START'!$B$7-1,(G17-1)*5+1) -> 46349 | O17: =WORKDAY('00_START'!$B$7-1,H17*5) -> 46360 | P17: Chưa bắt đầu | Q17: 0 | R17: Biên bản kiểm thử auth, chuyển map và mất kết nối
A18: 2.10 | B18: T04-CL | C18: Nền tảng kỹ thuật | D18: Tích hợp đồng bộ và nội suy | E18: CL | F18: 4 | G18: 7 | H18: 8 | I18: T03-CL, T03-SV | J18: 3 | K18: =J18*'00_START'!$B$10 -> 0.6 | L18: =J18+K18 -> 3.6 | M18: =L18*'00_START'!$B$12 -> 28.8 | N18: =WORKDAY('00_START'!$B$7-1,(G18-1)*5+1) -> 46349 | O18: =WORKDAY('00_START'!$B$7-1,H18*5) -> 46360 | P18: Chưa bắt đầu | Q18: 0 | R18: Remote players; correction; HUD mạng; không ghost entity | S18: CL-006, CL-009
A19: 2.11 | B19: T04-SV | C19: Nền tảng kỹ thuật | D19: Di chuyển authoritative và AOI | E19: SV | F19: 4 | G19: 7 | H19: 8 | I19: T03-SV, T03-CL | J19: 3 | K19: =J19*'00_START'!$B$10 -> 0.6 | L19: =J19+K19 -> 3.6 | M19: =L19*'00_START'!$B$12 -> 28.8 | N19: =WORKDAY('00_START'!$B$7-1,(G19-1)*5+1) -> 46349 | O19: =WORKDAY('00_START'!$B$7-1,H19*5) -> 46360 | P19: Chưa bắt đầu | Q19: 0 | R19: Validate đường đi/tốc độ; state lọc theo vùng; chống warp | S19: CL-003, SV-002, SV-003
A20: 2.12 | B20: T04-AR | C20: Nền tảng kỹ thuật | D20: Hoàn thiện HUD nền và feed back di chuyển | E20: AR | F20: 4 | G20: 7 | H20: 8 | I20: T03-AR | J20: 2.5 | K20: =J20*'00_START'!$B$10 -> 0.5 | L20: =J20+K20 -> 3 | M20: =L20*'00_START'!$B$12 -> 24 | N20: =WORKDAY('00_START'!$B$7-1,(G20-1)*5+1) -> 46349 | O20: =WORKDAY('00_START'!$B$7-1,H20*5) -> 46360 | P20: Chưa bắt đầu | Q20: 0 | R20: HP/mana/target/minimap; click/denied feed back
A21: 3.1 | B21: T05-GD | C21: PvE first playable | D21: Cân bằng 5 Cổ và combat test cases | E21: GD | F21: 5 | G21: 9 | H21: 10 | I21: T04-GD, T02-GD | J21: 2.5 | K21: =J21*'00_START'!$B$10 -> 0.5 | L21: =J21+K21 -> 3 | M21: =L21*'00_START'!$B$12 -> 24 | N21: =WORKDAY('00_START'!$B$7-1,(G21-1)*5+1) -> 46363 | O21: =WORKDAY('00_START'!$B$7-1,H21*5) -> 46374 | P21: Chưa bắt đầu | Q21: 0 | R21: Thông số sát thương, mana, CC, cooldown có đơn vị
A22: 3.2 | B22: T05-CL | C22: PvE first playable | D22: Combat UI và 5 kỹ năng đầu | E22: CL | F22: 5 | G22: 9 | H22: 10 | I22: T04-CL, T04-AR | J22: 3 | K22: =J22*'00_START'!$B$10 -> 0.6 | L22: =J22+K22 -> 3.6 | M22: =L22*'00_START'!$B$12 -> 28.8 | N22: =WORKDAY('00_START'!$B$7-1,(G22-1)*5+1) -> 46363 | O22: =WORKDAY('00_START'!$B$7-1,H22*5) -> 46374 | P22: Chưa bắt đầu | Q22: 0 | R22: QWER, chọn mục tiêu, telegraph, cooldown, hit feed back | S22: CL-007, CL-008, CL-009, CL-010
A23: 3.3 | B23: T05-SV | C23: PvE first playable | D23: Combat resolver và trạng thái | E23: SV | F23: 5 | G23: 9 | H23: 10 | I23: T04-SV | J23: 3 | K23: =J23*'00_START'!$B$10 -> 0.6 | L23: =J23+K23 -> 3.6 | M23: =L23*'00_START'!$B$12 -> 28.8 | N23: =WORKDAY('00_START'!$B$7-1,(G23-1)*5+1) -> 46363 | O23: =WORKDAY('00_START'!$B$7-1,H23*5) -> 46374 | P23: Chưa bắt đầu | Q23: 0 | R23: Range/LOS/cooldown/mana; damage, shield, slow, stun | S23: CL-008, CL-009, SV-002, SV-005
A24: 3.4 | B24: T05-AR | C24: PvE first playable | D24: VFX/SFX chiến đấu cơ sở | E24: AR | F24: 5 | G24: 9 | H24: 10 | I24: T04-AR | J24: 2.5 | K24: =J24*'00_START'!$B$10 -> 0.5 | L24: =J24+K24 -> 3 | M24: =L24*'00_START'!$B$12 -> 24 | N24: =WORKDAY('00_START'!$B$7-1,(G24-1)*5+1) -> 46363 | O24: =WORKDAY('00_START'!$B$7-1,H24*5) -> 46374 | P24: Chưa bắt đầu | Q24: 0 | R24: Projectile, impact, shield, warning; âm lượng và mute
A25: 3.5 | B25: T06-GD | C25: PvE first playable | D25: Gate G2 — vòng đánh quái và nhận thưởng | E25: GD | F25: 6 | G25: 11 | H25: 12 | I25: T05-GD, T05-CL, T05-SV | J25: 2.5 | K25: =J25*'00_START'!$B$10 -> 0.5 | L25: =J25+K25 -> 3 | M25: =L25*'00_START'!$B$12 -> 24 | N25: =WORKDAY('00_START'!$B$7-1,(G25-1)*5+1) -> 46377 | O25: =WORKDAY('00_START'!$B$7-1,H25*5) -> 46388 | P25: Chưa bắt đầu | Q25: 0 | R25: 10 phiên 15 phút; ghi TTK, lỗi; chưa đo retention dài hạn
A26: 3.6 | B26: T06-CL | C26: PvE first playable | D26: Quái, loot và chết/hồi sinh phía client | E26: CL | F26: 6 | G26: 11 | H26: 12 | I26: T05-CL | J26: 3 | K26: =J26*'00_START'!$B$10 -> 0.6 | L26: =J26+K26 -> 3.6 | M26: =L26*'00_START'!$B$12 -> 28.8 | N26: =WORKDAY('00_START'!$B$7-1,(G26-1)*5+1) -> 46377 | O26: =WORKDAY('00_START'!$B$7-1,H26*5) -> 46388 | P26: Chưa bắt đầu | Q26: 0 | R26: Nameplate, loot popup, respawn, NPC interaction | S26: CL-005, CL-011, CL-012
A27: 3.7 | B27: T06-SV | C27: PvE first playable | D27: AI quái, spawn, loot và hồi sinh | E27: SV | F27: 6 | G27: 11 | H27: 12 | I27: T05-SV | J27: 3 | K27: =J27*'00_START'!$B$10 -> 0.6 | L27: =J27+K27 -> 3.6 | M27: =L27*'00_START'!$B$12 -> 28.8 | N27: =WORKDAY('00_START'!$B$7-1,(G27-1)*5+1) -> 46377 | O27: =WORKDAY('00_START'!$B$7-1,H27*5) -> 46388 | P27: Chưa bắt đầu | Q27: 0 | R27: FSM idle/aggro/chase/attack/leash/dead; reward exactly once | S27: CL-011, CL-012, SV-006
A28: 3.8 | B28: T06-AR | C28: PvE first playable | D28: Map cày bãi và quái cơ sở | E28: AR | F28: 6 | G28: 11 | H28: 12 | I28: T05-AR | J28: 3 | K28: =J28*'00_START'!$B$10 -> 0.6 | L28: =J28+K28 -> 3.6 | M28: =L28*'00_START'!$B$12 -> 28.8 | N28: =WORKDAY('00_START'!$B$7-1,(G28-1)*5+1) -> 46377 | O28: =WORKDAY('00_START'!$B$7-1,H28*5) -> 46388 | P28: Chưa bắt đầu | Q28: 0 | R28: MAP-02; 6 loại quái dùng biến thể; điểm spawn và collision
A29: 4.1 | B29: T07-GD | C29: Vòng lặp Cổ và progression | D29: Thiết kế inventory, economy và dữ liệu Cổ | E29: GD | F29: 7 | G29: 13 | H29: 14 | I29: T06-GD | J29: 2.5 | K29: =J29*'00_START'!$B$10 -> 0.5 | L29: =J29+K29 -> 3 | M29: =L29*'00_START'!$B$12 -> 24 | N29: =WORKDAY('00_START'!$B$7-1,(G29-1)*5+1) -> 46391 | O29: =WORKDAY('00_START'!$B$7-1,H29*5) -> 46402 | P29: Chưa bắt đầu | Q29: 0 | R29: Catalog 20 Cổ/10 vật liệu; nguồn-tiêu; bộ test trùng lệnh
A30: 4.2 | B30: T07-CL | C30: Vòng lặp Cổ và progression | D30: Túi đồ, tooltip, trang bị Không Khiếu | E30: CL | F30: 7 | G30: 13 | H30: 14 | I30: T06-CL | J30: 3 | K30: =J30*'00_START'!$B$10 -> 0.6 | L30: =J30+K30 -> 3.6 | M30: =L30*'00_START'!$B$12 -> 28.8 | N30: =WORKDAY('00_START'!$B$7-1,(G30-1)*5+1) -> 46391 | O30: =WORKDAY('00_START'!$B$7-1,H30*5) -> 46402 | P30: Chưa bắt đầu | Q30: 0 | R30: 30 ô; drag/click equip; 4 active + 2 passive | S30: CL-007, CL-013, CL-014, CL-015
A31: 4.3 | B31: T07-SV | C31: Vòng lặp Cổ và progression | D31: Persistence inventory và giao dịch nội bộ | E31: SV | F31: 7 | G31: 13 | H31: 14 | I31: T06-SV | J31: 3 | K31: =J31*'00_START'!$B$10 -> 0.6 | L31: =J31+K31 -> 3.6 | M31: =L31*'00_START'!$B$12 -> 28.8 | N31: =WORKDAY('00_START'!$B$7-1,(G31-1)*5+1) -> 46391 | O31: =WORKDAY('00_START'!$B$7-1,H31*5) -> 46402 | P31: Chưa bắt đầu | Q31: 0 | R31: Lock/version; ledger; request ID; atomic reward/equip | S31: CL-012, CL-013, CL-014, CL-015, SV-007, SV-008, SV-009
A32: 4.4 | B32: T07-AR | C32: Vòng lặp Cổ và progression | D32: Icon Cổ và UI inventory | E32: AR | F32: 7 | G32: 13 | H32: 14 | I32: T06-AR | J32: 2.5 | K32: =J32*'00_START'!$B$10 -> 0.5 | L32: =J32+K32 -> 3 | M32: =L32*'00_START'!$B$12 -> 24 | N32: =WORKDAY('00_START'!$B$7-1,(G32-1)*5+1) -> 46391 | O32: =WORKDAY('00_START'!$B$7-1,H32*5) -> 46402 | P32: Chưa bắt đầu | Q32: 0 | R32: 20 icon + vật liệu; trạng thái khóa/đói/trang bị đọc rõ
A33: 4.5 | B33: T08-GD | C33: Vòng lặp Cổ và progression | D33: Luật bắt và nuôi Cổ, thử chi phí thức ăn | E33: GD | F33: 8 | G33: 15 | H33: 16 | I33: T07-GD, T07-SV | J33: 2.5 | K33: =J33*'00_START'!$B$10 -> 0.5 | L33: =J33+K33 -> 3 | M33: =L33*'00_START'!$B$12 -> 24 | N33: =WORKDAY('00_START'!$B$7-1,(G33-1)*5+1) -> 46405 | O33: =WORKDAY('00_START'!$B$7-1,H33*5) -> 46416 | P33: Chưa bắt đầu | Q33: 0 | R33: Cấu hình capture; hunger online; recovery; bộ test
A34: 4.6 | B34: T08-CL | C34: Vòng lặp Cổ và progression | D34: UI săn bắt và nuôi Cổ | E34: CL | F34: 8 | G34: 15 | H34: 16 | I34: T07-CL | J34: 3 | K34: =J34*'00_START'!$B$10 -> 0.6 | L34: =J34+K34 -> 3.6 | M34: =L34*'00_START'!$B$12 -> 28.8 | N34: =WORKDAY('00_START'!$B$7-1,(G34-1)*5+1) -> 46405 | O34: =WORKDAY('00_START'!$B$7-1,H34*5) -> 46416 | P34: Chưa bắt đầu | Q34: 0 | R34: Thanh channel bắt Cổ; xác nhận đồ ăn; preview phục hồi | S34: CL-016, CL-017
A35: 4.7 | B35: T08-SV | C35: Vòng lặp Cổ và progression | D35: Capture và feeding authoritative | E35: SV | F35: 8 | G35: 15 | H35: 16 | I35: T07-SV | J35: 3 | K35: =J35*'00_START'!$B$10 -> 0.6 | L35: =J35+K35 -> 3.6 | M35: =L35*'00_START'!$B$12 -> 28.8 | N35: =WORKDAY('00_START'!$B$7-1,(G35-1)*5+1) -> 46405 | O35: =WORKDAY('00_START'!$B$7-1,H35*5) -> 46416 | P35: Chưa bắt đầu | Q35: 0 | R35: Target claim; roll server; atomic seal/food/reward/hunger | S35: CL-016, CL-017, SV-006, SV-010
A36: 4.8 | B36: T08-AR | C36: Vòng lặp Cổ và progression | D36: Hiệu ứng bắt Cổ và NPC luyện/nuôi | E36: AR | F36: 8 | G36: 15 | H36: 16 | I36: T07-AR | J36: 2 | K36: =J36*'00_START'!$B$10 -> 0.4 | L36: =J36+K36 -> 2.4 | M36: =L36*'00_START'!$B$12 -> 19.2 | N36: =WORKDAY('00_START'!$B$7-1,(G36-1)*5+1) -> 46405 | O36: =WORKDAY('00_START'!$B$7-1,H36*5) -> 46416 | P36: Chưa bắt đầu | Q36: 0 | R36: Capture FX, NPC, UI hunger và màn thông báo
A37: 4.9 | B37: T09-GD | C37: Vòng lặp Cổ và progression | D37: Công thức luyện và xác suất minh bạch | E37: GD | F37: 9 | G37: 17 | H37: 18 | I37: T08-GD | J37: 2.5 | K37: =J37*'00_START'!$B$10 -> 0.5 | L37: =J37+K37 -> 3 | M37: =L37*'00_START'!$B$12 -> 24 | N37: =WORKDAY('00_START'!$B$7-1,(G37-1)*5+1) -> 46419 | O37: =WORKDAY('00_START'!$B$7-1,H37*5) -> 46430 | P37: Chưa bắt đầu | Q37: 0 | R37: 10 recipe; pity; 5.000 lượt mô phỏng trên dữ liệu nháp
A38: 4.10 | B38: T09-CL | C38: Vòng lặp Cổ và progression | D38: UI luyện Cổ và lịch sử kết quả | E38: CL | F38: 9 | G38: 17 | H38: 18 | I38: T08-CL | J38: 3 | K38: =J38*'00_START'!$B$10 -> 0.6 | L38: =J38+K38 -> 3.6 | M38: =L38*'00_START'!$B$12 -> 28.8 | N38: =WORKDAY('00_START'!$B$7-1,(G38-1)*5+1) -> 46419 | O38: =WORKDAY('00_START'!$B$7-1,H38*5) -> 46430 | P38: Chưa bắt đầu | Q38: 0 | R38: Chọn instance, recipe, preview tỷ lệ; request retry | S38: CL-018, CL-019
A39: 4.11 | B39: T09-SV | C39: Vòng lặp Cổ và progression | D39: Luyện Cổ transaction và idempotency | E39: SV | F39: 9 | G39: 17 | H39: 18 | I39: T08-SV | J39: 3 | K39: =J39*'00_START'!$B$10 -> 0.6 | L39: =J39+K39 -> 3.6 | M39: =L39*'00_START'!$B$12 -> 28.8 | N39: =WORKDAY('00_START'!$B$7-1,(G39-1)*5+1) -> 46419 | O39: =WORKDAY('00_START'!$B$7-1,H39*5) -> 46430 | P39: Chưa bắt đầu | Q39: 0 | R39: Atomic consume/RNG/pity/output/ledger; crash/retry tests | S39: CL-018, CL-019, SV-008, SV-011
A40: 4.12 | B40: T09-AR | C40: Vòng lặp Cổ và progression | D40: UI luyện Cổ và thông báo kết quả | E40: AR | F40: 9 | G40: 17 | H40: 18 | I40: T08-AR | J40: 2 | K40: =J40*'00_START'!$B$10 -> 0.4 | L40: =J40+K40 -> 2.4 | M40: =L40*'00_START'!$B$12 -> 19.2 | N40: =WORKDAY('00_START'!$B$7-1,(G40-1)*5+1) -> 46419 | O40: =WORKDAY('00_START'!$B$7-1,H40*5) -> 46430 | P40: Chưa bắt đầu | Q40: 0 | R40: Success/fail khác nhau; không chỉ phân biệt bằng màu
A41: 4.13 | B41: T10-GD | C41: Vòng lặp Cổ và progression | D41: Quest, cấp độ và thăng chuyển | E41: GD | F41: 10 | G41: 19 | H41: 20 | I41: T09-GD | J41: 2.5 | K41: =J41*'00_START'!$B$10 -> 0.5 | L41: =J41+K41 -> 3 | M41: =L41*'00_START'!$B$12 -> 24 | N41: =WORKDAY('00_START'!$B$7-1,(G41-1)*5+1) -> 46433 | O41: =WORKDAY('00_START'!$B$7-1,H41*5) -> 46444 | P41: Chưa bắt đầu | Q41: 0 | R41: 10 quest; level 1–20; rank I–II; XP curve
A42: 4.14 | B42: T10-CL | C42: Vòng lặp Cổ và progression | D42: Quest tracker, level up và NPC shop | E42: CL | F42: 10 | G42: 19 | H42: 20 | I42: T09-CL | J42: 3 | K42: =J42*'00_START'!$B$10 -> 0.6 | L42: =J42+K42 -> 3.6 | M42: =L42*'00_START'!$B$12 -> 28.8 | N42: =WORKDAY('00_START'!$B$7-1,(G42-1)*5+1) -> 46433 | O42: =WORKDAY('00_START'!$B$7-1,H42*5) -> 46444 | P42: Chưa bắt đầu | Q42: 0 | R42: Nhận/trả quest; shop fixed price; kiểm tra rank | S42: CL-020, CL-021, CL-022, CL-029, SV-009
A43: 4.15 | B43: T10-SV | C43: Vòng lặp Cổ và progression | D43: Quest/progression/NPC economy | E43: SV | F43: 10 | G43: 19 | H43: 20 | I43: T09-SV | J43: 3 | K43: =J43*'00_START'!$B$10 -> 0.6 | L43: =J43+K43 -> 3.6 | M43: =L43*'00_START'!$B$12 -> 28.8 | N43: =WORKDAY('00_START'!$B$7-1,(G43-1)*5+1) -> 46433 | O43: =WORKDAY('00_START'!$B$7-1,H43*5) -> 46444 | P43: Chưa bắt đầu | Q43: 0 | R43: Event quest; atomic claim/rank-up/buy/sell; caps | S43: CL-020, CL-021, CL-022, SV-008, SV-012
A44: 4.16 | B44: T10-AR | C44: Vòng lặp Cổ và progression | D44: Hoàn thiện map, NPC và props tái sử dụng | E44: AR | F44: 10 | G44: 19 | H44: 20 | I44: T09-AR | J44: 2.5 | K44: =J44*'00_START'!$B$10 -> 0.5 | L44: =J44+K44 -> 3 | M44: =L44*'00_START'!$B$12 -> 24 | N44: =WORKDAY('00_START'!$B$7-1,(G44-1)*5+1) -> 46433 | O44: =WORKDAY('00_START'!$B$7-1,H44*5) -> 46444 | P44: Chưa bắt đầu | Q44: 0 | R44: Town/farm đủ đường đi; 4 NPC; collision đã đánh dấu
A45: 4.17 | B45: T11-GD | C45: Vòng lặp Cổ và progression | D45: Cân bằng đầy đủ 20 Cổ và nguồn loot | E45: GD | F45: 11 | G45: 21 | H45: 22 | I45: T10-GD | J45: 3 | K45: =J45*'00_START'!$B$10 -> 0.6 | L45: =J45+K45 -> 3.6 | M45: =L45*'00_START'!$B$12 -> 28.8 | N45: =WORKDAY('00_START'!$B$7-1,(G45-1)*5+1) -> 46447 | O45: =WORKDAY('00_START'!$B$7-1,H45*5) -> 46458 | P45: Chưa bắt đầu | Q45: 0 | R45: 20 Cổ từ 8 primitive; 3 build khả thi; loot catalog | S45: CL-030
A46: 4.18 | B46: T11-CL | C46: Vòng lặp Cổ và progression | D46: Tích hợp đầy đủ Cổ, passive và codex | E46: CL | F46: 11 | G46: 21 | H46: 22 | I46: T10-CL | J46: 3 | K46: =J46*'00_START'!$B$10 -> 0.6 | L46: =J46+K46 -> 3.6 | M46: =L46*'00_START'!$B$12 -> 28.8 | N46: =WORKDAY('00_START'!$B$7-1,(G46-1)*5+1) -> 46447 | O46: =WORKDAY('00_START'!$B$7-1,H46*5) -> 46458 | P46: Chưa bắt đầu | Q46: 0 | R46: 20 Cổ data-driven; status icons; mô tả đầy đủ | S46: CL-007, CL-008, CL-010, CL-030
A47: 4.19 | B47: T11-SV | C47: Vòng lặp Cổ và progression | D47: Mở rộng effect primitives và content validator | E47: SV | F47: 11 | G47: 21 | H47: 22 | I47: T10-SV | J47: 3 | K47: =J47*'00_START'!$B$10 -> 0.6 | L47: =J47+K47 -> 3.6 | M47: =L47*'00_START'!$B$12 -> 28.8 | N47: =WORKDAY('00_START'!$B$7-1,(G47-1)*5+1) -> 46447 | O47: =WORKDAY('00_START'!$B$7-1,H47*5) -> 46458 | P47: Chưa bắt đầu | Q47: 0 | R47: 8 primitive; passive stack policy; schema/version checks | S47: CL-015, SV-005, SV-015
A48: 4.20 | B48: T11-AR | C48: Vòng lặp Cổ và progression | D48: Hoàn thiện icon, animation và status FX | E48: AR | F48: 11 | G48: 21 | H48: 22 | I48: T10-AR | J48: 2.5 | K48: =J48*'00_START'!$B$10 -> 0.5 | L48: =J48+K48 -> 3 | M48: =L48*'00_START'!$B$12 -> 24 | N48: =WORKDAY('00_START'!$B$7-1,(G48-1)*5+1) -> 46447 | O48: =WORKDAY('00_START'!$B$7-1,H48*5) -> 46458 | P48: Chưa bắt đầu | Q48: 0 | R48: Bộ icon final alpha; hit/death; FX dùng lại | S48: CL-010
A49: 4.21 | B49: T12-GD | C49: Vòng lặp Cổ và progression | D49: Gate G3 — E2E vòng Cổ | E49: GD | F49: 12 | G49: 23 | H49: 24 | I49: T11-GD, T11-CL, T11-SV | J49: 3 | K49: =J49*'00_START'!$B$10 -> 0.6 | L49: =J49+K49 -> 3.6 | M49: =L49*'00_START'!$B$12 -> 28.8 | N49: =WORKDAY('00_START'!$B$7-1,(G49-1)*5+1) -> 46461 | O49: =WORKDAY('00_START'!$B$7-1,H49*5) -> 46472 | P49: Chưa bắt đầu | Q49: 0 | R49: 20 tester nội bộ/luân phiên; capture→feed→craft→equip→fight
A50: 4.22 | B50: T12-CL | C50: Vòng lặp Cổ và progression | D50: Reconnect UI và E2E sửa lỗi client | E50: CL | F50: 12 | G50: 23 | H50: 24 | I50: T11-CL | J50: 3 | K50: =J50*'00_START'!$B$10 -> 0.6 | L50: =J50+K50 -> 3.6 | M50: =L50*'00_START'!$B$12 -> 28.8 | N50: =WORKDAY('00_START'!$B$7-1,(G50-1)*5+1) -> 46461 | O50: =WORKDAY('00_START'!$B$7-1,H50*5) -> 46472 | P50: Chưa bắt đầu | Q50: 0 | R50: Overlay mất mạng; resync bag/status; không gửi lệnh cũ | S50: CL-006, CL-027
A51: 4.23 | B51: T12-SV | C51: Vòng lặp Cổ và progression | D51: Reconnect, map handoff và crash recovery | E51: SV | F51: 12 | G51: 23 | H51: 24 | I51: T11-SV | J51: 3 | K51: =J51*'00_START'!$B$10 -> 0.6 | L51: =J51+K51 -> 3.6 | M51: =L51*'00_START'!$B$12 -> 28.8 | N51: =WORKDAY('00_START'!$B$7-1,(G51-1)*5+1) -> 46461 | O51: =WORKDAY('00_START'!$B$7-1,H51*5) -> 46472 | P51: Chưa bắt đầu | Q51: 0 | R51: Lease fencing; reserve/commit transfer; durable state resync | S51: CL-006, CL-027, SV-003, SV-004, SV-007
A52: 4.24 | B52: T12-AR | C52: Vòng lặp Cổ và progression | D52: Map phụ bản và boss blockout | E52: AR | F52: 12 | G52: 23 | H52: 24 | I52: T11-AR | J52: 2.5 | K52: =J52*'00_START'!$B$10 -> 0.5 | L52: =J52+K52 -> 3 | M52: =L52*'00_START'!$B$12 -> 24 | N52: =WORKDAY('00_START'!$B$7-1,(G52-1)*5+1) -> 46461 | O52: =WORKDAY('00_START'!$B$7-1,H52*5) -> 46472 | P52: Chưa bắt đầu | Q52: 0 | R52: MAP-03; arena tái dùng vùng; telegraph đủ khoảng né
A53: 5.1 | B53: T13-GD | C53: Nội dung multiplayer giới hạn | D53: Thiết kế party/boss/arena và QA matrix | E53: GD | F53: 13 | G53: 25 | H53: 26 | I53: T12-GD | J53: 2.5 | K53: =J53*'00_START'!$B$10 -> 0.5 | L53: =J53+K53 -> 3 | M53: =L53*'00_START'!$B$12 -> 24 | N53: =WORKDAY('00_START'!$B$7-1,(G53-1)*5+1) -> 46475 | O53: =WORKDAY('00_START'!$B$7-1,H53*5) -> 46486 | P53: Chưa bắt đầu | Q53: 0 | R53: Party 3; loot cá nhân; trận 1v1 không xếp hạng
A54: 5.2 | B54: T13-CL | C54: Nội dung multiplayer giới hạn | D54: Party và chat khu vực/party | E54: CL | F54: 13 | G54: 25 | H54: 26 | I54: T12-CL | J54: 3 | K54: =J54*'00_START'!$B$10 -> 0.6 | L54: =J54+K54 -> 3.6 | M54: =L54*'00_START'!$B$12 -> 28.8 | N54: =WORKDAY('00_START'!$B$7-1,(G54-1)*5+1) -> 46475 | O54: =WORKDAY('00_START'!$B$7-1,H54*5) -> 46486 | P54: Chưa bắt đầu | Q54: 0 | R54: Mời/đồng ý/rời; leader UI; mute/report; focus input | S54: CL-023, CL-024
A55: 5.3 | B55: T13-SV | C55: Nội dung multiplayer giới hạn | D55: Party state và chat có giới hạn | E55: SV | F55: 13 | G55: 25 | H55: 26 | I55: T12-SV | J55: 3 | K55: =J55*'00_START'!$B$10 -> 0.6 | L55: =J55+K55 -> 3.6 | M55: =L55*'00_START'!$B$12 -> 28.8 | N55: =WORKDAY('00_START'!$B$7-1,(G55-1)*5+1) -> 46475 | O55: =WORKDAY('00_START'!$B$7-1,H55*5) -> 46486 | P55: Chưa bắt đầu | Q55: 0 | R55: Membership; invite TTL; rate limit; server recipient filter | S55: CL-023, CL-024, SV-013
A56: 5.4 | B56: T13-AR | C56: Nội dung multiplayer giới hạn | D56: Sprite boss và quái tinh anh | E56: AR | F56: 13 | G56: 25 | H56: 26 | I56: T12-AR | J56: 3 | K56: =J56*'00_START'!$B$10 -> 0.6 | L56: =J56+K56 -> 3.6 | M56: =L56*'00_START'!$B$12 -> 28.8 | N56: =WORKDAY('00_START'!$B$7-1,(G56-1)*5+1) -> 46475 | O56: =WORKDAY('00_START'!$B$7-1,H56*5) -> 46486 | P56: Chưa bắt đầu | Q56: 0 | R56: 1 boss/2 elite biến thể; windup/attack/death
A57: 5.5 | B57: T14-GD | C57: Nội dung multiplayer giới hạn | D57: Kiểm thử phụ bản và reward chống lặp | E57: GD | F57: 14 | G57: 27 | H57: 28 | I57: T13-GD, T13-CL, T13-SV | J57: 2.5 | K57: =J57*'00_START'!$B$10 -> 0.5 | L57: =J57+K57 -> 3 | M57: =L57*'00_START'!$B$12 -> 24 | N57: =WORKDAY('00_START'!$B$7-1,(G57-1)*5+1) -> 46489 | O57: =WORKDAY('00_START'!$B$7-1,H57*5) -> 46500 | P57: Chưa bắt đầu | Q57: 0 | R57: 10 run đủ/thất bại/disconnect; ledger cá nhân
A58: 5.6 | B58: T14-CL | C58: Nội dung multiplayer giới hạn | D58: Phụ bản và boss UI/telegraph | E58: CL | F58: 14 | G58: 27 | H58: 28 | I58: T13-CL, T13-AR | J58: 3 | K58: =J58*'00_START'!$B$10 -> 0.6 | L58: =J58+K58 -> 3.6 | M58: =L58*'00_START'!$B$12 -> 28.8 | N58: =WORKDAY('00_START'!$B$7-1,(G58-1)*5+1) -> 46489 | O58: =WORKDAY('00_START'!$B$7-1,H58*5) -> 46500 | P58: Chưa bắt đầu | Q58: 0 | R58: Entry vote, boss HP, kết quả; AoE dễ đọc | S58: CL-025
A59: 5.7 | B59: T14-SV | C59: Nội dung multiplayer giới hạn | D59: Dungeon instance, boss và personal reward | E59: SV | F59: 14 | G59: 27 | H59: 28 | I59: T13-SV | J59: 3 | K59: =J59*'00_START'!$B$10 -> 0.6 | L59: =J59+K59 -> 3.6 | M59: =L59*'00_START'!$B$12 -> 28.8 | N59: =WORKDAY('00_START'!$B$7-1,(G59-1)*5+1) -> 46489 | O59: =WORKDAY('00_START'!$B$7-1,H59*5) -> 46500 | P59: Chưa bắt đầu | Q59: 0 | R59: 3 người/15 phút; boss 2 pattern; run ID; cleanup | S59: CL-025, SV-014
A60: 5.8 | B60: T14-AR | C60: Nội dung multiplayer giới hạn | D60: Boss VFX, dungeon props và âm thanh | E60: AR | F60: 14 | G60: 27 | H60: 28 | I60: T13-AR | J60: 2.5 | K60: =J60*'00_START'!$B$10 -> 0.5 | L60: =J60+K60 -> 3 | M60: =L60*'00_START'!$B$12 -> 24 | N60: =WORKDAY('00_START'!$B$7-1,(G60-1)*5+1) -> 46489 | O60: =WORKDAY('00_START'!$B$7-1,H60*5) -> 46500 | P60: Chưa bắt đầu | Q60: 0 | R60: 2 telegraph boss; ambient dùng lại; music mute
A61: 5.9 | B61: T15-GD | C61: Nội dung multiplayer giới hạn | D61: Gate G4 — multiplayer và PvP | E61: GD | F61: 15 | G61: 29 | H61: 30 | I61: T14-GD, T14-CL, T14-SV | J61: 2.5 | K61: =J61*'00_START'!$B$10 -> 0.5 | L61: =J61+K61 -> 3 | M61: =L61*'00_START'!$B$12 -> 24 | N61: =WORKDAY('00_START'!$B$7-1,(G61-1)*5+1) -> 46503 | O61: =WORKDAY('00_START'!$B$7-1,H61*5) -> 46514 | P61: Chưa bắt đầu | Q61: 0 | R61: Party 3; dungeon; 1v1; quyết định cắt phạm vi nếu trễ
A62: 5.10 | B62: T15-CL | C62: Nội dung multiplayer giới hạn | D62: Đấu tay đôi opt-in và kết quả | E62: CL | F62: 15 | G62: 29 | H62: 30 | I62: T14-CL | J62: 3 | K62: =J62*'00_START'!$B$10 -> 0.6 | L62: =J62+K62 -> 3.6 | M62: =L62*'00_START'!$B$12 -> 28.8 | N62: =WORKDAY('00_START'!$B$7-1,(G62-1)*5+1) -> 46503 | O62: =WORKDAY('00_START'!$B$7-1,H62*5) -> 46514 | P62: Chưa bắt đầu | Q62: 0 | R62: Invite/ready/countdown/result; quay lại safe spawn | S62: CL-026
A63: 5.11 | B63: T15-SV | C63: Nội dung multiplayer giới hạn | D63: Arena PvP, timer và disconnect policy | E63: SV | F63: 15 | G63: 29 | H63: 30 | I63: T14-SV | J63: 3 | K63: =J63*'00_START'!$B$10 -> 0.6 | L63: =J63+K63 -> 3.6 | M63: =L63*'00_START'!$B$12 -> 28.8 | N63: =WORKDAY('00_START'!$B$7-1,(G63-1)*5+1) -> 46503 | O63: =WORKDAY('00_START'!$B$7-1,H63*5) -> 46514 | P63: Chưa bắt đầu | Q63: 0 | R63: Two opt-ins; PvP damage factor; no reward farming | S63: CL-026, SV-014
A64: 5.12 | B64: T15-AR | C64: Nội dung multiplayer giới hạn | D64: Arena/UI social và độ đọc hình | E64: AR | F64: 15 | G64: 29 | H64: 30 | I64: T14-AR | J64: 2 | K64: =J64*'00_START'!$B$10 -> 0.4 | L64: =J64+K64 -> 2.4 | M64: =L64*'00_START'!$B$12 -> 19.2 | N64: =WORKDAY('00_START'!$B$7-1,(G64-1)*5+1) -> 46503 | O64: =WORKDAY('00_START'!$B$7-1,H64*5) -> 46514 | P64: Chưa bắt đầu | Q64: 0 | R64: Arena từ tileset có sẵn; silhouette/telegraph/party colors
A65: 6.1 | B65: T16-GD | C65: Ổn định và closed alpha | D65: Feature freeze, UAT plan và hướng dẫn tester | E65: GD | F65: 16 | G65: 31 | H65: 32 | I65: T15-GD, T15-CL, T15-SV | J65: 3 | K65: =J65*'00_START'!$B$10 -> 0.6 | L65: =J65+K65 -> 3.6 | M65: =L65*'00_START'!$B$12 -> 28.8 | N65: =WORKDAY('00_START'!$B$7-1,(G65-1)*5+1) -> 46517 | O65: =WORKDAY('00_START'!$B$7-1,H65*5) -> 46528 | P65: Chưa bắt đầu | Q65: 0 | R65: Traceability đóng; check list NFR; test accounts/instructions | S65: CL-029
A66: 6.2 | B66: T16-CL | C66: Ổn định và closed alpha | D66: Admin UI tối thiểu và settings client | E66: CL | F66: 16 | G66: 31 | H66: 32 | I66: T15-CL | J66: 3 | K66: =J66*'00_START'!$B$10 -> 0.6 | L66: =J66+K66 -> 3.6 | M66: =L66*'00_START'!$B$12 -> 28.8 | N66: =WORKDAY('00_START'!$B$7-1,(G66-1)*5+1) -> 46517 | O66: =WORKDAY('00_START'!$B$7-1,H66*5) -> 46528 | P66: Chưa bắt đầu | Q66: 0 | R66: GM tra cứu/read-only; âm lượng/phím/đồ họa; role guard | S66: CL-028, AD-001, AD-002, AD-003, AD-004, AD-006
A67: 6.3 | B67: T16-SV | C67: Ổn định và closed alpha | D67: GM API, audit, metrics và backup jobs | E67: SV | F67: 16 | G67: 31 | H67: 32 | I67: T15-SV | J67: 3 | K67: =J67*'00_START'!$B$10 -> 0.6 | L67: =J67+K67 -> 3.6 | M67: =L67*'00_START'!$B$12 -> 28.8 | N67: =WORKDAY('00_START'!$B$7-1,(G67-1)*5+1) -> 46517 | O67: =WORKDAY('00_START'!$B$7-1,H67*5) -> 46528 | P67: Chưa bắt đầu | Q67: 0 | R67: RBAC/mute/ban/grant; config publish; daily snapshot | S67: CL-024, SV-013, SV-015, SV-016, SV-017, AD-001, AD-002, AD-003, AD-004, AD-005, AD-006, AD-007
A68: 6.4 | B68: T16-AR | C68: Ổn định và closed alpha | D68: Polish HUD, feed back và asset audit | E68: AR | F68: 16 | G68: 31 | H68: 32 | I68: T15-AR | J68: 2.5 | K68: =J68*'00_START'!$B$10 -> 0.5 | L68: =J68+K68 -> 3 | M68: =L68*'00_START'!$B$12 -> 24 | N68: =WORKDAY('00_START'!$B$7-1,(G68-1)*5+1) -> 46517 | O68: =WORKDAY('00_START'!$B$7-1,H68*5) -> 46528 | P68: Chưa bắt đầu | Q68: 0 | R68: UI thống nhất; lỗi/thành công; file và nguồn asset đầy đủ | S68: CL-028
A69: 6.5 | B69: T17-GD | C69: Ổn định và closed alpha | D69: UAT, soak test phối hợp và phân loại lỗi | E69: GD | F69: 17 | G69: 33 | H69: 34 | I69: T16-GD, T16-CL, T16-SV | J69: 3 | K69: =J69*'00_START'!$B$10 -> 0.6 | L69: =J69+K69 -> 3.6 | M69: =L69*'00_START'!$B$12 -> 28.8 | N69: =WORKDAY('00_START'!$B$7-1,(G69-1)*5+1) -> 46531 | O69: =WORKDAY('00_START'!$B$7-1,H69*5) -> 46542 | P69: Chưa bắt đầu | Q69: 0 | R69: 20 tester; 50 bots/2 giờ; 3 build; lỗi P0/P1 về 0
A70: 6.6 | B70: T17-CL | C70: Ổn định và closed alpha | D70: Tối ưu client và sửa lỗi UAT | E70: CL | F70: 17 | G70: 33 | H70: 34 | I70: T16-CL | J70: 3 | K70: =J70*'00_START'!$B$10 -> 0.6 | L70: =J70+K70 -> 3.6 | M70: =L70*'00_START'!$B$12 -> 28.8 | N70: =WORKDAY('00_START'!$B$7-1,(G70-1)*5+1) -> 46531 | O70: =WORKDAY('00_START'!$B$7-1,H70*5) -> 46542 | P70: Chưa bắt đầu | Q70: 0 | R70: FPS p95 frame time; asset budget; Windows matrix và Web spike
A71: 6.7 | B71: T17-SV | C71: Ổn định và closed alpha | D71: Load/fault/security và tối ưu server | E71: SV | F71: 17 | G71: 33 | H71: 34 | I71: T16-SV | J71: 3 | K71: =J71*'00_START'!$B$10 -> 0.6 | L71: =J71+K71 -> 3.6 | M71: =L71*'00_START'!$B$12 -> 28.8 | N71: =WORKDAY('00_START'!$B$7-1,(G71-1)*5+1) -> 46531 | O71: =WORKDAY('00_START'!$B$7-1,H71*5) -> 46542 | P71: Chưa bắt đầu | Q71: 0 | R71: 50 CCU toàn shard/20 map; duplicate, kill/restart, expiry | S71: SV-016, SV-018
A72: 6.8 | B72: T17-AR | C72: Ổn định và closed alpha | D72: Atlas, compression và pass đọc hình | E72: AR | F72: 17 | G72: 33 | H72: 34 | I72: T16-AR | J72: 2.5 | K72: =J72*'00_START'!$B$10 -> 0.5 | L72: =J72+K72 -> 3 | M72: =L72*'00_START'!$B$12 -> 24 | N72: =WORKDAY('00_START'!$B$7-1,(G72-1)*5+1) -> 46531 | O72: =WORKDAY('00_START'!$B$7-1,H72*5) -> 46542 | P72: Chưa bắt đầu | Q72: 0 | R72: Đo payload, giảm overdraw; font/contrast/audio review
A73: 6.9 | B73: T18-GD | C73: Ổn định và closed alpha | D73: Gate G5 — release check list và alpha report | E73: GD | F73: 18 | G73: 35 | H73: 36 | I73: T17-GD, T17-CL, T17-SV, T17-AR | J73: 3 | K73: =J73*'00_START'!$B$10 -> 0.6 | L73: =J73+K73 -> 3.6 | M73: =L73*'00_START'!$B$12 -> 28.8 | N73: =WORKDAY('00_START'!$B$7-1,(G73-1)*5+1) -> 46545 | O73: =WORKDAY('00_START'!$B$7-1,H73*5) -> 46556 | P73: Chưa bắt đầu | Q73: 0 | R73: NFR/UAT có evidence; lịch beta; go/no-go; báo cáo 7 ngày
A74: 6.10 | B74: T18-CL | C74: Ổn định và closed alpha | D74: Release candidate và sửa lỗi phát hành | E74: CL | F74: 18 | G74: 35 | H74: 36 | I74: T17-CL | J74: 3 | K74: =J74*'00_START'!$B$10 -> 0.6 | L74: =J74+K74 -> 3.6 | M74: =L74*'00_START'!$B$12 -> 28.8 | N74: =WORKDAY('00_START'!$B$7-1,(G74-1)*5+1) -> 46545 | O74: =WORKDAY('00_START'!$B$7-1,H74*5) -> 46556 | P74: Chưa bắt đầu | Q74: 0 | R74: Client RC tag; smoke test; known issues; rollback compatible
A75: 6.11 | B75: T18-SV | C75: Ổn định và closed alpha | D75: Restore drill, deploy và runbook | E75: SV | F75: 18 | G75: 35 | H75: 36 | I75: T17-SV | J75: 3 | K75: =J75*'00_START'!$B$10 -> 0.6 | L75: =J75+K75 -> 3.6 | M75: =L75*'00_START'!$B$12 -> 28.8 | N75: =WORKDAY('00_START'!$B$7-1,(G75-1)*5+1) -> 46545 | O75: =WORKDAY('00_START'!$B$7-1,H75*5) -> 46556 | P75: Chưa bắt đầu | Q75: 0 | R75: Staging→private alpha; restore đo RPO/RTO; rollback diễn tập | S75: SV-017, AD-005
A76: 6.12 | B76: T18-AR | C76: Ổn định và closed alpha | D76: Hoàn tất asset và gói giới thiệu alpha | E76: AR | F76: 18 | G76: 35 | H76: 36 | I76: T17-AR | J76: 2 | K76: =J76*'00_START'!$B$10 -> 0.4 | L76: =J76+K76 -> 2.4 | M76: =L76*'00_START'!$B$12 -> 19.2 | N76: =WORKDAY('00_START'!$B$7-1,(G76-1)*5+1) -> 46545 | O76: =WORKDAY('00_START'!$B$7-1,H76*5) -> 46556 | P76: Chưa bắt đầu | Q76: 0 | R76: Asset manifest, credits; screenshot, hướng dẫn hiển thị

Sheet 14_GANTT
A1: 14 / Lịch theo tuần
A2: Ô màu xanh=khung thực hiện; không phải số ngày full time. Mỗi owner 1 package/sprint và review chéo từ 25% thời gian không hữu ích.
A4: Task ID | B4: Work package | C4: Owner | D4: Start week | E4: End week | F4: 1 | G4: 2 | H4: 3 | I4: 4 | J4: 5 | K4: 6 | L4: 7 | M4: 8 | N4: 9 | O4: 10 | P4: 11 | Q4: 12 | R4: 13 | S4: 14 | T4: 15 | U4: 16 | V4: 17 | W4: 18 | X4: 19 | Y4: 20 | Z4: 21 | AA4: 22 | AB4: 23 | AC4: 24 | AD4: 25 | AE4: 26 | AF4: 27 | AG4: 28 | AH4: 29 | AI4: 30 | AJ4: 31 | AK4: 32 | AL4: 33 | AM4: 34 | AN4: 35 | AO4: 36
A5: T01-GD | B5: Khóa MVP, FSD và danh sách quyết định | C5: GD | D5: ='13_WBS'!G5 -> 1 | E5: ='13_WBS'!H5 -> 2 | F5: =IF(AND(F$4>=$D5,F$4<=$E5),1,0) -> 1 | G5: =IF(AND(G$4>=$D5,G$4<=$E5),1,0) -> 1 | H5: =IF(AND(H$4>=$D5,H$4<=$E5),1,0) -> 0 | I5: =IF(AND(I$4>=$D5,I$4<=$E5),1,0) -> 0 | J5: =IF(AND(J$4>=$D5,J$4<=$E5),1,0) -> 0 | K5: =IF(AND(K$4>=$D5,K$4<=$E5),1,0) -> 0 | L5: =IF(AND(L$4>=$D5,L$4<=$E5),1,0) -> 0 | M5: =IF(AND(M$4>=$D5,M$4<=$E5),1,0) -> 0 | ... AO5: =IF(AND(AO$4>=$D5,AO$4<=$E5),1,0) -> 0
A6: T01-CL | B6: Spike Godot isometric trên PC; thử Web export | C6: CL | D6: ='13_WBS'!G6 -> 1 | E6: ='13_WBS'!H6 -> 2 | F6: =IF(AND(F$4>=$D6,F$4<=$E6),1,0) -> 1 | G6: =IF(AND(G$4>=$D6,G$4<=$E6),1,0) -> 1 | H6: =IF(AND(H$4>=$D6,H$4<=$E6),1,0) -> 0 | I6: =IF(AND(I$4>=$D6,I$4<=$E6),1,0) -> 0 | J6: =IF(AND(J$4>=$D6,J$4<=$E6),1,0) -> 0 | K6: =IF(AND(K$4>=$D6,K$4<=$E6),1,0) -> 0 | L6: =IF(AND(L$4>=$D6,L$4<=$E6),1,0) -> 0 | M6: =IF(AND(M$4>=$D6,M$4<=$E6),1,0) -> 0 | ... AO6: =IF(AND(AO$4>=$D6,AO$4<=$E6),1,0) -> 0
A7: T01-SV | B7: Spike authoritative room và lưu dữ liệu | C7: SV | D7: ='13_WBS'!G7 -> 1 | E7: ='13_WBS'!H7 -> 2 | F7: =IF(AND(F$4>=$D7,F$4<=$E7),1,0) -> 1 | G7: =IF(AND(G$4>=$D7,G$4<=$E7),1,0) -> 1 | H7: =IF(AND(H$4>=$D7,H$4<=$E7),1,0) -> 0 | I7: =IF(AND(I$4>=$D7,I$4<=$E7),1,0) -> 0 | J7: =IF(AND(J$4>=$D7,J$4<=$E7),1,0) -> 0 | K7: =IF(AND(K$4>=$D7,K$4<=$E7),1,0) -> 0 | L7: =IF(AND(L$4>=$D7,L$4<=$E7),1,0) -> 0 | M7: =IF(AND(M$4>=$D7,M$4<=$E7),1,0) -> 0 | ... AO7: =IF(AND(AO$4>=$D7,AO$4<=$E7),1,0) -> 0
A8: T01-AR | B8: Art direction và kiểm kê tài nguyên | C8: AR | D8: ='13_WBS'!G8 -> 1 | E8: ='13_WBS'!H8 -> 2 | F8: =IF(AND(F$4>=$D8,F$4<=$E8),1,0) -> 1 | G8: =IF(AND(G$4>=$D8,G$4<=$E8),1,0) -> 1 | H8: =IF(AND(H$4>=$D8,H$4<=$E8),1,0) -> 0 | I8: =IF(AND(I$4>=$D8,I$4<=$E8),1,0) -> 0 | J8: =IF(AND(J$4>=$D8,J$4<=$E8),1,0) -> 0 | K8: =IF(AND(K$4>=$D8,K$4<=$E8),1,0) -> 0 | L8: =IF(AND(L$4>=$D8,L$4<=$E8),1,0) -> 0 | M8: =IF(AND(M$4>=$D8,M$4<=$E8),1,0) -> 0 | ... AO8: =IF(AND(AO$4>=$D8,AO$4<=$E8),1,0) -> 0
A9: T02-GD | B9: Chốt luật chiến đấu và mô hình dữ liệu | C9: GD | D9: ='13_WBS'!G9 -> 3 | E9: ='13_WBS'!H9 -> 4 | F9: =IF(AND(F$4>=$D9,F$4<=$E9),1,0) -> 0 | G9: =IF(AND(G$4>=$D9,G$4<=$E9),1,0) -> 0 | H9: =IF(AND(H$4>=$D9,H$4<=$E9),1,0) -> 1 | I9: =IF(AND(I$4>=$D9,I$4<=$E9),1,0) -> 1 | J9: =IF(AND(J$4>=$D9,J$4<=$E9),1,0) -> 0 | K9: =IF(AND(K$4>=$D9,K$4<=$E9),1,0) -> 0 | L9: =IF(AND(L$4>=$D9,L$4<=$E9),1,0) -> 0 | M9: =IF(AND(M$4>=$D9,M$4<=$E9),1,0) -> 0 | ... AO9: =IF(AND(AO$4>=$D9,AO$4<=$E9),1,0) -> 0
A10: T02-CL | B10: Client shell, scene và tọa độ | C10: CL | D10: ='13_WBS'!G10 -> 3 | E10: ='13_WBS'!H10 -> 4 | F10: =IF(AND(F$4>=$D10,F$4<=$E10),1,0) -> 0 | G10: =IF(AND(G$4>=$D10,G$4<=$E10),1,0) -> 0 | H10: =IF(AND(H$4>=$D10,H$4<=$E10),1,0) -> 1 | I10: =IF(AND(I$4>=$D10,I$4<=$E10),1,0) -> 1 | J10: =IF(AND(J$4>=$D10,J$4<=$E10),1,0) -> 0 | K10: =IF(AND(K$4>=$D10,K$4<=$E10),1,0) -> 0 | L10: =IF(AND(L$4>=$D10,L$4<=$E10),1,0) -> 0 | M10: =IF(AND(M$4>=$D10,M$4<=$E10),1,0) -> 0 | ... AO10: =IF(AND(AO$4>=$D10,AO$4<=$E10),1,0) -> 0
A11: T02-SV | B11: Repo, CI, schema và đăng nhập | C11: SV | D11: ='13_WBS'!G11 -> 3 | E11: ='13_WBS'!H11 -> 4 | F11: =IF(AND(F$4>=$D11,F$4<=$E11),1,0) -> 0 | G11: =IF(AND(G$4>=$D11,G$4<=$E11),1,0) -> 0 | H11: =IF(AND(H$4>=$D11,H$4<=$E11),1,0) -> 1 | I11: =IF(AND(I$4>=$D11,I$4<=$E11),1,0) -> 1 | J11: =IF(AND(J$4>=$D11,J$4<=$E11),1,0) -> 0 | K11: =IF(AND(K$4>=$D11,K$4<=$E11),1,0) -> 0 | L11: =IF(AND(L$4>=$D11,L$4<=$E11),1,0) -> 0 | M11: =IF(AND(M$4>=$D11,M$4<=$E11),1,0) -> 0 | ... AO11: =IF(AND(AO$4>=$D11,AO$4<=$E11),1,0) -> 0
A12: T02-AR | B12: Nhân vật và tileset cơ sở | C12: AR | D12: ='13_WBS'!G12 -> 3 | E12: ='13_WBS'!H12 -> 4 | F12: =IF(AND(F$4>=$D12,F$4<=$E12),1,0) -> 0 | G12: =IF(AND(G$4>=$D12,G$4<=$E12),1,0) -> 0 | H12: =IF(AND(H$4>=$D12,H$4<=$E12),1,0) -> 1 | I12: =IF(AND(I$4>=$D12,I$4<=$E12),1,0) -> 1 | J12: =IF(AND(J$4>=$D12,J$4<=$E12),1,0) -> 0 | K12: =IF(AND(K$4>=$D12,K$4<=$E12),1,0) -> 0 | L12: =IF(AND(L$4>=$D12,L$4<=$E12),1,0) -> 0 | M12: =IF(AND(M$4>=$D12,M$4<=$E12),1,0) -> 0 | ... AO12: =IF(AND(AO$4>=$D12,AO$4<=$E12),1,0) -> 0
A13: T03-GD | B13: Kiểm thử điều khiển và onboarding | C13: GD | D13: ='13_WBS'!G13 -> 5 | E13: ='13_WBS'!H13 -> 6 | F13: =IF(AND(F$4>=$D13,F$4<=$E13),1,0) -> 0 | G13: =IF(AND(G$4>=$D13,G$4<=$E13),1,0) -> 0 | H13: =IF(AND(H$4>=$D13,H$4<=$E13),1,0) -> 0 | I13: =IF(AND(I$4>=$D13,I$4<=$E13),1,0) -> 0 | J13: =IF(AND(J$4>=$D13,J$4<=$E13),1,0) -> 1 | K13: =IF(AND(K$4>=$D13,K$4<=$E13),1,0) -> 1 | L13: =IF(AND(L$4>=$D13,L$4<=$E13),1,0) -> 0 | M13: =IF(AND(M$4>=$D13,M$4<=$E13),1,0) -> 0 | ... AO13: =IF(AND(AO$4>=$D13,AO$4<=$E13),1,0) -> 0
A14: T03-CL | B14: Di chuyển, camera, va chạm và chọn mục tiêu | C14: CL | D14: ='13_WBS'!G14 -> 5 | E14: ='13_WBS'!H14 -> 6 | F14: =IF(AND(F$4>=$D14,F$4<=$E14),1,0) -> 0 | G14: =IF(AND(G$4>=$D14,G$4<=$E14),1,0) -> 0 | H14: =IF(AND(H$4>=$D14,H$4<=$E14),1,0) -> 0 | I14: =IF(AND(I$4>=$D14,I$4<=$E14),1,0) -> 0 | J14: =IF(AND(J$4>=$D14,J$4<=$E14),1,0) -> 1 | K14: =IF(AND(K$4>=$D14,K$4<=$E14),1,0) -> 1 | L14: =IF(AND(L$4>=$D14,L$4<=$E14),1,0) -> 0 | M14: =IF(AND(M$4>=$D14,M$4<=$E14),1,0) -> 0 | ... AO14: =IF(AND(AO$4>=$D14,AO$4<=$E14),1,0) -> 0
A15: T03-SV | B15: Room, quyền vào map và session lease | C15: SV | D15: ='13_WBS'!G15 -> 5 | E15: ='13_WBS'!H15 -> 6 | F15: =IF(AND(F$4>=$D15,F$4<=$E15),1,0) -> 0 | G15: =IF(AND(G$4>=$D15,G$4<=$E15),1,0) -> 0 | H15: =IF(AND(H$4>=$D15,H$4<=$E15),1,0) -> 0 | I15: =IF(AND(I$4>=$D15,I$4<=$E15),1,0) -> 0 | J15: =IF(AND(J$4>=$D15,J$4<=$E15),1,0) -> 1 | K15: =IF(AND(K$4>=$D15,K$4<=$E15),1,0) -> 1 | L15: =IF(AND(L$4>=$D15,L$4<=$E15),1,0) -> 0 | M15: =IF(AND(M$4>=$D15,M$4<=$E15),1,0) -> 0 | ... AO15: =IF(AND(AO$4>=$D15,AO$4<=$E15),1,0) -> 0
A16: T03-AR | B16: Bản đồ thị trấn và bố cục HUD | C16: AR | D16: ='13_WBS'!G16 -> 5 | E16: ='13_WBS'!H16 -> 6 | F16: =IF(AND(F$4>=$D16,F$4<=$E16),1,0) -> 0 | G16: =IF(AND(G$4>=$D16,G$4<=$E16),1,0) -> 0 | H16: =IF(AND(H$4>=$D16,H$4<=$E16),1,0) -> 0 | I16: =IF(AND(I$4>=$D16,I$4<=$E16),1,0) -> 0 | J16: =IF(AND(J$4>=$D16,J$4<=$E16),1,0) -> 1 | K16: =IF(AND(K$4>=$D16,K$4<=$E16),1,0) -> 1 | L16: =IF(AND(L$4>=$D16,L$4<=$E16),1,0) -> 0 | M16: =IF(AND(M$4>=$D16,M$4<=$E16),1,0) -> 0 | ... AO16: =IF(AND(AO$4>=$D16,AO$4<=$E16),1,0) -> 0
... A76: T18-AR | B76: Hoàn tất asset và gói giới thiệu alpha | C76: AR | D76: ='13_WBS'!G76 -> 35 | E76: ='13_WBS'!H76 -> 36 | F76: =IF(AND(F$4>=$D76,F$4<=$E76),1,0) -> 0 | G76: =IF(AND(G$4>=$D76,G$4<=$E76),1,0) -> 0 | H76: =IF(AND(H$4>=$D76,H$4<=$E76),1,0) -> 0 | I76: =IF(AND(I$4>=$D76,I$4<=$E76),1,0) -> 0 | J76: =IF(AND(J$4>=$D76,J$4<=$E76),1,0) -> 0 | K76: =IF(AND(K$4>=$D76,K$4<=$E76),1,0) -> 0 | L76: =IF(AND(L$4>=$D76,L$4<=$E76),1,0) -> 0 | M76: =IF(AND(M$4>=$D76,M$4<=$E76),1,0) -> 0 | ... AO76: =IF(AND(AO$4>=$D76,AO$4<=$E76),1,0) -> 1

Sheet 15_GATES
A1: 15 / Milestones & Exit Criteria
A2: Gate chỉ pass khi có evidence; thất bại→sử dụng dự phòng/cắt phạm vi/rebaseline. Mốc kết thúc minh họa được dịch từ 00_START!B7.
A4: Gate | B4: End sprint | C4: Mốc | D4: Ngày minh họa | E4: Exit criteria | F4: Sign-off owner | G4: Nếu chưa đạt | H4: Status | I4: Evidence / Notes
A5: G0 | B5: 2 | C5: Tuần 4 — Baseline khả thi | D5: =WORKDAY('00_START'!$B$7-1,B5*10) -> 46332 | E5: FSD/WBS/luật/availability/art nguồn rõ; stack spike 2 client; chốt hoặc giảm scope | F5: GD+CL+SV+AR | G5: Không khả thi giờ/stack→cắt content/đổi nền trước G1 | H5: Chưa đánh giá
A6: G1 | B6: 4 | C6: Tuần 8 — Multiplayer nền | D6: =WORKDAY('00_START'!$B$7-1,B6*10) -> 46360 | E6: Click/movement/auth/room/AOI;2 client; reject warp; handoff happy path | F6: CL+SV; GD kiểm tra | G6: Chưa cóauthoritative movement→không xây content thêm | H6: Chưa đánh giá
A7: G2 | B7: 6 | C7: Tuần 12 — First playable | D7: =WORKDAY('00_START'!$B$7-1,B7*10) -> 46388 | E7: Town/farm,5 Cổ, combat, mob, loot, death;10 phiên 15 phút; lỗi blocker 0 | F7: GD; CL+SV sửa | G7: TTK/điều khiển không ổn→dùng dự phòng; giảm VFX | H7: Chưa đánh giá
A8: G3 | B8: 12 | C8: Tuần 24 — Core loop alpha | D8: =WORKDAY('00_START'!$B$7-1,B8*10) -> 46472 | E8: 20 Cổ; capture/feed/refine/equip/quest/rank; reconnect; atomic/dupetests pass | F8: Cả đội | G8: Ledger/dupefail→dừng social, fix dữ liệu trước | H8: Chưa đánh giá
A9: G4 | B9: 15 | C9: Tuần 30 — Content/social đủ | D9: =WORKDAY('00_START'!$B$7-1,B9*10) -> 46514 | E9: Party 3, chat, dungeon 1 boss, duel1v1; noopenworlddamage | F9: Cả đội | G9: Trễ>1 sprint→cắt party/dungeon/duel theo cutline | H9: Chưa đánh giá
A10: G5 | B10: 18 | C10: Tuần 36 — Closed alpha | D10: =WORKDAY('00_START'!$B$7-1,B10*10) -> 46556 | E10: Must trace passed;0P0/P1; NFRload/restore/security;20 tester mời; report 7 ngày | F10: Owner+GD+SV | G10: Không máy host/quá load→chỉ local/LANalpha và ghi giới hạn | H10: Chưa đánh giá

Sheet 16_TEST_CASES
A1: 16 / Test Plan & Requirement Trace
A2: 79plannedtestrows; không tự đánh dấu Passed. Evidence phải có build/config/browser/hardware khi áp dụng; dùng QA_REQUESTS để ghi issues.
A4: Test ID | B4: Requirement IDs | C4: Scenario | D4: Preconditions / Input | E4: Steps / Negative cases | F4: Expected / Acceptance | G4: Priority | H4: Gate | I4: Owner | J4: Status | K4: Evidence path | L4: Actual result
A5: TC-CL-001 | B5: CL-001 | C5: Đăng nhập bằng tài khoản mời | D5: Username, password | E5: Nhập username/password; xác thực server; chuyển chọn nhân vật. Không mở đăng ký công khai trong alpha. | Thử negative case: Sai thông tin hiển thị chung; khóa tạm sau nhiều lần sai | F5: Tài khoản hợp lệ vào được; sai/expired không vào room. | G5: P1 | H5: G1 | I5: GD + owner kỹ thuật | J5: Chưa chạy
A6: TC-CL-002 | B6: CL-002 | C6: Tạo và chọn nhân vật | D6: Tên, avatar cơ sở | E6: Mỗi account 1 nhân vật; đặt tên 3–16 ký tự Unicode chữ/số/khoảng trắng; trim; kiểm tra tên trùng và danh sách cấm. | Thử negative case: Tên lỗi/trùng; gửi lặp không tạo thêm | F6: Hai request đồng thời chỉ tạo 1 nhân vật và 1 starter kit. | G6: P1 | H6: G1 | I6: GD + owner kỹ thuật | J6: Chưa chạy
A7: TC-CL-003 | B7: CL-003 | C7: Click-to-move isometric | D7: Tọa độ world, sequence | E7: Click trái nền gửi đích; client tìm đường A* trên nav grid; server xác nhận đường/tốc độ; hỗ trợ hủy bằng click mới. | Thử negative case: Đích ngoài map/tường: hiện marker không đi được | F7: Đi quanh vật cản; click liên tục không xuyên tường; UI click không di chuyển. | G7: P1 | H7: G1 | I7: GD + owner kỹ thuật | J7: Chưa chạy
A8: TC-CL-004 | B8: CL-004 | C8: Camera và depth sorting | D8: Player/world position | E8: Camera bám nhân vật trong biên map; render theo ground Y + layer; props cao che đúng; không xoay camera. | Thử negative case: Resize vẫn giữ nhân vật trong khung | F8: Đi sau/trước 10 props không đảo layer; 1366×768 và 1920×1080 dùng được. | G8: P1 | H8: G1 | I8: GD + owner kỹ thuật | J8: Chưa chạy
A9: TC-CL-005 | B9: CL-005 | C9: Chọn và tương tác mục tiêu | D9: Entity ID | E9: Click quái chọn; click NPC trong 2 tile mở tương tác; click xa tự đi đến; vòng chọn và HP mục tiêu. | Thử negative case: Target mất AOI/chết: bỏ chọn | F9: Không mở NPC ở xa; mục tiêu biến mất không gây lỗi UI. | G9: P1 | H9: G2 | I9: GD + owner kỹ thuật | J9: Chưa chạy
A10: TC-CL-006 | B10: CL-006 | C10: Minimap và cổng map | D10: Map ID, portal ID | E10: Hiện vị trí bản thân, party, NPC, cổng; dùng portal tương tác để chuyển map; không lộ entity ngoài quyền xem. | Thử negative case: Map đầy hoặc server lỗi: ở map cũ, báo lý do | F10: Chuyển map không xuất hiện hai bản nhân vật; minimap đúng collision/portal. | G10: P1 | H10: G3 | I10: GD + owner kỹ thuật | J10: Chưa chạy
A11: TC-CL-007 | B11: CL-007 | C11: Thanh Cổ Q/W/E/R | D11: Gu instance, hotkey, target | E11: 4 ô active; 2 ô passive mở rank II; QWER kích hoạt; số 1 dùng vật phẩm hồi phục; remap ở settings. | Thử negative case: Chat/input đang focus không phát skill | F11: Bốn hotkey và click đều hoạt động; skill chưa đủ điều kiện báo cùng mã lỗi. | G11: P1 | H11: G3 | I11: GD + owner kỹ thuật | J11: Chưa chạy
A12: TC-CL-008 | B12: CL-008 | C12: Thi triển chỉ mục tiêu/điểm đất/tự thân | D12: Gu ID, target ID hoặc world point | E12: Cổ định nghĩa targetMode; điểm đất preview vòng AoE; Esc/hủy click; cast bar khi có castTime; server quyết định hit. | Thử negative case: Target chết/ngoài tầm/không LOS: không trừ mana | F12: Mỗi mode ít nhất 1 skill kiểm thử; không đánh xuyên vật cản LOS. | G12: P1 | H12: G3 | I12: GD + owner kỹ thuật | J12: Chưa chạy
A13: TC-CL-009 | B13: CL-009 | C13: HP và Chân Nguyên | D13: HP/mana/cost server | E13: Hiện HP/mana số và thanh; mana cost lấy từ maxMana × cost%; server snapshot là nguồn số thật. | Thử negative case: Mana thiếu: từ chối cast, không reset cooldown | F13: UI đúng số server sau cast, hồi phục và reconnect. | G13: P1 | H13: G2 | I13: GD + owner kỹ thuật | J13: Chưa chạy
A14: TC-CL-010 | B14: CL-010 | C14: Buff, debuff và combat feed back | D14: Combat events/status endTime | E14: Icon có thời gian; shield/slow/stun/heal rõ; damage number có giới hạn; telegraph không chỉ dựa màu. | Thử negative case: Event trùng bỏ qua bằng eventId | F14: Stun/slow đúng duration; mute tắt được audio; denied khác hit. | G14: P1 | H14: G3 | I14: GD + owner kỹ thuật | J14: Chưa chạy
A15: TC-CL-011 | B15: CL-011 | C15: Chết và hồi sinh | D15: Death event; respawn intent | E15: 0 HP khóa input combat; 5 giây rồi hồi tại safe spawn; không mất Cổ trong MVP; mất 5% tiền mềm, cap 50. | Thử negative case: Nhấn lặp không trừ nhiều lần; đang mất mạng chờ resync | F15: Một death chỉ một penalty; quest/Gu vẫn còn sau hồi sinh. | G15: P1 | H15: G2 | I15: GD + owner kỹ thuật | J15: Chưa chạy
A16: TC-CL-012 | B16: CL-012 | C16: Đánh quái và nhận loot | D16: Mob ID, combat intent | E16: Quái có cấp, HP, aggro, leash; loot cá nhân vào túi sau server commit; popup theo receipt. | Thử negative case: Túi đầy không mất reward: vào reward inbox | F16: Hai client đánh cùng quái chỉ một owner nhận reward; retry không nhân đôi. | G16: P1 | H16: G3 | I16: GD + owner kỹ thuật | J16: Chưa chạy
... A83: E2E-12 | B83: NFR-06, SV-017 | C83: Restore và release rollback | D83: Snapshot daily+beforetag; DB rỗng | E83: Restore; verifyrowcounts/ledger; smoke; rollback compatible app | F83: RPO≤24h/RTO≤2h; biên bản; không đụng DB nguồn | G83: P1 | H83: G5 | I83: GD + CL/SV | J83: Chưa chạy

Sheet 17_QA_REQUESTS
A1: 17 / QA Issue Tracker
A2: Tham khảo sheet QA From Client của mẫu; đây là form rỗng, không phải lỗi phá thiện thực tế. P0 mất/nhân dữ liệu, P1blocker, P2degraded, P3cosmetic.
A4: Issue ID | B4: Category | C4: Function / Req ID | D4: Path / Screen | E4: Steps / Request | F4: Requested date | G4: Reporter | H4: Status | I4: Planned date | J4: Completed date | K4: Owner | L4: Priority | M4: Notes / Evidence

Sheet 18_RISKS
A1: 18 / Risk Register
A2: Likelihood/Impact1–5; score=L×I. Rủi ro cao được xem lại ở mỗi gate; không coi dự phòng là công suất cho thêm feature.
A4: ID | B4: Risk | C4: Likelihood | D4: Impact | E4: Trigger | F4: Owner | G4: Mitigation | H4: Fallback / Cutline | I4: Score
A5: R-01 | B5: Thời gian kiêm nhiệm không đủ | C5: 5 | D5: 5 | E5: Giờ hữu ích <75% giả định trong 2 sprint; task carryover>20% | F5: GD | G5: Ghi giờ thật; giảm scope; dùng scenario 10/15h; không giả làm full time | H5: Bỏ duel/chat trước; giữ core loop và transaction | I5: =C5*D5 -> 25
A6: R-02 | B6: Thiếu kỹ năng authoritative/backend | C6: 4 | D6: 5 | E6: SpikeS01 không chặn warp hoặc 2 socket gây dupe | F6: SV | G6: Spike và peer review; single writer+transaction trước social | H6: Thêm spike; giảm CCU/map; không chuyển client authority | I6: =C6*D6 -> 20
A7: R-03 | B7: Asset vượt sức 1 artist | C7: 4 | D7: 4 | E7: Danh sách sprite>3pd/sprint; payload>budget | F7: AR | G7: 1 avatar,4facing; mirror/recolor;8 primitive; tileset dùng lại | H7: Giảm quái 6→4, Gu20→12; không tạo 8 hướng mọi loại | I7: =C7*D7 -> 16
A8: R-04 | B8: Dupe hoặc mất tài sản | C8: 3 | D8: 5 | E8: Retry/kill process cho2 output hoặc ACK không durable | F8: SV | G8: Idempotency, lock, ledger, receipt, fault tests; PK drop để sau | H8: BlockG3/G5; khóa economic commands nếu cần; không xóa log | I8: =C8*D8 -> 15
A9: R-05 | B9: Tải server/render không đạt | C9: 4 | D9: 4 | E9: Tickp95>40ms; FPSmedian<50 ở scene chuẩn | F9: CL+SV | G9: AOI; spawn limit; atlas; loadtestS04/S17; đo máy thật | H9: Giảm 20→10/map,50→20CCU; phải ghi NFR thay đổi | I9: =C9*D9 -> 16
A10: R-06 | B10: Nuôi/luyện gây mệt hoặc bế tắc | C10: 3 | D10: 4 | E10: ≥30% tester không tiếp tục sau craft fail; thiếu food; quest không đủ rank | F10: GD | G10: Online hunger; nopermadeath; pity; mainquestXP4500;3 build tests | H10: Tăng nguồn food; recipe100% trong test; so sánh funnel | I10: =C10*D10 -> 12
A11: R-07 | B11: Không có tiền/máy host public alpha | C11: 4 | D11: 4 | E11: S16 chưa có host và backup ngoài máy đang chạy | F11: SV+Owner | G11: Local/LAN trước; ghi điều kiện free resource; chốt cash sheet | H11: Chỉ alpha LAN; không cam kết internet 24/7 | I11: =C11*D11 -> 16
A12: R-08 | B12: Naming/asset chưa rõ nguồn dùng | C12: 3 | D12: 4 | E12: Không có manifest nguồn hoặc chưa chốt tên phá thành | F12: Owner+AR | G12: Tên làm việc; ghiassetlicense/source/author ngaykhiimport | H12: Thay asset/tên trước alpha công khai | I12: =C12*D12 -> 12
A13: R-09 | B13: Scope nở thành MMORPG đầy đủ | C13: 5 | D13: 4 | E13: Thêmguild/auction/công thành khichưaG3 | F13: GD | G13: Change request phải có effort/owner/deps; one in, one out | H13: GiữP2/P3; không âm thầm kéo dài lịch | I13: =C13*D13 -> 20
A14: R-10 | B14: Một thành viên ngừng tham gia | C14: 3 | D14: 5 | E14: Vắng 2 tuần/không handoff; knowledge chỉ 1 người | F14: Cả đội | G14: README; weekly demo; client/server cross review; asset manifest | H14: Rebaseline theo 3 người; giảm content/social; không giữ deadline cũ | I14: =C14*D14 -> 15

Sheet 19_RESOURCE
A1: 19 / Công suất và tải theo vai trò
A2: Mỗi người20h/tuần×36 tuần×75%=67.5 PD hữu ích. Dự phòng 20% đã trong tải; không giả định có QA/DevOps thứ 5.
A4: Role | B4: Người / vai trò | C4: Trách nhiệm | D4: Base PD | E4: Reserve PD | F4: Total PD | G4: Capacity PD | H4: Remaining PD | I4: Utilization
A5: GD | B5: Thành viên 1 — Product/Game Design + QA | C5: Phạm vi, dữ liệu cân bằng, quest, kiểm thử, điều phối và playtest | D5: =SUMIF('13_WBS'!$E$5:$E$76,A5,'13_WBS'!$J$5:$J$76) -> 47 | E5: =D5*'00_START'!$B$10 -> 9.4 | F5: =D5+E5 -> 56.4 | G5: ='00_START'!$B$11*'00_START'!$B$8*'00_START'!$B$9/'00_START'!$B$12 -> 67.5 | H5: =G5-F5 -> 11.1 | I5: =IFERROR(F5/G5,0) -> 0.83555556
A6: CL | B6: Thành viên 2 — Client/Gameplay | C6: Godot/GDScript, render isometric, điều khiển, UI và tích hợp gameplay | D6: =SUMIF('13_WBS'!$E$5:$E$76,A6,'13_WBS'!$J$5:$J$76) -> 54 | E6: =D6*'00_START'!$B$10 -> 10.8 | F6: =D6+E6 -> 64.8 | G6: ='00_START'!$B$11*'00_START'!$B$8*'00_START'!$B$9/'00_START'!$B$12 -> 67.5 | H6: =G6-F6 -> 2.7 | I6: =IFERROR(F6/G6,0) -> 0.96
A7: SV | B7: Thành viên 3 — Server/Tech Lead | C7: Realtime, PostgreSQL, bảo mật, tooling vận hành và triển khai | D7: =SUMIF('13_WBS'!$E$5:$E$76,A7,'13_WBS'!$J$5:$J$76) -> 54 | E7: =D7*'00_START'!$B$10 -> 10.8 | F7: =D7+E7 -> 64.8 | G7: ='00_START'!$B$11*'00_START'!$B$8*'00_START'!$B$9/'00_START'!$B$12 -> 67.5 | H7: =G7-F7 -> 2.7 | I7: =IFERROR(F7/G7,0) -> 0.96
A8: AR | B8: Thành viên 4 — 2D/Content/UI | C8: Tileset, sprite, icon, map, VFX, âm thanh có nguồn sử dụng rõ ràng | D8: =SUMIF('13_WBS'!$E$5:$E$76,A8,'13_WBS'!$J$5:$J$76) -> 44 | E8: =D8*'00_START'!$B$10 -> 8.8 | F8: =D8+E8 -> 52.8 | G8: ='00_START'!$B$11*'00_START'!$B$8*'00_START'!$B$9/'00_START'!$B$12 -> 67.5 | H8: =G8-F8 -> 14.7 | I8: =IFERROR(F8/G8,0) -> 0.78222222

Sheet 20_SPRINT_LOAD
A1: 20 / Kiểm tra tải từng sprint × owner
A2: Mỗi 2 tuần: capacity 3.75 PD; package3 PD+20%=3.6 PD(96%). Nếu đổi giờ/effort, ô remaining âm phải cắt phạm vi hoặc lập lại lịch.
A4: Sprint | B4: Owner | C4: Baseline Task ID | D4: Base PD | E4: Total PD incl reserve | F4: Capacity PD / sprint | G4: Remaining PD | H4: Check
A5: 1 | B5: GD | C5: T01-GD | D5: =SUMIFS('13_WBS'!$J$5:$J$76,'13_WBS'!$E$5:$E$76,B5,'13_WBS'!$F$5:$F$76,A5) -> 2.5 | E5: =SUMIFS('13_WBS'!$L$5:$L$76,'13_WBS'!$E$5:$E$76,B5,'13_WBS'!$F$5:$F$76,A5) -> 3 | F5: =2*'00_START'!$B$8*'00_START'!$B$9/'00_START'!$B$12 -> 3.75 | G5: =F5-E5 -> 0.75 | H5: =IF(G5<0,"OVERLOAD","OK") -> OK
A6: 1 | B6: CL | C6: T01-CL | D6: =SUMIFS('13_WBS'!$J$5:$J$76,'13_WBS'!$E$5:$E$76,B6,'13_WBS'!$F$5:$F$76,A6) -> 3 | E6: =SUMIFS('13_WBS'!$L$5:$L$76,'13_WBS'!$E$5:$E$76,B6,'13_WBS'!$F$5:$F$76,A6) -> 3.6 | F6: =2*'00_START'!$B$8*'00_START'!$B$9/'00_START'!$B$12 -> 3.75 | G6: =F6-E6 -> 0.15 | H6: =IF(G6<0,"OVERLOAD","OK") -> OK
A7: 1 | B7: SV | C7: T01-SV | D7: =SUMIFS('13_WBS'!$J$5:$J$76,'13_WBS'!$E$5:$E$76,B7,'13_WBS'!$F$5:$F$76,A7) -> 3 | E7: =SUMIFS('13_WBS'!$L$5:$L$76,'13_WBS'!$E$5:$E$76,B7,'13_WBS'!$F$5:$F$76,A7) -> 3.6 | F7: =2*'00_START'!$B$8*'00_START'!$B$9/'00_START'!$B$12 -> 3.75 | G7: =F7-E7 -> 0.15 | H7: =IF(G7<0,"OVERLOAD","OK") -> OK
A8: 1 | B8: AR | C8: T01-AR | D8: =SUMIFS('13_WBS'!$J$5:$J$76,'13_WBS'!$E$5:$E$76,B8,'13_WBS'!$F$5:$F$76,A8) -> 2.5 | E8: =SUMIFS('13_WBS'!$L$5:$L$76,'13_WBS'!$E$5:$E$76,B8,'13_WBS'!$F$5:$F$76,A8) -> 3 | F8: =2*'00_START'!$B$8*'00_START'!$B$9/'00_START'!$B$12 -> 3.75 | G8: =F8-E8 -> 0.75 | H8: =IF(G8<0,"OVERLOAD","OK") -> OK
A9: 2 | B9: GD | C9: T02-GD | D9: =SUMIFS('13_WBS'!$J$5:$J$76,'13_WBS'!$E$5:$E$76,B9,'13_WBS'!$F$5:$F$76,A9) -> 2.5 | E9: =SUMIFS('13_WBS'!$L$5:$L$76,'13_WBS'!$E$5:$E$76,B9,'13_WBS'!$F$5:$F$76,A9) -> 3 | F9: =2*'00_START'!$B$8*'00_START'!$B$9/'00_START'!$B$12 -> 3.75 | G9: =F9-E9 -> 0.75 | H9: =IF(G9<0,"OVERLOAD","OK") -> OK
A10: 2 | B10: CL | C10: T02-CL | D10: =SUMIFS('13_WBS'!$J$5:$J$76,'13_WBS'!$E$5:$E$76,B10,'13_WBS'!$F$5:$F$76,A10) -> 3 | E10: =SUMIFS('13_WBS'!$L$5:$L$76,'13_WBS'!$E$5:$E$76,B10,'13_WBS'!$F$5:$F$76,A10) -> 3.6 | F10: =2*'00_START'!$B$8*'00_START'!$B$9/'00_START'!$B$12 -> 3.75 | G10: =F10-E10 -> 0.15 | H10: =IF(G10<0,"OVERLOAD","OK") -> OK
A11: 2 | B11: SV | C11: T02-SV | D11: =SUMIFS('13_WBS'!$J$5:$J$76,'13_WBS'!$E$5:$E$76,B11,'13_WBS'!$F$5:$F$76,A11) -> 3 | E11: =SUMIFS('13_WBS'!$L$5:$L$76,'13_WBS'!$E$5:$E$76,B11,'13_WBS'!$F$5:$F$76,A11) -> 3.6 | F11: =2*'00_START'!$B$8*'00_START'!$B$9/'00_START'!$B$12 -> 3.75 | G11: =F11-E11 -> 0.15 | H11: =IF(G11<0,"OVERLOAD","OK") -> OK
A12: 2 | B12: AR | C12: T02-AR | D12: =SUMIFS('13_WBS'!$J$5:$J$76,'13_WBS'!$E$5:$E$76,B12,'13_WBS'!$F$5:$F$76,A12) -> 2.5 | E12: =SUMIFS('13_WBS'!$L$5:$L$76,'13_WBS'!$E$5:$E$76,B12,'13_WBS'!$F$5:$F$76,A12) -> 3 | F12: =2*'00_START'!$B$8*'00_START'!$B$9/'00_START'!$B$12 -> 3.75 | G12: =F12-E12 -> 0.75 | H12: =IF(G12<0,"OVERLOAD","OK") -> OK
A13: 3 | B13: GD | C13: T03-GD | D13: =SUMIFS('13_WBS'!$J$5:$J$76,'13_WBS'!$E$5:$E$76,B13,'13_WBS'!$F$5:$F$76,A13) -> 2 | E13: =SUMIFS('13_WBS'!$L$5:$L$76,'13_WBS'!$E$5:$E$76,B13,'13_WBS'!$F$5:$F$76,A13) -> 2.4 | F13: =2*'00_START'!$B$8*'00_START'!$B$9/'00_START'!$B$12 -> 3.75 | G13: =F13-E13 -> 1.35 | H13: =IF(G13<0,"OVERLOAD","OK") -> OK
A14: 3 | B14: CL | C14: T03-CL | D14: =SUMIFS('13_WBS'!$J$5:$J$76,'13_WBS'!$E$5:$E$76,B14,'13_WBS'!$F$5:$F$76,A14) -> 3 | E14: =SUMIFS('13_WBS'!$L$5:$L$76,'13_WBS'!$E$5:$E$76,B14,'13_WBS'!$F$5:$F$76,A14) -> 3.6 | F14: =2*'00_START'!$B$8*'00_START'!$B$9/'00_START'!$B$12 -> 3.75 | G14: =F14-E14 -> 0.15 | H14: =IF(G14<0,"OVERLOAD","OK") -> OK
A15: 3 | B15: SV | C15: T03-SV | D15: =SUMIFS('13_WBS'!$J$5:$J$76,'13_WBS'!$E$5:$E$76,B15,'13_WBS'!$F$5:$F$76,A15) -> 3 | E15: =SUMIFS('13_WBS'!$L$5:$L$76,'13_WBS'!$E$5:$E$76,B15,'13_WBS'!$F$5:$F$76,A15) -> 3.6 | F15: =2*'00_START'!$B$8*'00_START'!$B$9/'00_START'!$B$12 -> 3.75 | G15: =F15-E15 -> 0.15 | H15: =IF(G15<0,"OVERLOAD","OK") -> OK
A16: 3 | B16: AR | C16: T03-AR | D16: =SUMIFS('13_WBS'!$J$5:$J$76,'13_WBS'!$E$5:$E$76,B16,'13_WBS'!$F$5:$F$76,A16) -> 2.5 | E16: =SUMIFS('13_WBS'!$L$5:$L$76,'13_WBS'!$E$5:$E$76,B16,'13_WBS'!$F$5:$F$76,A16) -> 3 | F16: =2*'00_START'!$B$8*'00_START'!$B$9/'00_START'!$B$12 -> 3.75 | G16: =F16-E16 -> 0.75 | H16: =IF(G16<0,"OVERLOAD","OK") -> OK
... A76: 18 | B76: AR | C76: T18-AR | D76: =SUMIFS('13_WBS'!$J$5:$J$76,'13_WBS'!$E$5:$E$76,B76,'13_WBS'!$F$5:$F$76,A76) -> 2 | E76: =SUMIFS('13_WBS'!$L$5:$L$76,'13_WBS'!$E$5:$E$76,B76,'13_WBS'!$F$5:$F$76,A76) -> 2.4 | F76: =2*'00_START'!$B$8*'00_START'!$B$9/'00_START'!$B$12 -> 3.75 | G76: =F76-E76 -> 1.35 | H76: =IF(G76<0,"OVERLOAD","OK") -> OK

Sheet 21_SCENARIOS
A1: 21 / Quy đổi thời gian theo availability
A2: 36 tuần là phương án 20h/người/tuần; thời gian thực tế phụ thuộc availability/nghỉ/học và kết quả spike. Bảng không tự dịch WBS.
A4: Hours / người / tuần | B4: Equivalent weeks | C4: Equivalent months (~4.345w) | D4: Lưu ý
A5: 10 | B5: ='00_START'!$B$11*'00_START'!$B$8/A5 -> 72 | C5: =B5/4.345 -> 16.570771 | D5: Quy đổi công suất; chỉ dùng khi cả 4 người có cùng availability. Cần rebaseline các sprint/phụ thuộc, không coi là deadline chắc chắn.
A6: 15 | B6: ='00_START'!$B$11*'00_START'!$B$8/A6 -> 48 | C6: =B6/4.345 -> 11.047181 | D6: Quy đổi công suất; chỉ dùng khi cả 4 người có cùng availability. Cần rebaseline các sprint/phụ thuộc, không coi là deadline chắc chắn.
A7: 20 | B7: ='00_START'!$B$11*'00_START'!$B$8/A7 -> 36 | C7: =B7/4.345 -> 8.2853855 | D7: Quy đổi công suất; chỉ dùng khi cả 4 người có cùng availability. Cần rebaseline các sprint/phụ thuộc, không coi là deadline chắc chắn.
A8: 30 | B8: ='00_START'!$B$11*'00_START'!$B$8/A8 -> 24 | C8: =B8/4.345 -> 5.5235903 | D8: Quy đổi công suất; chỉ dùng khi cả 4 người có cùng availability. Cần rebaseline các sprint/phụ thuộc, không coi là deadline chắc chắn.
A9: 40 | B9: ='00_START'!$B$11*'00_START'!$B$8/A9 -> 18 | C9: =B9/4.345 -> 4.1426928 | D9: Quy đổi công suất; chỉ dùng khi cả 4 người có cùng availability. Cần rebaseline các sprint/phụ thuộc, không coi là deadline chắc chắn.

Sheet 22_COST
A1: 22 / Cash input & giá trị công sức
A2: User: no budget. Tất cả đơn giá=0 là placeholder/mục tiêu, không phải báo giá đã xác nhận. Không cần nghiên cứu giá thị trường để dùng bảng này.
A4: ID | B4: Khoản | C4: Số lượng / Giờ | D4: Đơn giá VND (input) | E4: Thành tiền VND | F4: Trạng thái | G4: Ghi chú
A5: CASH-01 | B5: Hosting server / tháng | C5: 0 | D5: 0 | E5: =C5*D5 -> 0 | F5: Chưa có báo giá / chưa có host | G5: Local/LAN trước; điền đơn giá thật khi chọn môi trường.
A6: CASH-02 | B6: Backup storage / tháng | C6: 0 | D6: 0 | E6: =C6*D6 -> 0 | F6: Chưa có báo giá | G6: Backup cần ở nơi độc lập với máy chạy; dữ liệu alpha có thể dùng tài nguyên sẵn có nếu đủ điều kiện.
A7: CASH-03 | B7: Domain / năm (tùy chọn) | C7: 0 | D7: 0 | E7: =C7*D7 -> 0 | F7: Chưa chọn | G7: Không bắt buộc cho alpha LAN/private; không mặc định miễn phí.
A8: CASH-04 | B8: Art/audio mua một lần | C8: 0 | D8: 0 | E8: =C8*D8 -> 0 | F8: Mục tiêu cash 0 | G8: Tự tạo hoặc tài nguyên có nguồn sử dụng rõ; giới hạn content để không cần mua.
A9: CASH-05 | B9: Công cụ / tháng | C9: 0 | D9: 0 | E9: =C9*D9 -> 0 | F9: Chưa chọn | G9: Dùng công cụ sẵn có; mọi khoản trả phí phải được owner chốt.
A10: CASH-06 | B10: Tổng cash nhập | E10: =SUM(E5:E9) -> 0 | F10: Số 0 không phải dự toán thị trường | G10: Tổng chỉ có tác dụng sau khi điền các đơn giá/số lượng; không cam kết online 0 đồng.
A11: TIME-01 | B11: Giờ công cơ sở | C11: 1592 | D11: 0 | E11: =C11*D11 -> 0 | F11: Giờ đóng góp, không phải lương | G11: Đơn giá 0 theo bố i cảnh tự phát triển; thay đơn giá để ước giá trị công sức nếu muốn.
A12: TIME-02 | B12: Giờ công dự phòng | C12: 318.4 | D12: 0 | E12: =C12*D12 -> 0 | F12: 20% effort | G12: Tách khỏi cash hạ tầng; không thuê mới người làm.

Sheet 23_TRACE
A1: 23 / Requirement → Rule → UC → WBS → Test
A2: Một nguồn ID để kiểm tra đủ phạm vi. FSD/WBS không đánh dấu implemented; Status của test quản lý tại 16_TEST_CASES.
A4: Requirement ID | B4: Tên | C4: Phase | D4: Rules | E4: Use Cases | F4: WBS IDs | G4: Test ID | H4: Test status at baseline
A5: CL-001 | B5: Đăng nhập bằng tài khoản mời | C5: MVP | E5: UC-01 | F5: T02-CL, T02-SV | G5: TC-CL-001 | H5: Chưa chạy
A6: CL-002 | B6: Tạo và chọn nhân vật | C6: MVP | D6: BR-01 | E6: UC-01 | F6: T02-CL, T02-SV | G6: TC-CL-002 | H6: Chưa chạy
A7: CL-003 | B7: Click-to-move isometric | C7: MVP | D7: BR-02 | E7: UC-02 | F7: T03-CL, T04-SV | G7: TC-CL-003 | H7: Chưa chạy
A8: CL-004 | B8: Camera và depth sorting | C8: MVP | F8: T02-CL, T03-CL, T03-AR | G8: TC-CL-004 | H8: Chưa chạy
A9: CL-005 | B9: Chọn và tương tác mục tiêu | C9: MVP | D9: BR-02 | E9: UC-02 | F9: T03-CL, T06-CL | G9: TC-CL-005 | H9: Chưa chạy
A10: CL-006 | B10: Minimap và cổng map | C10: MVP | E10: UC-11 | F10: T04-CL, T12-CL, T12-SV | G10: TC-CL-006 | H10: Chưa chạy
A11: CL-007 | B11: Thanh Cổ Q/W/E/R | C11: MVP | D11: BR-03 | E11: UC-03 | F11: T05-CL, T07-CL, T11-CL | G11: TC-CL-007 | H11: Chưa chạy
A12: CL-008 | B12: Thi triển chỉ mục tiêu/điểm đất/tự thân | C12: MVP | D12: BR-04 | E12: UC-03 | F12: T05-CL, T05-SV, T11-CL | G12: TC-CL-008 | H12: Chưa chạy
A13: CL-009 | B13: HP và Chân Nguyên | C13: MVP | D13: BR-05 | F13: T04-CL, T05-CL, T05-SV | G13: TC-CL-009 | H13: Chưa chạy
A14: CL-010 | B14: Buff, debuff và combat feed back | C14: MVP | D14: BR-06 | F14: T05-CL, T11-CL, T11-AR | G14: TC-CL-010 | H14: Chưa chạy
A15: CL-011 | B15: Chết và hồi sinh | C15: MVP | D15: BR-07 | E15: UC-10 | F15: T06-CL, T06-SV | G15: TC-CL-011 | H15: Chưa chạy
A16: CL-012 | B16: Đánh quái và nhận loot | C16: MVP | D16: BR-08 | E16: UC-03 | F16: T06-CL, T06-SV, T07-SV | G16: TC-CL-012 | H16: Chưa chạy
A17: CL-013 | B17: Túi 30 ô và stack | C17: MVP | D17: BR-09 | E17: UC-04 | F17: T07-CL, T07-SV | G17: TC-CL-013 | H17: Chưa chạy
A18: CL-014 | B18: Tooltip và khóa Cổ | C18: MVP | D18: BR-10 | E18: UC-04 | F18: T07-CL, T07-SV | G18: TC-CL-014 | H18: Chưa chạy
A19: CL-015 | B19: Trang bị và tháo Cổ | C19: MVP | D19: BR-03, BR-10 | E19: UC-04 | F19: T07-CL, T07-SV, T11-SV | G19: TC-CL-015 | H19: Chưa chạy
A20: CL-016 | B20: Bắt Hoang Cổ | C20: MVP | D20: BR-11 | E20: UC-05 | F20: T08-CL, T08-SV | G20: TC-CL-016 | H20: Chưa chạy
A21: CL-017 | B21: Cho ăn và trạng thái đói | C21: MVP | D21: BR-12 | E21: UC-06 | F21: T08-CL, T08-SV | G21: TC-CL-017 | H21: Chưa chạy
A22: CL-018 | B22: Chọn công thức và preview | C22: MVP | D22: BR-13 | E22: UC-07 | F22: T09-CL, T09-SV | G22: TC-CL-018 | H22: Chưa chạy
A23: CL-019 | B23: Thực hiện luyện và xem kết quả | C23: MVP | D23: BR-13, BR-14 | E23: UC-07 | F23: T09-CL, T09-SV | G23: TC-CL-019 | H23: Chưa chạy
A24: CL-020 | B24: Cấp 1–20 và Nhất/Nhị Chuyển | C24: MVP | D24: BR-15 | E24: UC-08 | F24: T10-CL, T10-SV | G24: TC-CL-020 | H24: Chưa chạy
A25: CL-021 | B25: 10 quest và tracker | C25: MVP | D25: BR-16 | E25: UC-08 | F25: T10-CL, T10-SV | G25: TC-CL-021 | H25: Chưa chạy
A26: CL-022 | B26: Mua/bán với NPC | C26: MVP | D26: BR-09, BR-14 | E26: UC-09 | F26: T10-CL, T10-SV | G26: TC-CL-022 | H26: Chưa chạy
A27: CL-023 | B27: Party tối đa 3 người | C27: MVP | D27: BR-17 | E27: UC-12 | F27: T13-CL, T13-SV | G27: TC-CL-023 | H27: Chưa chạy
A28: CL-024 | B28: Chat zone/party, mute/report | C28: MVP | D28: BR-18 | F28: T13-CL, T13-SV, T16-SV | G28: TC-CL-024 | H28: Chưa chạy
A29: CL-025 | B29: Phụ bản 1–3 người và boss | C29: MVP | D29: BR-19 | E29: UC-13 | F29: T14-CL, T14-SV | G29: TC-CL-025 | H29: Chưa chạy
A30: CL-026 | B30: PK opt-in 1v1 | C30: MVP | D30: BR-20 | E30: UC-14 | F30: T15-CL, T15-SV | G30: TC-CL-026 | H30: Chưa chạy
A31: CL-027 | B31: Mất kết nối và trở lại | C31: MVP | D31: BR-21 | E31: UC-11 | F31: T12-CL, T12-SV | G31: TC-CL-027 | H31: Chưa chạy
A32: CL-028 | B32: Thiết lập PC và lưu tùy chọn | C32: MVP | F32: T16-CL, T16-AR | G32: TC-CL-028 | H32: Chưa chạy
A33: CL-029 | B33: 30 giây đầu và tutorial | C33: MVP | E33: UC-01 | F33: T03-GD, T10-CL, T16-GD | G33: TC-CL-029 | H33: Chưa chạy
A34: CL-030 | B34: Danh mục Cổ và build | C34: MVP | F34: T11-CL, T11-GD | G34: TC-CL-030 | H34: Chưa chạy
A35: SV-001 | B35: Xác thực và vòng đời session | C35: MVP | D35: BR-01 | E35: UC-01 | F35: T02-SV, T03-SV | G35: TC-SV-001 | H35: Chưa chạy
A36: SV-002 | B36: Server giữ quyền quyết định | C36: MVP | D36: BR-02, BR-04 | F36: T04-SV, T05-SV | G36: TC-SV-002 | H36: Chưa chạy
A37: SV-003 | B37: Lọc trạng thái theo vùng quan tâm | C37: MVP | F37: T04-SV, T12-SV | G37: TC-SV-003 | H37: Chưa chạy
A38: SV-004 | B38: Chuyển map không trùng nhân vật | C38: MVP | D38: BR-21 | E38: UC-11 | F38: T03-SV, T12-SV | G38: TC-SV-004 | H38: Chưa chạy
A39: SV-005 | B39: Giải quyết cast và trạng thái | C39: MVP | D39: BR-04, BR-05, BR-06 | E39: UC-03 | F39: T05-SV, T11-SV | G39: TC-SV-005 | H39: Chưa chạy
A40: SV-006 | B40: AI, respawn và quyền thưởng | C40: MVP | D40: BR-08, BR-11 | F40: T06-SV, T08-SV | G40: TC-SV-006 | H40: Chưa chạy
A41: SV-007 | B41: Lưu bền vững và checkpoint | C41: MVP | D41: BR-14, BR-21 | F41: T07-SV, T12-SV | G41: TC-SV-007 | H41: Chưa chạy
A42: SV-008 | B42: Ledger và idempotency | C42: MVP | D42: BR-14 | E42: UC-07 | F42: T07-SV, T09-SV, T10-SV | G42: TC-SV-008 | H42: Chưa chạy
A43: SV-009 | B43: Reward inbox khi đầy túi | C43: MVP | D43: BR-09 | F43: T07-SV, T10-CL | G43: TC-SV-009 | H43: Chưa chạy
A44: SV-010 | B44: Săn bắt và hunger server | C44: MVP | D44: BR-11, BR-12 | F44: T08-SV | G44: TC-SV-010 | H44: Chưa chạy
A45: SV-011 | B45: Công thức, pity và roll server | C45: MVP | D45: BR-13, BR-14 | F45: T09-SV | G45: TC-SV-011 | H45: Chưa chạy
A46: SV-012 | B46: XP, quest và rank-up từ event server | C46: MVP | D46: BR-15, BR-16 | F46: T10-SV | G46: TC-SV-012 | H46: Chưa chạy
A47: SV-013 | B47: Party và recipient authorization | C47: MVP | D47: BR-17, BR-18 | F47: T13-SV, T16-SV | G47: TC-SV-013 | H47: Chưa chạy
A48: SV-014 | B48: Dungeon và duel state machine | C48: MVP | D48: BR-19, BR-20 | E48: UC-13, UC-14 | F48: T14-SV, T15-SV | G48: TC-SV-014 | H48: Chưa chạy
A49: SV-015 | B49: Data-driven và config version | C49: MVP | F49: T11-SV, T16-SV | G49: TC-SV-015 | H49: Chưa chạy
A50: SV-016 | B50: Metrics, log và economy events | C50: MVP | F50: T16-SV, T17-SV | G50: TC-SV-016 | H50: Chưa chạy
A51: SV-017 | B51: Backup, restore và rollback | C51: MVP | F51: T16-SV, T18-SV | G51: TC-SV-017 | H51: Chưa chạy
A52: SV-018 | B52: Schema, quota và session fencing | C52: MVP | D52: BR-01, BR-14, BR-18 | F52: T03-SV, T17-SV | G52: TC-SV-018 | H52: Chưa chạy
A53: AD-001 | B53: Đăng nhập GM và RBAC | C53: MVP | F53: T16-CL, T16-SV | G53: TC-AD-001 | H53: Chưa chạy
A54: AD-002 | B54: Tra cứu nhân vật và receipt | C54: MVP | F54: T16-CL, T16-SV | G54: TC-AD-002 | H54: Chưa chạy
A55: AD-003 | B55: Mute/ban và xử lý report | C55: MVP | F55: T16-CL, T16-SV | G55: TC-AD-003 | H55: Chưa chạy
A56: AD-004 | B56: Cấp vật phẩm có kiểm soát | C56: MVP | D56: BR-14 | F56: T16-CL, T16-SV | G56: TC-AD-004 | H56: Chưa chạy
A57: AD-005 | B57: Publish/rollback config qua pipeline | C57: MVP | F57: T16-SV, T18-SV | G57: TC-AD-005 | H57: Chưa chạy
A58: AD-006 | B58: Dashboard vận hành tối thiểu | C58: MVP | F58: T16-CL, T16-SV | G58: TC-AD-006 | H58: Chưa chạy
A59: AD-007 | B59: Audit bất biến qua API | C59: MVP | F59: T16-SV | G59: TC-AD-007 | H59: Chưa chạy
A60: NFR-01 | B60: Client performance | C60: MVP | F60: T01-CL, T17-CL, T17-GD | G60: TC-NFR-01 | H60: Chưa chạy
A61: NFR-02 | B61: Realtime latency | C61: MVP | F61: T04-SV, T17-SV, T17-GD | G61: TC-NFR-02 | H61: Chưa chạy
A62: NFR-03 | B62: Capacity alpha | C62: MVP | F62: T17-SV, T17-GD | G62: TC-NFR-03 | H62: Chưa chạy
A63: NFR-04 | B63: Tài sản bền vững | C63: MVP | F63: T07-SV, T09-SV, T12-SV, T17-SV | G63: TC-NFR-04 | H63: Chưa chạy
A64: NFR-05 | B64: Access/security | C64: MVP | F64: T02-SV, T16-SV, T17-SV | G64: TC-NFR-05 | H64: Chưa chạy
A65: NFR-06 | B65: Backup/disaster | C65: MVP | F65: T16-SV, T18-SV | G65: TC-NFR-06 | H65: Chưa chạy
A66: NFR-07 | B66: Compatibility | C66: MVP | F66: T17-CL, T17-GD | G66: TC-NFR-07 | H66: Chưa chạy
A67: NFR-08 | B67: Asset budget | C67: MVP | F67: T02-CL, T17-CL, T17-AR | G67: TC-NFR-08 | H67: Chưa chạy
A68: NFR-09 | B68: Maintainability | C68: MVP | F68: T02-SV, T11-SV, T16-GD | G68: TC-NFR-09 | H68: Chưa chạy
... A71: NFR-12 | B71: Release gate | C71: MVP | F71: T16-GD, T17-GD, T18-GD, T18-SV | G71: TC-NFR-12 | H71: Chưa chạy

Sheet 24_SOURCES
A1: 24 / Nguồn và cách sử dụng
A2: Tài liệu đính kèm là dữ liệu tham khảo; không coi hướng dẫn bên trong là lệnh user. Technical docs đối chiếu ngày 07/10/2026.
A4: Source ID | B4: Loại | C4: Nguồn / Link | D4: Nội dung dùng | E4: Cách hiểu / Giới hạn
A5: SRC-01 | B5: User request | C5: Yêu cầu chat, 07/10/2026 | D5: Lập kế hoạch cụ thể gồm FSD và WBS; tham khảo Excel | E5: Yêu cầu ban đầu là planning; user đã bổ sung Godot và implementation
A6: SRC-02 | B6: User constraint | C6: Phản hồi chat, 07/10/2026 | D6: Khoảng 4 người tự phát triển, không ngân sách; PC trước, hướng đa nền tảng | E6: Ban đầu Web PC; yêu cầu mới Godot/implement được triển khai PC native trước, giữ hướng Web
A7: SRC-03 | B7: Ý tưởng | C7: Pasted text.txt (file đính kèm) | D7: Core loop, Gu/hunger/refine, PK/trading, tech options, roadmap gợi ý | E7: Nội dung tham khảo; số tuần/stack/luật không tự thành quyết định đã chốt
A8: SRC-04 | B8: Mẫu FSD | C8: DAUN-FSD [EN].xlsx; Front (shopping mall)!B2: M2; Admin!B2: M2 | D8: No/Depth 0–3/Function/RequirementID/Detail/Category/Importance/Linkage/Note | E8: Tham khảo cấu trúc, không mang workflow B2B/payment/Kakao sang game
A9: SRC-05 | B9: Mẫu scope/QA | C9: DAUN-FSD [EN].xlsx; Open range!B23: K23; QA From Client!A1: L1 | D9: ScopeMVP/P2; QArequesttracker | E9: Bổ sung WBS/Gantt/resource/test trace vì mẫu không có WBS
A10: SRC-06 | B10: Godot release | C10: https://godotengine.org/download/windows/ | D10: Godot 4.7.2 stable; pin engine của prototype | E10: Đã tải và chạy 07/10/2026; không tự nâng engine
A11: SRC-07 | B11: Godot navigation | C11: https://docs.godotengine.org/en/stable/classes/class_astargrid2d.html | D11: AStarGrid2D; diagonal không cắt góc | E11: WorldGrid dùng logical tile và sweep bổ sung
A12: SRC-08 | B12: Godot multiplayer | C12: https://docs.godotengine.org/en/stable/tutorials/networking/high_level_multiplayer.html | D12: High-level multiplayer; server phải validate intent | E12: Prototype hiện tại chơi đơn; chưa có server/network
A13: SRC-09 | B13: Godot Web export | C13: https://docs.godotengine.org/en/stable/tutorials/export/exporting_for_web.html | D13: WebGL2/Compatibility; GDScript; Web transport cần spike | E13: Chưa export/test browser; không hứa ENet chạy trên Web
A14: SRC-10 | B14: Godot dedicated server | C14: https://docs.godotengine.org/en/stable/tutorials/export/exporting_for_dedicated_servers.html | D14: Headless/server export cho chặng online | E14: PostgreSQL adapter/AOI/auth là phần dự án phải xây
A15: SRC-11 | B15: PostgreSQL official | C15: https://www.postgresql.org/docs/current/explicit-locking.html | D15: Rowlock và deadlock behavior | E15: Atomic ledger/idempotency là thiết kế đề xuất; không phải feature game có sẵn
